Workbook

Sheet CLIENTES ACTIVOS
A1: Ejecutivo | B1: Nombre Cliente | C1: Merchant ID | D1: Creado en CRM | E1: Mes Año | F1: Fecha de activacion | G1: Mes | H1: Año | I1: ORIGEN del Cliente | J1: Si es referido Correo electronico De quien refiere de no ser asi dejar N/A | K1: TPV Potencial en MIllones | L1: Tarifa Aplicada | M1: DATAFONOS | N1: QR-LINK-BOTON | O1: CONTRATOS FRAUDE | P1: CONTRATOS | Q1: TPV M0 | R1: TPV M1 | S1: TPV M2 | T1: TPV M3 | U1: PROMEDIO TPV | V1: Se entrega a CS | W1: KAM que recibe Comercio
A2: jhonatan.torres@bold.co | B2: Ferrelectric El Proveedor | C2: OTT8ZA91GS | D2: Si | E2: =TEXT(F2, "mmmm yyyy") -> enero 2024 | F2: 45296 | G2: =F2 -> 45296 | H2: =G2 -> 45296 | I2: SI | J2: luis.castellar@bold.co | K2: 50000000 | L2: 2,19 +300 | Q2: =VLOOKUP(C2,QS!E:AB,21,0) -> #REF! | R2: =VLOOKUP(C2,QS!E:AB,22,0) -> #REF! | S2: =VLOOKUP(C2,QS!E:AB,23,0) -> #REF! | T2: =VLOOKUP(C2,QS!E:AB,24,0) -> #REF!
A3: juan.salgado@bold.co | B3: JANGUEO CARTAGENA | C3: LWU5FIZZPX | D3: Si | E3: =TEXT(F3, "mmmm yyyy") -> enero 2024 | F3: 45303 | G3: =F3 -> 45303 | H3: =G3 -> 45303 | I3: SI | J3: Estefanía.torres@bold.co | K3: 50000000 | L3: 2,19+$300 | P3: Pendientes | Q3: =VLOOKUP(C3,QS!E:AB,21,0) -> #REF! | R3: =VLOOKUP(C3,QS!E:AB,22,0) -> #REF! | S3: =VLOOKUP(C3,QS!E:AB,23,0) -> #REF! | T3: =VLOOKUP(C3,QS!E:AB,24,0) -> #REF!
A4: jhonatan.moreno@bold.co | B4: Majestic burgers | C4: 7IW47CWHLA | D4: Si | E4: =TEXT(F4, "mmmm yyyy") -> enero 2024 | F4: 45306 | G4: =F4 -> 45306 | H4: =G4 -> 45306 | I4: Referido Outbound | J4: jaime.barrios@bold.co | K4: 150000000 | L4: 2,19+$300 | P4: Si | Q4: =VLOOKUP(C4,QS!E:AB,21,0) -> #REF! | R4: =VLOOKUP(C4,QS!E:AB,22,0) -> #REF! | S4: =VLOOKUP(C4,QS!E:AB,23,0) -> #REF! | T4: =VLOOKUP(C4,QS!E:AB,24,0) -> #REF!
A5: jhonatan.moreno@bold.co | B5: caribean team | C5: PM6BZ0OM41 | D5: Si | E5: =TEXT(F5, "mmmm yyyy") -> enero 2024 | F5: 45308 | G5: =F5 -> 45308 | H5: =G5 -> 45308 | I5: Referido Outbound | J5: jaime.barrios@bold.co | L5: 2,19+$300 | P5: Si | Q5: =VLOOKUP(C5,QS!E:AB,21,0) -> #REF! | R5: =VLOOKUP(C5,QS!E:AB,22,0) -> #REF! | S5: =VLOOKUP(C5,QS!E:AB,23,0) -> #REF! | T5: =VLOOKUP(C5,QS!E:AB,24,0) -> #REF!
A6: jhonatan.moreno@bold.co | B6: Tolifruver | C6: V2D10H30A6 | D6: Si | E6: =TEXT(F6, "mmmm yyyy") -> enero 2024 | F6: 45308 | G6: =F6 -> 45308 | H6: =G6 -> 45308 | I6: Cliente Propio | K6: 40000000 | L6: 2,39 + 300 | Q6: =VLOOKUP(C6,QS!E:AB,21,0) -> #REF! | R6: =VLOOKUP(C6,QS!E:AB,22,0) -> #REF! | S6: =VLOOKUP(C6,QS!E:AB,23,0) -> #REF! | T6: =VLOOKUP(C6,QS!E:AB,24,0) -> #REF!
A7: angel.lesmes@bold.co | B7: Manns Design | C7: W9Y4L8F4N2 | D7: Si | E7: =TEXT(F7, "mmmm yyyy") -> enero 2024 | F7: 45309 | G7: =F7 -> 45309 | H7: =G7 -> 45309 | K7: 30000000 | L7: 2,89+300 | Q7: =VLOOKUP(C7,QS!E:AB,21,0) -> #REF! | R7: =VLOOKUP(C7,QS!E:AB,22,0) -> #REF! | S7: =VLOOKUP(C7,QS!E:AB,23,0) -> #REF! | T7: =VLOOKUP(C7,QS!E:AB,24,0) -> #REF!
A8: jhonatan.moreno@bold.co | B8: Macro pollos | C8: AYILZWWK0P | D8: Si | E8: =TEXT(F8, "mmmm yyyy") -> enero 2024 | F8: 45316 | G8: =F8 -> 45316 | H8: =G8 -> 45316 | I8: Referido Outbound | J8: andres.cardozo@bold.co | K8: 20000000 | L8: 2,29+300 | P8: Si | Q8: =VLOOKUP(C8,QS!E:AB,21,0) -> #REF! | R8: =VLOOKUP(C8,QS!E:AB,22,0) -> #REF! | S8: =VLOOKUP(C8,QS!E:AB,23,0) -> #REF! | T8: =VLOOKUP(C8,QS!E:AB,24,0) -> #REF!
A9: luis.corredor@bold.co | B9: Sofiian Cedritos | C9: ARYDJSNS2X | D9: Si | E9: =TEXT(F9, "mmmm yyyy") -> enero 2024 | F9: 45316 | G9: =F9 -> 45316 | H9: =G9 -> 45316 | I9: Cliente Propio | K9: 35000000 | L9: 2,19 +300 | Q9: =VLOOKUP(C9,QS!E:AB,21,0) -> #REF! | R9: =VLOOKUP(C9,QS!E:AB,22,0) -> #REF! | S9: =VLOOKUP(C9,QS!E:AB,23,0) -> #REF! | T9: =VLOOKUP(C9,QS!E:AB,24,0) -> #REF!
A10: luis.corredor@bold.co | B10: Veolia | C10: D9BBCAUZRK | D10: Si | E10: =TEXT(F10, "mmmm yyyy") -> enero 2024 | F10: 45316 | G10: =F10 -> 45316 | H10: =G10 -> 45316 | I10: Cliente Propio | J10: lorena.oviedo@bold.co | K10: 150000000 | L10: 2.19 | P10: Pendientes | Q10: =VLOOKUP(C10,QS!E:AB,21,0) -> #REF! | R10: =VLOOKUP(C10,QS!E:AB,22,0) -> #REF! | S10: =VLOOKUP(C10,QS!E:AB,23,0) -> #REF! | T10: =VLOOKUP(C10,QS!E:AB,24,0) -> #REF!
A11: jhonatan.torres@bold.co | B11: DECORADOS Y ACABADOS CERMAMICOS | C11: MLSOQIAORD | D11: Si | E11: =TEXT(F11, "mmmm yyyy") -> enero 2024 | F11: 45316 | G11: =F11 -> 45316 | H11: =G11 -> 45316 | I11: No | K11: 200000000 | L11: 1.99 | P11: Pendientes | Q11: =VLOOKUP(C11,QS!E:AB,21,0) -> #REF! | R11: =VLOOKUP(C11,QS!E:AB,22,0) -> #REF! | S11: =VLOOKUP(C11,QS!E:AB,23,0) -> #REF! | T11: =VLOOKUP(C11,QS!E:AB,24,0) -> #REF!
A12: jhonatan.moreno@bold.co | B12: BEYROUTH 93 | C12: ZBFT9JBRNT | D12: Si | E12: =TEXT(F12, "mmmm yyyy") -> enero 2024 | F12: 45317 | G12: =F12 -> 45317 | H12: =G12 -> 45317 | I12: Referido Outbound | J12: margareth.arias@bold.co | K12: 200000000 | L12: 2.05 | Q12: =VLOOKUP(C12,QS!E:AB,21,0) -> #REF! | R12: =VLOOKUP(C12,QS!E:AB,22,0) -> #REF! | S12: =VLOOKUP(C12,QS!E:AB,23,0) -> #REF! | T12: =VLOOKUP(C12,QS!E:AB,24,0) -> #REF!
A13: luis.corredor@bold.co | B13: CASSARENA | C13: W06BXLMD3C | D13: Si | E13: =TEXT(F13, "mmmm yyyy") -> enero 2024 | F13: 45318 | G13: =F13 -> 45318 | H13: =G13 -> 45318 | I13: SI | J13: andres.cardozo@bold.co | K13: 100000000 | L13: 2,19+300 | P13: Si | Q13: =VLOOKUP(C13,QS!E:AB,21,0) -> #REF! | R13: =VLOOKUP(C13,QS!E:AB,22,0) -> #REF! | S13: =VLOOKUP(C13,QS!E:AB,23,0) -> #REF! | T13: =VLOOKUP(C13,QS!E:AB,24,0) -> #REF!
A14: jhonatan.moreno@bold.co | B14: ALFAPARF | C14: VOG2HUW5VO | D14: Si | E14: =TEXT(F14, "mmmm yyyy") -> febrero 2024 | F14: 45323 | G14: =F14 -> 45323 | H14: =G14 -> 45323 | I14: Cliente Propio | K14: 250000000 | L14: 2,19+$300 | Q14: =VLOOKUP(C14,QS!E:AB,21,0) -> #REF! | R14: =VLOOKUP(C14,QS!E:AB,22,0) -> #REF! | S14: =VLOOKUP(C14,QS!E:AB,23,0) -> #REF! | T14: =VLOOKUP(C14,QS!E:AB,24,0) -> #REF!
A15: jhonatan.moreno@bold.co | B15: Surubi Food | C15: VIFU5YJBTM | D15: Si | E15: =TEXT(F15, "mmmm yyyy") -> febrero 2024 | F15: 45324 | G15: =F15 -> 45324 | H15: =G15 -> 45324 | I15: Referido Outbound | J15: jaime.barrios@bold.co | K15: 100000000 | L15: 2,19+$300 | P15: Si | Q15: =VLOOKUP(C15,QS!E:AB,21,0) -> #REF! | R15: =VLOOKUP(C15,QS!E:AB,22,0) -> #REF! | S15: =VLOOKUP(C15,QS!E:AB,23,0) -> #REF! | T15: =VLOOKUP(C15,QS!E:AB,24,0) -> #REF!
A16: luis.corredor@bold.co | B16: Miguel Burger | C16: DQDQKMENXA | D16: Si | E16: =TEXT(F16, "mmmm yyyy") -> febrero 2024 | F16: 45324 | G16: =F16 -> 45324 | H16: =G16 -> 45324 | I16: No | K16: 160000000 | L16: 2,09+$100 | P16: Si | Q16: =VLOOKUP(C16,QS!E:AB,21,0) -> #REF! | R16: =VLOOKUP(C16,QS!E:AB,22,0) -> #REF! | S16: =VLOOKUP(C16,QS!E:AB,23,0) -> #REF! | T16: =VLOOKUP(C16,QS!E:AB,24,0) -> #REF!
A17: angel.lesmes@bold.co | B17: Restaurante Musashi | C17: QKCESKPA91 | D17: Si | E17: =TEXT(F17, "mmmm yyyy") -> febrero 2024 | F17: 45336 | G17: =F17 -> 45336 | H17: =G17 -> 45336 | I17: No | K17: 20000000 | L17: 2,19% + $300 | P17: Pendientes | Q17: =VLOOKUP(C17,QS!E:AB,21,0) -> #REF! | R17: =VLOOKUP(C17,QS!E:AB,22,0) -> #REF! | S17: =VLOOKUP(C17,QS!E:AB,23,0) -> #REF! | T17: =VLOOKUP(C17,QS!E:AB,24,0) -> #REF!
A18: angel.lesmes@bold.co | B18: Restaurante Musashi | C18: YE6RMJFK6K | D18: Si | E18: =TEXT(F18, "mmmm yyyy") -> febrero 2024 | F18: 45336 | G18: =F18 -> 45336 | H18: =G18 -> 45336 | I18: No | K18: 20000000 | L18: 2,19% + $300 | P18: Pendientes | Q18: =VLOOKUP(C18,QS!E:AB,21,0) -> #REF! | R18: =VLOOKUP(C18,QS!E:AB,22,0) -> #REF! | S18: =VLOOKUP(C18,QS!E:AB,23,0) -> #REF! | T18: =VLOOKUP(C18,QS!E:AB,24,0) -> #REF!
A19: jhonatan.torres@bold.co | B19: Artesanal | C19: YEY17SS4UP | D19: Si | E19: =TEXT(F19, "mmmm yyyy") -> febrero 2024 | F19: 45336 | G19: =F19 -> 45336 | H19: =G19 -> 45336 | I19: Referido Outbound | J19: luis.correa@bold.co | K19: 100000000 | L19: 2,19% + $300 | Q19: =VLOOKUP(C19,QS!E:AB,21,0) -> #REF! | R19: =VLOOKUP(C19,QS!E:AB,22,0) -> #REF! | S19: =VLOOKUP(C19,QS!E:AB,23,0) -> #REF! | T19: =VLOOKUP(C19,QS!E:AB,24,0) -> #REF!
A20: angel.lesmes@bold.co | B20: Almacén Y Taller Todo Nissan Ayt Sas | C20: VTCXH9AYXO | D20: Si | E20: =TEXT(F20, "mmmm yyyy") -> febrero 2024 | F20: 45337 | G20: =F20 -> 45337 | H20: =G20 -> 45337 | I20: Cliente Propio | K20: 50000000 | L20: 2,19% + $300 | P20: Pendientes | Q20: =VLOOKUP(C20,QS!E:AB,21,0) -> #REF! | R20: =VLOOKUP(C20,QS!E:AB,22,0) -> #REF! | S20: =VLOOKUP(C20,QS!E:AB,23,0) -> #REF! | T20: =VLOOKUP(C20,QS!E:AB,24,0) -> #REF!
A21: cristian.baquero@bold.co | B21: Acabados dyp | C21: CGTPT8L3DG | D21: Si | E21: =TEXT(F21, "mmmm yyyy") -> febrero 2024 | F21: 45332 | G21: =F21 -> 45332 | H21: =G21 -> 45332 | I21: Cliente Propio | K21: 30000000 | L21: 2,19% + $300 | Q21: =VLOOKUP(C21,QS!E:AB,21,0) -> #REF! | R21: =VLOOKUP(C21,QS!E:AB,22,0) -> #REF! | S21: =VLOOKUP(C21,QS!E:AB,23,0) -> #REF! | T21: =VLOOKUP(C21,QS!E:AB,24,0) -> #REF!
A22: cristian.baquero@bold.co | B22: Dukari | C22: CBL16SJULR | D22: Si | E22: =TEXT(F22, "mmmm yyyy") -> febrero 2024 | F22: 45334 | G22: =F22 -> 45334 | H22: =G22 -> 45334 | I22: Cliente Propio | K22: 50000000 | L22: 2,59% + $900 (solo Link) | Q22: 482000 | R22: =VLOOKUP(C22,QS!E:AB,22,0) -> #REF! | S22: =VLOOKUP(C22,QS!E:AB,23,0) -> #REF! | T22: =VLOOKUP(C22,QS!E:AB,24,0) -> #REF!
A23: cristian.baquero@bold.co | B23: Lebog | C23: EO5ZB49DG2 | D23: Si | E23: =TEXT(F23, "mmmm yyyy") -> febrero 2024 | F23: 45336 | G23: =F23 -> 45336 | H23: =G23 -> 45336 | I23: Cliente Propio | K23: 50000000 | L23: 2,19% + $300 | Q23: =VLOOKUP(C23,QS!E:AB,21,0) -> #REF! | R23: =VLOOKUP(C23,QS!E:AB,22,0) -> #REF! | S23: =VLOOKUP(C23,QS!E:AB,23,0) -> #REF! | T23: =VLOOKUP(C23,QS!E:AB,24,0) -> #REF!
A24: cristian.baquero@bold.co | B24: Foodology | C24: OFC2I4Z2PO | D24: Si | E24: =TEXT(F24, "mmmm yyyy") -> febrero 2024 | F24: 45342 | G24: =F24 -> 45342 | H24: =G24 -> 45342 | I24: Referido Outbound | J24: cristian.casas@bold.co | K24: 600000000 | L24: 0.0199 | P24: Pendientes | Q24: =VLOOKUP(C24,QS!E:AB,21,0) -> #REF! | R24: =VLOOKUP(C24,QS!E:AB,22,0) -> #REF! | S24: =VLOOKUP(C24,QS!E:AB,23,0) -> #REF! | T24: =VLOOKUP(C24,QS!E:AB,24,0) -> #REF!
A25: angel.lesmes@bold.co | B25: Medina Golden | C25: DUJE9XZH3Q | D25: Si | E25: =TEXT(F25, "mmmm yyyy") -> febrero 2024 | F25: 45345 | G25: =F25 -> 45345 | H25: =G25 -> 45345 | I25: Cliente Propio | K25: 100000000 | L25: 1.99 | P25: Pendientes | Q25: =VLOOKUP(C25,QS!E:AB,21,0) -> #REF! | R25: =VLOOKUP(C25,QS!E:AB,22,0) -> #REF! | S25: =VLOOKUP(C25,QS!E:AB,23,0) -> #REF! | T25: =VLOOKUP(C25,QS!E:AB,24,0) -> #REF!
A26: luis.corredor@bold.co | B26: Beef PuraRaza | C26: NY6646ULTO | D26: Si | E26: =TEXT(F26, "mmmm yyyy") -> febrero 2024 | F26: 45345 | G26: =F26 -> 45345 | H26: =G26 -> 45345 | I26: Referido Spiders | J26: angie.rodriguez@bold.co | K26: 150000000 | L26: 2,09+$100 | P26: Si | Q26: =VLOOKUP(C26,QS!E:AB,21,0) -> #REF! | R26: =VLOOKUP(C26,QS!E:AB,22,0) -> #REF! | S26: =VLOOKUP(C26,QS!E:AB,23,0) -> #REF! | T26: =VLOOKUP(C26,QS!E:AB,24,0) -> #REF!
A27: jhonatan.moreno@bold.co | B27: LA FINCA DE RIGOLLANOGRANDE | C27: 1AG1WY7CSP | D27: Si | E27: =TEXT(F27, "mmmm yyyy") -> marzo 2024 | F27: 45352 | G27: =F27 -> 45352 | H27: =G27 -> 45352 | I27: Referido Spiders | J27: angie.rodriguez@bold.co | K27: 200000000 | P27: Pendientes
A28: jhonatan.moreno@bold.co | B28: GO RIGO GO PALMAS | C28: 3F86R9UN91 | D28: Si | E28: =TEXT(F28, "mmmm yyyy") -> marzo 2024 | F28: 45352 | G28: =F28 -> 45352 | H28: =G28 -> 45352 | I28: Referido Spiders | J28: sandra.robayo@bold.co | K28: 200000000 | P28: Pendientes
A29: luis.corredor@bold.co | B29: Zona cafe y pan | C29: C2T5G954F1 | D29: Si | E29: =TEXT(F29, "mmmm yyyy") -> marzo 2024 | F29: 45352 | G29: =F29 -> 45352 | H29: =G29 -> 45352 | I29: Referido Spiders | J29: nazareth.ruiz@bold.co | K29: 40000000 | L29: 2,19% + $300
A30: angel.lesmes@bold.co | B30: Mi Tierra | C30: T0EM6PSD79 | D30: Si | E30: =TEXT(F30, "mmmm yyyy") -> marzo 2024 | F30: 45352 | G30: =F30 -> 45352 | H30: =G30 -> 45352 | I30: Referido Spiders | J30: milton.ortiz@bold.co | K30: 50000000 | L30: 2,19% + $300
A31: jhonatan.moreno@bold.co | B31: GRACIES | C31: PQFEX2AY4O | D31: Si | E31: =TEXT(F31, "mmmm yyyy") -> marzo 2024 | F31: 45355 | G31: =F31 -> 45355 | H31: =G31 -> 45355 | I31: Cliente Propio | K31: 80000000 | L31: 2.19
A32: jhonatan.moreno@bold.co | B32: COLTOLIMA | C32: KUQFCYOJ5F | D32: Si | E32: =TEXT(F32, "mmmm yyyy") -> marzo 2024 | F32: 45355 | G32: =F32 -> 45355 | H32: =G32 -> 45355 | I32: Cliente Propio | P32: Pendientes
A33: luis.corredor@bold.co | B33: Veolia Archipiélago sas esp | C33: YO5Y2NTPRY | D33: Si | E33: =TEXT(F33, "mmmm yyyy") -> marzo 2024 | F33: 45355 | G33: =F33 -> 45355 | H33: =G33 -> 45355 | I33: Referido Outbound | J33: edwar.sinisterra@bold.co | K33: 150000000 | L33: 2.19 | P33: Revision
A34: cristian.baquero@bold.co | B34: Rosalba Sanchez | C34: 1MEOXAZD4L | D34: Si | E34: =TEXT(F34, "mmmm yyyy") -> marzo 2024 | F34: 45356 | G34: =F34 -> 45356 | H34: =G34 -> 45356 | I34: Referido Spiders | J34: angie.rodriguez@bold.co | K34: 80000000 | L34: 2,19 + $300 | P34: Pendientes
A35: cristian.baquero@bold.co | B35: VFS Colombia SAS | C35: W522Q392Y7 | D35: Si | E35: =TEXT(F35, "mmmm yyyy") -> marzo 2024 | F35: 45356 | G35: =F35 -> 45356 | H35: =G35 -> 45356 | I35: Referido Spiders | J35: milton.ortiz@bold.co | K35: 400000000 | L35: 0.0199 | P35: Pendientes
A36: cristian.baquero@bold.co | B36: VFS Colombia SAS | C36: PZKOSYJEEO | D36: Si | E36: =TEXT(F36, "mmmm yyyy") -> marzo 2024 | F36: 45356 | G36: =F36 -> 45356 | H36: =G36 -> 45356 | I36: Referido Spiders | J36: milton.ortiz@bold.co | K36: 400000000 | L36: 0.0199 | P36: Pendientes
A37: cristian.baquero@bold.co | B37: VFS Colombia SAS | C37: W636X85VHW | D37: Si | E37: =TEXT(F37, "mmmm yyyy") -> marzo 2024 | F37: 45356 | G37: =F37 -> 45356 | H37: =G37 -> 45356 | I37: Referido Spiders | J37: milton.ortiz@bold.co | K37: 400000000 | L37: 0.0199 | P37: Pendientes
A38: jhonatan.moreno@bold.co | B38: German Summa | C38: 0NAMJ65HII | D38: Si | E38: =TEXT(F38, "mmmm yyyy") -> marzo 2024 | F38: 45363 | G38: =F38 -> 45363 | H38: =G38 -> 45363 | I38: Cliente Propio | K38: 40000000
A39: luis.corredor@bold.co | B39: Combos cosmicos portal 80 | C39: OFZJDWZPTJ | D39: Si | E39: =TEXT(F39, "mmmm yyyy") -> marzo 2024 | F39: 45363 | G39: =F39 -> 45363 | H39: =G39 -> 45363 | I39: Cliente Propio | K39: 30000000 | L39: 2,19 + $300
A40: jhonatan.moreno@bold.co | B40: Atractiva Calzados | C40: TP4LNEUN1M | D40: Si | E40: =TEXT(F40, "mmmm yyyy") -> marzo 2024 | F40: 45365 | G40: =F40 -> 45365 | H40: =G40 -> 45365 | I40: Cliente Propio | K40: 30000000 | L40: 2,19 + $300
A41: cristian.baquero@bold.co | B41: HH innovación y fabricación | C41: 0KN0WI1S9F | D41: Si | E41: =TEXT(F41, "mmmm yyyy") -> marzo 2024 | F41: 45364 | G41: =F41 -> 45364 | H41: =G41 -> 45364 | K41: 30000000 | L41: 2,59 + $300
A42: jhonatan.moreno@bold.co | B42: La meca | C42: ATLO1FBHKN | D42: Si | E42: =TEXT(F42, "mmmm yyyy") -> marzo 2024 | F42: 45365 | G42: =F42 -> 45365 | H42: =G42 -> 45365 | I42: Referido Spiders | J42: milton.ortiz@bold.co | K42: 30000000 | L42: 2,19 + $300
A43: jhonatan.moreno@bold.co | B43: PM Burger Boliva | C43: OQ7TIDV5MD | D43: Si | E43: =TEXT(F43, "mmmm yyyy") -> marzo 2024 | F43: 45366 | G43: =F43 -> 45366 | H43: =G43 -> 45366 | I43: Referido Spiders | J43: milton.ortiz@bold.co | K43: 40000000 | L43: 2,19 + $300
A44: jhonatan.moreno@bold.co | B44: Bacanal | C44: 372E652JMS | D44: Si | E44: =TEXT(F44, "mmmm yyyy") -> marzo 2024 | F44: 45366 | G44: =F44 -> 45366 | H44: =G44 -> 45366 | I44: Referido Spiders | J44: milton.ortiz@bold.co | K44: 0 | L44: 2,19 + $300
A45: jhonatan.moreno@bold.co | B45: Pablo y Maria Burger Brothers | C45: GQVPXX6V8G | D45: Si | E45: =TEXT(F45, "mmmm yyyy") -> marzo 2024 | F45: 45366 | G45: =F45 -> 45366 | H45: =G45 -> 45366 | I45: Referido Spiders | J45: milton.ortiz@bold.co | K45: 0 | L45: 2,19 + $300
A46: jhonatan.torres@bold.co | B46: La Ruana | C46: SJN7XJ8236 | D46: Si | E46: =TEXT(F46, "mmmm yyyy") -> marzo 2024 | F46: 45371 | G46: =F46 -> 45371 | H46: =G46 -> 45371 | I46: Referido Spiders | J46: milton.ortiz@bold.co | K46: 80000000 | L46: 0.0219
A47: angel.lesmes@bold.co | B47: CONSTRUCERAMICAS COLOMBIA SAS | C47: 45E8YNVYMM | D47: Si | E47: =TEXT(F47, "mmmm yyyy") -> abril 2024 | F47: 45383 | G47: =F47 -> 45383 | H47: =G47 -> 45383 | I47: Referido Inbound | J47: ana.reyes@bold.co | K47: 700000000 | L47: 0.0169 | P47: Si
A48: jhonatan.moreno@bold.co | B48: Scarpy Portal 80 | C48: 5AVCGZK2P8 | D48: Si | E48: =TEXT(F48, "mmmm yyyy") -> abril 2024 | F48: 45386 | G48: =F48 -> 45386 | H48: =G48 -> 45386 | I48: Cliente Propio | K48: 30000000 | L48: 2,19 + $300
A49: jhonatan.torres@bold.co | B49: AMC Odontologia | C49: 442EGE688O | D49: Si | E49: =TEXT(F49, "mmmm yyyy") -> abril 2024 | F49: 45386 | G49: =F49 -> 45386 | H49: =G49 -> 45386 | I49: Referido Spiders | J49: milton.ortiz@bold.co | K49: 25000000 | L49: 2.29%
A50: jhonatan.torres@bold.co | B50: AMC Odontologia | C50: 9AR1MMWV5A | D50: Si | E50: =TEXT(F50, "mmmm yyyy") -> abril 2024 | F50: 45386 | G50: =F50 -> 45386 | H50: =G50 -> 45386 | I50: Referido Spiders | J50: milton.ortiz@bold.co | K50: 25000000 | L50: 2.29%
B51: Ichiraku Chia | C51: TXFEH92VFO | D51: Si | E51: =TEXT(F51, "mmmm yyyy") -> abril 2024 | F51: 45387 | G51: =F51 -> 45387 | H51: =G51 -> 45387 | I51: Cliente Propio | K51: 100000000 | L51: 0.0189
A52: angel.lesmes@bold.co | B52: Perros JR | C52: VPRNTGJCB2 | D52: Si | E52: =TEXT(F52, "mmmm yyyy") -> abril 2024 | F52: 45391 | G52: =F52 -> 45391 | H52: =G52 -> 45391 | I52: Referido Spiders | J52: angie.rodriguez@bold.co | K52: 50000000 | L52: 2,09%+$100 | P52: Pendientes
A53: angel.lesmes@bold.co | B53: Perros JR | C53: 0JO6SWOPF5 | D53: Si | E53: =TEXT(F53, "mmmm yyyy") -> abril 2024 | F53: 45391 | G53: =F53 -> 45391 | H53: =G53 -> 45391 | I53: Referido Spiders | J53: angie.rodriguez@bold.co | K53: 50000000 | L53: 2,09%+$100 | P53: Pendientes
A54: angel.lesmes@bold.co | B54: Perros JR | C54: SNM2QGYKAJ | D54: Si | E54: =TEXT(F54, "mmmm yyyy") -> abril 2024 | F54: 45391 | G54: =F54 -> 45391 | H54: =G54 -> 45391 | I54: Referido Spiders | J54: angie.rodriguez@bold.co | K54: 50000000 | L54: 2,09%+$100 | P54: Pendientes
A55: angel.lesmes@bold.co | B55: Perros JR | C55: VI2AZEVQ73 | D55: Si | E55: =TEXT(F55, "mmmm yyyy") -> abril 2024 | F55: 45391 | G55: =F55 -> 45391 | H55: =G55 -> 45391 | I55: Referido Spiders | J55: angie.rodriguez@bold.co | K55: 50000000 | L55: 2,09%+$100 | P55: Pendientes
A56: cristian.baquero@bold.co | B56: Aroma Resto Bar SAS | C56: WZGSPR0JXV | D56: Si | E56: =TEXT(F56, "mmmm yyyy") -> abril 2024 | F56: 45387 | G56: =F56 -> 45387 | H56: =G56 -> 45387 | I56: Cliente Propio | K56: 100000000 | L56: 0.0219
A57: jhonatan.moreno@bold.co | B57: Ricasole | C57: X4JIGATJGL | D57: Si | E57: =TEXT(F57, "mmmm yyyy") -> abril 2024 | F57: 45393 | G57: =F57 -> 45393 | H57: =G57 -> 45393 | I57: Cliente Propio | K57: 50000000 | L57: 2,19 + 300 | P57: Pendientes
A58: cristian.baquero@bold.co | B58: Ililaserdent | C58: H4DQ3W9NLM | D58: Si | E58: =TEXT(F58, "mmmm yyyy") -> abril 2024 | F58: 45394 | G58: =F58 -> 45394 | H58: =G58 -> 45394 | I58: Referido Spiders | J58: nazareth.ruiz@bold.co | K58: 50000000 | L58: 2,19 % + $ 300
A59: cristian.baquero@bold.co | B59: Thai Station | C59: 4SFPMWKA6T | D59: Si | E59: =TEXT(F59, "mmmm yyyy") -> abril 2024 | F59: 45394 | G59: =F59 -> 45394 | H59: =G59 -> 45394 | I59: Cliente Propio | K59: 100000000 | L59: 2,09%+$100
A60: angel.lesmes@bold.co | B60: Imporcepo | C60: VFR0TAG2F7 | D60: Si | E60: =TEXT(F60, "mmmm yyyy") -> abril 2024 | F60: 45397 | G60: =F60 -> 45397 | H60: =G60 -> 45397 | I60: Referido Spiders | J60: nazareth.ruiz@bold.co | K60: 50000000 | L60: 2,59+300
A61: jhonatan.moreno@bold.co | B61: Monalisa | C61: 2XGLJL6ASW | D61: Si | E61: =TEXT(F61, "mmmm yyyy") -> abril 2024 | F61: 45400 | G61: =F61 -> 45400 | H61: =G61 -> 45400 | I61: Cliente Propio | K61: 40000000 | L61: 2.29
A62: jhonatan.moreno@bold.co | B62: Ichiraku Norte | C62: 5LSE5CTE6X | D62: Si | E62: =TEXT(F62, "mmmm yyyy") -> abril 2024 | F62: 45411 | G62: =F62 -> 45411 | H62: =G62 -> 45411 | I62: Cliente Propio | K62: 100000000 | L62: 0.0189 | P62: Pendientes
A63: jhonatan.moreno@bold.co | B63: Emme cafam floresta | C63: RMJJCNLKKI | D63: Si | E63: =TEXT(F63, "mmmm yyyy") -> abril 2024 | F63: 45412 | G63: =F63 -> 45412 | H63: =G63 -> 45412 | I63: Cliente Propio | K63: 30000000 | L63: 2,19 + 300
A64: jhonatan.moreno@bold.co | B64: Emme ensueno | C64: O63GT7UONQ | D64: Si | E64: =TEXT(F64, "mmmm yyyy") -> abril 2024 | F64: 45412 | G64: =F64 -> 45412 | H64: =G64 -> 45412 | I64: Cliente Propio | K64: 30000000 | L64: 2,19 + 300
A65: jhonatan.moreno@bold.co | B65: TOTAL SERVICE | C65: 9D25IUH6ZU | D65: Si | E65: =TEXT(F65, "mmmm yyyy") -> mayo 2024 | F65: 45414 | G65: =F65 -> 45414 | H65: =G65 -> 45414 | I65: Referido Spiders | J65: nazareth.ruiz@bold.co | K65: 40000000 | L65: 2.19
A66: jhonatan.moreno@bold.co | B66: La Bendita | C66: RA4XAW89EA | D66: Si | E66: =TEXT(F66, "mmmm yyyy") -> mayo 2024 | F66: 45414 | G66: =F66 -> 45414 | H66: =G66 -> 45414 | I66: Referido Spiders | J66: paula.ruiz@bold.co | K66: 150000000 | L66: 2.19
A67: jhonatan.moreno@bold.co | B67: Isla Corona (arrecife) | C67: V7F11RKN8F | D67: Si | E67: =TEXT(F67, "mmmm yyyy") -> mayo 2024 | F67: 45414 | G67: =F67 -> 45414 | H67: =G67 -> 45414 | I67: Referido Spiders | J67: paula.ruiz@bold.co | K67: 150000000 | L67: 2.19
A68: luis.corredor@bold.co | B68: wcar | C68: 9Q9H9V0QE5 | D68: Si | E68: =TEXT(F68, "mmmm yyyy") -> mayo 2024 | F68: 45414 | G68: =F68 -> 45414 | H68: =G68 -> 45414 | I68: Cliente Propio | K68: 70000000 | L68: 2.19
A69: luis.corredor@bold.co | B69: Mrscreativo | C69: VFP4AM2X8R | D69: Si | E69: =TEXT(F69, "mmmm yyyy") -> mayo 2024 | F69: 45414 | G69: =F69 -> 45414 | H69: =G69 -> 45414 | I69: Cliente Propio | K69: 20000000 | L69: 2,19 + 300
A70: jhonatan.torres@bold.co | B70: RAMGUIFLEX | C70: XBJD6EJPEE | D70: Si | E70: =TEXT(F70, "mmmm yyyy") -> mayo 2024 | F70: 45414 | G70: =F70 -> 45414 | H70: =G70 -> 45414 | I70: Cliente Propio | K70: 800000000 | L70: 1.60% | P70: Si
A71: jhonatan.moreno@bold.co | B71: SUBWAY | C71: 5LEB6JQ3ZX | D71: Si | E71: =TEXT(F71, "mmmm yyyy") -> mayo 2024 | F71: 45415 | G71: =F71 -> 45415 | H71: =G71 -> 45415 | I71: Referido Spiders | J71: nazareth.ruiz@bold.co | K71: 120000000 | L71: 1.99
A72: jhonatan.moreno@bold.co | B72: Urban | C72: X243MWK7PT | D72: Si | E72: =TEXT(F72, "mmmm yyyy") -> mayo 2024 | F72: 45415 | G72: =F72 -> 45415 | H72: =G72 -> 45415 | I72: Referido Spiders | J72: nazareth.ruiz@bold.co | K72: 30000000 | L72: 1.99
A73: jhonatan.moreno@bold.co | B73: Tortas del Gordo | C73: C6WTZMVXUJ | D73: Si | E73: =TEXT(F73, "mmmm yyyy") -> mayo 2024 | F73: 45416 | G73: =F73 -> 45416 | H73: =G73 -> 45416 | I73: Cliente Propio | K73: 90000000 | L73: 2.19
A74: jhonatan.moreno@bold.co | B74: Seoul medicina estetica | C74: J141IRHCAT | D74: Si | E74: =TEXT(F74, "mmmm yyyy") -> mayo 2024 | F74: 45420 | G74: =F74 -> 45420 | H74: =G74 -> 45420 | I74: Referido Spiders | J74: nazareth.ruiz@bold.co | K74: 200000000 | L74: 1.99 | P74: Pendientes
A75: jhonatan.moreno@bold.co | B75: LinkCo Marketing | C75: XRDVP47X28 | D75: Si | E75: =TEXT(F75, "mmmm yyyy") -> mayo 2024 | F75: 45420 | G75: =F75 -> 45420 | H75: =G75 -> 45420 | I75: Cliente Propio | K75: 20000000 | L75: 1.99
A76: jhonatan.moreno@bold.co | B76: Bel Skin SAS | C76: 6FYGDXFONI | D76: Si | E76: =TEXT(F76, "mmmm yyyy") -> mayo 2024 | F76: 45421 | G76: =F76 -> 45421 | H76: =G76 -> 45421 | I76: Cliente Propio | K76: 100000000 | L76: 1.99
A77: cristian.baquero@bold.co | B77: Quality Tires | C77: KYQDQ9DDUT | D77: Si | E77: =TEXT(F77, "mmmm yyyy") -> mayo 2024 | F77: 45423 | G77: =F77 -> 45423 | H77: =G77 -> 45423 | I77: Cliente Propio | K77: 20000000 | L77: 2,19 + 300
A78: jhonatan.moreno@bold.co | B78: Ichiraku Medellin | C78: ASKFYM2VN1 | D78: Si | E78: =TEXT(F78, "mmmm yyyy") -> mayo 2024 | F78: 45428 | G78: =F78 -> 45428 | H78: =G78 -> 45428 | I78: Cliente Propio | K78: 100000000 | L78: 0.0189 | P78: Pendientes
A79: jhonatan.moreno@bold.co | B79: Ichiraku Candelaria | C79: 8Y1CCKGDWM | D79: Si | E79: =TEXT(F79, "mmmm yyyy") -> mayo 2024 | F79: 45428 | G79: =F79 -> 45428 | H79: =G79 -> 45428 | I79: Cliente Propio | K79: 100000000 | L79: 0.0189 | P79: Pendientes
A80: luis.corredor@bold.co | B80: Rogelio Red Tacos | C80: CR64Q2ZH6L | D80: Si | E80: =TEXT(F80, "mmmm yyyy") -> mayo 2024 | F80: 45428 | G80: =F80 -> 45428 | H80: =G80 -> 45428 | I80: Referido Spiders | J80: milton.ortiz@bold.co | K80: 500000000 | L80: 1,99 + 100 | P80: Pendientes
A81: juan.salgado@bold.co | B81: ACTION BLACK | C81: GEDYCRICWZ | D81: Si | E81: =TEXT(F81, "mmmm yyyy") -> mayo 2024 | F81: 45430 | G81: =F81 -> 45430 | H81: =G81 -> 45430 | I81: Cliente Propio | K81: 200000000 | L81: 1.79
A82: angel.lesmes@bold.co | B82: Hello Park | C82: DF5AYBNCG7 | D82: Si | E82: =TEXT(F82, "mmmm yyyy") -> mayo 2024 | F82: 45432 | G82: =F82 -> 45432 | H82: =G82 -> 45432 | I82: Cliente Propio | K82: 100000000 | L82: 2.09 | P82: Pendientes
A83: jhonatan.torres@bold.co | B83: Hotel Tequendama Medellin | C83: 5OCMIYC9E1 | D83: Si | E83: =TEXT(F83, "mmmm yyyy") -> mayo 2024 | F83: 45435 | G83: =F83 -> 45435 | H83: =G83 -> 45435 | I83: Referido Spiders | J83: paula.ruiz@bold.co | K83: 40000000 | L83: full
A84: jhonatan.moreno@bold.co | B84: Rodamientos CJR | C84: 853AVNZ579 | D84: Si | E84: =TEXT(F84, "mmmm yyyy") -> mayo 2024 | F84: 45443 | G84: =F84 -> 45443 | H84: =G84 -> 45443 | I84: Referido Spiders | J84: angie.rodriguez@bold.co | K84: 20000000 | L84: 2,59 + 300
A85: jhonatan.moreno@bold.co | B85: Grupo 360 | C85: DTFL3QWOCZ | D85: Si | E85: =TEXT(F85, "mmmm yyyy") -> junio 2024 | F85: 45447 | G85: =F85 -> 45447 | H85: =G85 -> 45447 | I85: Referido Spiders | J85: milton.ortiz@bold.co | K85: 200000000 | L85: 2.05 | P85: Si
A86: luis.corredor@bold.co | B86: Ferreteria luis penagos | C86: 01AVRUSPXN | D86: Si | E86: =TEXT(F86, "mmmm yyyy") -> junio 2024 | F86: 45444 | G86: =F86 -> 45444 | H86: =G86 -> 45444 | I86: Referido Spiders | J86: sandra.robayo@bold.co | K86: 700000000 | L86: 45383 | P86: Si
A87: jhonatan.moreno@bold.co | B87: Selva nevada | C87: PS1W9XB6FQ | D87: Si | E87: =TEXT(F87, "mmmm yyyy") -> junio 2024 | F87: 45447 | G87: =F87 -> 45447 | H87: =G87 -> 45447 | I87: Referido Spiders | J87: angie.rodriguez@bold.co | K87: 40000000 | L87: 2.19
A88: jhonatan.moreno@bold.co | B88: Ferricentro | C88: GNC0EBFLKR | D88: Si | E88: =TEXT(F88, "mmmm yyyy") -> junio 2024 | F88: 45447 | G88: =F88 -> 45447 | H88: =G88 -> 45447 | I88: Cliente Propio | K88: 2000000000 | L88: 1.4 | P88: Pendientes
A89: jhonatan.moreno@bold.co | B89: Oporto Pollo | C89: RLDMWCDBC9 | D89: Si | E89: =TEXT(F89, "mmmm yyyy") -> junio 2024 | F89: 45448 | G89: =F89 -> 45448 | H89: =G89 -> 45448 | I89: Referido Spiders | J89: Nicolas.velandia@bold.co | K89: 40000000 | L89: 2.29
A90: jhonatan.torres@bold.co | B90: KSP SEALS AND PARTS | C90: M4LOYUCSQI | D90: Si | E90: =TEXT(F90, "mmmm yyyy") -> junio 2024 | F90: 45454 | G90: =F90 -> 45454 | H90: =G90 -> 45454 | I90: Referido Spiders | J90: sandra.robayo@bold.co | K90: 50000000 | L90: 2.29 + 300
A91: jhonatan.torres@bold.co | B91: Pink key | C91: TXEIYCNRVA | D91: Si | E91: =TEXT(F91, "mmmm yyyy") -> junio 2024 | F91: 45451 | G91: =F91 -> 45451 | H91: =G91 -> 45451 | I91: Cliente Propio | K91: 50000000 | L91: 2.19 + 200
A92: luis.corredor@bold.co | B92: Bestseller | C92: KNJ3NC4FSQ | D92: Si | E92: =TEXT(F92, "mmmm yyyy") -> junio 2024 | F92: 45454 | G92: =F92 -> 45454 | H92: =G92 -> 45454 | I92: Cliente Propio | K92: 200000000 | L92: 2.19
A93: jhonatan.moreno@bold.co | B93: RESTAURANTES LA PAMPA PARRILLA | C93: NW6BWOKGG9 | D93: Si | E93: =TEXT(F93, "mmmm yyyy") -> junio 2024 | F93: 45456 | G93: =F93 -> 45456 | H93: =G93 -> 45456 | I93: Referido Spiders | J93: milton.ortiz@bold.co | K93: 500000000 | L93: 1,99+300 | P93: Pendientes
A94: luis.corredor@bold.co | B94: Repuestos rimar | C94: BE6TICAMHK | D94: Si | E94: =TEXT(F94, "mmmm yyyy") -> junio 2024 | F94: 45457 | G94: =F94 -> 45457 | H94: =G94 -> 45457 | I94: Referido Spiders | J94: sandra.robayo@bold.co | K94: 70000000 | L94: 2.09 | P94: Si
A95: jhonatan.moreno@bold.co | B95: Monkey Burger | C95: EOEZSU8XRB | D95: Si | E95: =TEXT(F95, "mmmm yyyy") -> junio 2024 | F95: 45464 | G95: =F95 -> 45464 | H95: =G95 -> 45464 | I95: Referido Spiders | J95: milton.ortiz@bold.co | K95: 500000000 | L95: 1,99+300 | P95: Pendientes
A96: angel.lesmes@bold.co | B96: Al Alma café | C96: 51C9TI7TZK | D96: Si | E96: =TEXT(F96, "mmmm yyyy") -> junio 2024 | F96: 45464 | G96: =F96 -> 45464 | H96: =G96 -> 45464 | I96: Referido Spiders | J96: sandra.robayo@bold.co | K96: 500000000 | L96: 1,99+300
A97: angel.lesmes@bold.co | B97: Suzuki Suba | C97: LIJXVKVO17 | D97: Si | E97: =TEXT(F97, "mmmm yyyy") -> junio 2024 | F97: 45464 | G97: =F97 -> 45464 | H97: =G97 -> 45464 | I97: Referido Spiders | J97: sandra.robayo@bold.co | K97: 500000000 | L97: 1.69
A98: angel.lesmes@bold.co | B98: Oben | C98: E273MPSWXT | D98: Si | E98: =TEXT(F98, "mmmm yyyy") -> junio 2024 | F98: 45456 | G98: =F98 -> 45456 | H98: =G98 -> 45456 | I98: Cliente Propio | K98: 50000000 | L98: 2,19+300
A99: angel.lesmes@bold.co | B99: Perros JR Colina | C99: 6I3LZUJUWN | D99: Si | E99: =TEXT(F99, "mmmm yyyy") -> junio 2024 | F99: 45450 | G99: =F99 -> 45450 | H99: =G99 -> 45450 | I99: Referido Spiders | J99: angie.rodriguez@bold.co | K99: 50000000 | L99: 2,15+200
A100: angel.lesmes@bold.co | B100: Perros JR PLaza de las Américas | C100: Y9EAD1AQFT | D100: Si | E100: =TEXT(F100, "mmmm yyyy") -> junio 2024 | F100: 45450 | G100: =F100 -> 45450 | H100: =G100 -> 45450 | I100: Referido Spiders | J100: angie.rodriguez@bold.co | K100: 50000000 | L100: 2,15+200
...

Sheet Copia de CLIENTES ACTIVOS
A1: Ejecutivo | B1: Nombre Cliente | C1: Merchant ID | D1: Creado en CRM | E1: Mes Año | F1: Fecha de activacion | G1: Mes | H1: Año | I1: ORIGEN del Cliente | J1: Si es referido Correo electronico De quien refiere de no ser asi dejar N/A | K1: TPV Potencial en MIllones | L1: Tarifa Aplicada | M1: DATAFONOS | N1: QR-LINK-BOTON | O1: CONTRATOS FRAUDE | P1: CONTRATOS | Q1: TPV M0 | R1: TPV M1 | S1: TPV M2 | T1: TPV M3 | U1: PROMEDIO TPV | V1: Se entrega a CS | W1: KAM que recibe Comercio
A2: jhonatan.torres@bold.co | B2: Ferrelectric El Proveedor | C2: OTT8ZA91GS | D2: Si | E2: =TEXT(F2, "mmmm yyyy") -> enero 2024 | F2: 45296 | G2: =F2 -> 45296 | H2: =G2 -> 45296 | I2: SI | J2: luis.castellar@bold.co | K2: 50000000 | L2: 2,19 +300 | Q2: =VLOOKUP(C2,QS!E:AB,21,0) -> #REF! | R2: =VLOOKUP(C2,QS!E:AB,22,0) -> #REF! | S2: =VLOOKUP(C2,QS!E:AB,23,0) -> #REF! | T2: =VLOOKUP(C2,QS!E:AB,24,0) -> #REF!
A3: juan.salgado@bold.co | B3: JANGUEO CARTAGENA | C3: LWU5FIZZPX | D3: Si | E3: =TEXT(F3, "mmmm yyyy") -> enero 2024 | F3: 45303 | G3: =F3 -> 45303 | H3: =G3 -> 45303 | I3: SI | J3: Estefanía.torres@bold.co | K3: 50000000 | L3: 2,19+$300 | P3: Pendientes | Q3: =VLOOKUP(C3,QS!E:AB,21,0) -> #REF! | R3: =VLOOKUP(C3,QS!E:AB,22,0) -> #REF! | S3: =VLOOKUP(C3,QS!E:AB,23,0) -> #REF! | T3: =VLOOKUP(C3,QS!E:AB,24,0) -> #REF!
A4: jhonatan.moreno@bold.co | B4: Majestic burgers | C4: 7IW47CWHLA | D4: Si | E4: =TEXT(F4, "mmmm yyyy") -> enero 2024 | F4: 45306 | G4: =F4 -> 45306 | H4: =G4 -> 45306 | I4: Referido Outbound | J4: jaime.barrios@bold.co | K4: 150000000 | L4: 2,19+$300 | P4: Si | Q4: =VLOOKUP(C4,QS!E:AB,21,0) -> #REF! | R4: =VLOOKUP(C4,QS!E:AB,22,0) -> #REF! | S4: =VLOOKUP(C4,QS!E:AB,23,0) -> #REF! | T4: =VLOOKUP(C4,QS!E:AB,24,0) -> #REF!
A5: jhonatan.moreno@bold.co | B5: caribean team | C5: PM6BZ0OM41 | D5: Si | E5: =TEXT(F5, "mmmm yyyy") -> enero 2024 | F5: 45308 | G5: =F5 -> 45308 | H5: =G5 -> 45308 | I5: Referido Outbound | J5: jaime.barrios@bold.co | L5: 2,19+$300 | P5: Si | Q5: =VLOOKUP(C5,QS!E:AB,21,0) -> #REF! | R5: =VLOOKUP(C5,QS!E:AB,22,0) -> #REF! | S5: =VLOOKUP(C5,QS!E:AB,23,0) -> #REF! | T5: =VLOOKUP(C5,QS!E:AB,24,0) -> #REF!
A6: jhonatan.moreno@bold.co | B6: Tolifruver | C6: V2D10H30A6 | D6: Si | E6: =TEXT(F6, "mmmm yyyy") -> enero 2024 | F6: 45308 | G6: =F6 -> 45308 | H6: =G6 -> 45308 | I6: Cliente Propio | K6: 40000000 | L6: 2,39 + 300 | Q6: =VLOOKUP(C6,QS!E:AB,21,0) -> #REF! | R6: =VLOOKUP(C6,QS!E:AB,22,0) -> #REF! | S6: =VLOOKUP(C6,QS!E:AB,23,0) -> #REF! | T6: =VLOOKUP(C6,QS!E:AB,24,0) -> #REF!
A7: angel.lesmes@bold.co | B7: Manns Design | C7: W9Y4L8F4N2 | D7: Si | E7: =TEXT(F7, "mmmm yyyy") -> enero 2024 | F7: 45309 | G7: =F7 -> 45309 | H7: =G7 -> 45309 | K7: 30000000 | L7: 2,89+300 | Q7: =VLOOKUP(C7,QS!E:AB,21,0) -> #REF! | R7: =VLOOKUP(C7,QS!E:AB,22,0) -> #REF! | S7: =VLOOKUP(C7,QS!E:AB,23,0) -> #REF! | T7: =VLOOKUP(C7,QS!E:AB,24,0) -> #REF!
A8: jhonatan.moreno@bold.co | B8: Macro pollos | C8: AYILZWWK0P | D8: Si | E8: =TEXT(F8, "mmmm yyyy") -> enero 2024 | F8: 45316 | G8: =F8 -> 45316 | H8: =G8 -> 45316 | I8: Referido Outbound | J8: andres.cardozo@bold.co | K8: 20000000 | L8: 2,29+300 | P8: Si | Q8: =VLOOKUP(C8,QS!E:AB,21,0) -> #REF! | R8: =VLOOKUP(C8,QS!E:AB,22,0) -> #REF! | S8: =VLOOKUP(C8,QS!E:AB,23,0) -> #REF! | T8: =VLOOKUP(C8,QS!E:AB,24,0) -> #REF!
A9: luis.corredor@bold.co | B9: Sofiian Cedritos | C9: ARYDJSNS2X | D9: Si | E9: =TEXT(F9, "mmmm yyyy") -> enero 2024 | F9: 45316 | G9: =F9 -> 45316 | H9: =G9 -> 45316 | I9: Cliente Propio | K9: 35000000 | L9: 2,19 +300 | Q9: =VLOOKUP(C9,QS!E:AB,21,0) -> #REF! | R9: =VLOOKUP(C9,QS!E:AB,22,0) -> #REF! | S9: =VLOOKUP(C9,QS!E:AB,23,0) -> #REF! | T9: =VLOOKUP(C9,QS!E:AB,24,0) -> #REF!
A10: luis.corredor@bold.co | B10: Veolia | C10: D9BBCAUZRK | D10: Si | E10: =TEXT(F10, "mmmm yyyy") -> enero 2024 | F10: 45316 | G10: =F10 -> 45316 | H10: =G10 -> 45316 | I10: Cliente Propio | J10: lorena.oviedo@bold.co | K10: 150000000 | L10: 2.19 | P10: Pendientes | Q10: =VLOOKUP(C10,QS!E:AB,21,0) -> #REF! | R10: =VLOOKUP(C10,QS!E:AB,22,0) -> #REF! | S10: =VLOOKUP(C10,QS!E:AB,23,0) -> #REF! | T10: =VLOOKUP(C10,QS!E:AB,24,0) -> #REF!
A11: jhonatan.torres@bold.co | B11: DECORADOS Y ACABADOS CERMAMICOS | C11: MLSOQIAORD | D11: Si | E11: =TEXT(F11, "mmmm yyyy") -> enero 2024 | F11: 45316 | G11: =F11 -> 45316 | H11: =G11 -> 45316 | I11: No | K11: 200000000 | L11: 1.99 | P11: Pendientes | Q11: =VLOOKUP(C11,QS!E:AB,21,0) -> #REF! | R11: =VLOOKUP(C11,QS!E:AB,22,0) -> #REF! | S11: =VLOOKUP(C11,QS!E:AB,23,0) -> #REF! | T11: =VLOOKUP(C11,QS!E:AB,24,0) -> #REF!
A12: jhonatan.moreno@bold.co | B12: BEYROUTH 93 | C12: ZBFT9JBRNT | D12: Si | E12: =TEXT(F12, "mmmm yyyy") -> enero 2024 | F12: 45317 | G12: =F12 -> 45317 | H12: =G12 -> 45317 | I12: Referido Outbound | J12: margareth.arias@bold.co | K12: 200000000 | L12: 2.05 | Q12: =VLOOKUP(C12,QS!E:AB,21,0) -> #REF! | R12: =VLOOKUP(C12,QS!E:AB,22,0) -> #REF! | S12: =VLOOKUP(C12,QS!E:AB,23,0) -> #REF! | T12: =VLOOKUP(C12,QS!E:AB,24,0) -> #REF!
A13: luis.corredor@bold.co | B13: CASSARENA | C13: W06BXLMD3C | D13: Si | E13: =TEXT(F13, "mmmm yyyy") -> enero 2024 | F13: 45318 | G13: =F13 -> 45318 | H13: =G13 -> 45318 | I13: SI | J13: andres.cardozo@bold.co | K13: 100000000 | L13: 2,19+300 | P13: Si | Q13: =VLOOKUP(C13,QS!E:AB,21,0) -> #REF! | R13: =VLOOKUP(C13,QS!E:AB,22,0) -> #REF! | S13: =VLOOKUP(C13,QS!E:AB,23,0) -> #REF! | T13: =VLOOKUP(C13,QS!E:AB,24,0) -> #REF!
A14: jhonatan.moreno@bold.co | B14: ALFAPARF | C14: VOG2HUW5VO | D14: Si | E14: =TEXT(F14, "mmmm yyyy") -> febrero 2024 | F14: 45323 | G14: =F14 -> 45323 | H14: =G14 -> 45323 | I14: Cliente Propio | K14: 250000000 | L14: 2,19+$300 | Q14: =VLOOKUP(C14,QS!E:AB,21,0) -> #REF! | R14: =VLOOKUP(C14,QS!E:AB,22,0) -> #REF! | S14: =VLOOKUP(C14,QS!E:AB,23,0) -> #REF! | T14: =VLOOKUP(C14,QS!E:AB,24,0) -> #REF!
A15: jhonatan.moreno@bold.co | B15: Surubi Food | C15: VIFU5YJBTM | D15: Si | E15: =TEXT(F15, "mmmm yyyy") -> febrero 2024 | F15: 45324 | G15: =F15 -> 45324 | H15: =G15 -> 45324 | I15: Referido Outbound | J15: jaime.barrios@bold.co | K15: 100000000 | L15: 2,19+$300 | P15: Si | Q15: =VLOOKUP(C15,QS!E:AB,21,0) -> #REF! | R15: =VLOOKUP(C15,QS!E:AB,22,0) -> #REF! | S15: =VLOOKUP(C15,QS!E:AB,23,0) -> #REF! | T15: =VLOOKUP(C15,QS!E:AB,24,0) -> #REF!
A16: luis.corredor@bold.co | B16: Miguel Burger | C16: DQDQKMENXA | D16: Si | E16: =TEXT(F16, "mmmm yyyy") -> febrero 2024 | F16: 45324 | G16: =F16 -> 45324 | H16: =G16 -> 45324 | I16: No | K16: 160000000 | L16: 2,09+$100 | P16: Si | Q16: =VLOOKUP(C16,QS!E:AB,21,0) -> #REF! | R16: =VLOOKUP(C16,QS!E:AB,22,0) -> #REF! | S16: =VLOOKUP(C16,QS!E:AB,23,0) -> #REF! | T16: =VLOOKUP(C16,QS!E:AB,24,0) -> #REF!
A17: angel.lesmes@bold.co | B17: Restaurante Musashi | C17: QKCESKPA91 | D17: Si | E17: =TEXT(F17, "mmmm yyyy") -> febrero 2024 | F17: 45336 | G17: =F17 -> 45336 | H17: =G17 -> 45336 | I17: No | K17: 20000000 | L17: 2,19% + $300 | P17: Pendientes | Q17: =VLOOKUP(C17,QS!E:AB,21,0) -> #REF! | R17: =VLOOKUP(C17,QS!E:AB,22,0) -> #REF! | S17: =VLOOKUP(C17,QS!E:AB,23,0) -> #REF! | T17: =VLOOKUP(C17,QS!E:AB,24,0) -> #REF!
A18: angel.lesmes@bold.co | B18: Restaurante Musashi | C18: YE6RMJFK6K | D18: Si | E18: =TEXT(F18, "mmmm yyyy") -> febrero 2024 | F18: 45336 | G18: =F18 -> 45336 | H18: =G18 -> 45336 | I18: No | K18: 20000000 | L18: 2,19% + $300 | P18: Pendientes | Q18: =VLOOKUP(C18,QS!E:AB,21,0) -> #REF! | R18: =VLOOKUP(C18,QS!E:AB,22,0) -> #REF! | S18: =VLOOKUP(C18,QS!E:AB,23,0) -> #REF! | T18: =VLOOKUP(C18,QS!E:AB,24,0) -> #REF!
A19: jhonatan.torres@bold.co | B19: Artesanal | C19: YEY17SS4UP | D19: Si | E19: =TEXT(F19, "mmmm yyyy") -> febrero 2024 | F19: 45336 | G19: =F19 -> 45336 | H19: =G19 -> 45336 | I19: Referido Outbound | J19: luis.correa@bold.co | K19: 100000000 | L19: 2,19% + $300 | Q19: =VLOOKUP(C19,QS!E:AB,21,0) -> #REF! | R19: =VLOOKUP(C19,QS!E:AB,22,0) -> #REF! | S19: =VLOOKUP(C19,QS!E:AB,23,0) -> #REF! | T19: =VLOOKUP(C19,QS!E:AB,24,0) -> #REF!
A20: angel.lesmes@bold.co | B20: Almacén Y Taller Todo Nissan Ayt Sas | C20: VTCXH9AYXO | D20: Si | E20: =TEXT(F20, "mmmm yyyy") -> febrero 2024 | F20: 45337 | G20: =F20 -> 45337 | H20: =G20 -> 45337 | I20: Cliente Propio | K20: 50000000 | L20: 2,19% + $300 | P20: Pendientes | Q20: =VLOOKUP(C20,QS!E:AB,21,0) -> #REF! | R20: =VLOOKUP(C20,QS!E:AB,22,0) -> #REF! | S20: =VLOOKUP(C20,QS!E:AB,23,0) -> #REF! | T20: =VLOOKUP(C20,QS!E:AB,24,0) -> #REF!
A21: cristian.baquero@bold.co | B21: Acabados dyp | C21: CGTPT8L3DG | D21: Si | E21: =TEXT(F21, "mmmm yyyy") -> febrero 2024 | F21: 45332 | G21: =F21 -> 45332 | H21: =G21 -> 45332 | I21: Cliente Propio | K21: 30000000 | L21: 2,19% + $300 | Q21: =VLOOKUP(C21,QS!E:AB,21,0) -> #REF! | R21: =VLOOKUP(C21,QS!E:AB,22,0) -> #REF! | S21: =VLOOKUP(C21,QS!E:AB,23,0) -> #REF! | T21: =VLOOKUP(C21,QS!E:AB,24,0) -> #REF!
A22: cristian.baquero@bold.co | B22: Dukari | C22: CBL16SJULR | D22: Si | E22: =TEXT(F22, "mmmm yyyy") -> febrero 2024 | F22: 45334 | G22: =F22 -> 45334 | H22: =G22 -> 45334 | I22: Cliente Propio | K22: 50000000 | L22: 2,59% + $900 (solo Link) | Q22: 482000 | R22: =VLOOKUP(C22,QS!E:AB,22,0) -> #REF! | S22: =VLOOKUP(C22,QS!E:AB,23,0) -> #REF! | T22: =VLOOKUP(C22,QS!E:AB,24,0) -> #REF!
A23: cristian.baquero@bold.co | B23: Lebog | C23: EO5ZB49DG2 | D23: Si | E23: =TEXT(F23, "mmmm yyyy") -> febrero 2024 | F23: 45336 | G23: =F23 -> 45336 | H23: =G23 -> 45336 | I23: Cliente Propio | K23: 50000000 | L23: 2,19% + $300 | Q23: =VLOOKUP(C23,QS!E:AB,21,0) -> #REF! | R23: =VLOOKUP(C23,QS!E:AB,22,0) -> #REF! | S23: =VLOOKUP(C23,QS!E:AB,23,0) -> #REF! | T23: =VLOOKUP(C23,QS!E:AB,24,0) -> #REF!
A24: cristian.baquero@bold.co | B24: Foodology | C24: OFC2I4Z2PO | D24: Si | E24: =TEXT(F24, "mmmm yyyy") -> febrero 2024 | F24: 45342 | G24: =F24 -> 45342 | H24: =G24 -> 45342 | I24: Referido Outbound | J24: cristian.casas@bold.co | K24: 600000000 | L24: 0.0199 | P24: Pendientes | Q24: =VLOOKUP(C24,QS!E:AB,21,0) -> #REF! | R24: =VLOOKUP(C24,QS!E:AB,22,0) -> #REF! | S24: =VLOOKUP(C24,QS!E:AB,23,0) -> #REF! | T24: =VLOOKUP(C24,QS!E:AB,24,0) -> #REF!
A25: angel.lesmes@bold.co | B25: Medina Golden | C25: DUJE9XZH3Q | D25: Si | E25: =TEXT(F25, "mmmm yyyy") -> febrero 2024 | F25: 45345 | G25: =F25 -> 45345 | H25: =G25 -> 45345 | I25: Cliente Propio | K25: 100000000 | L25: 1.99 | P25: Pendientes | Q25: =VLOOKUP(C25,QS!E:AB,21,0) -> #REF! | R25: =VLOOKUP(C25,QS!E:AB,22,0) -> #REF! | S25: =VLOOKUP(C25,QS!E:AB,23,0) -> #REF! | T25: =VLOOKUP(C25,QS!E:AB,24,0) -> #REF!
A26: luis.corredor@bold.co | B26: Beef PuraRaza | C26: NY6646ULTO | D26: Si | E26: =TEXT(F26, "mmmm yyyy") -> febrero 2024 | F26: 45345 | G26: =F26 -> 45345 | H26: =G26 -> 45345 | I26: Referido Spiders | J26: angie.rodriguez@bold.co | K26: 150000000 | L26: 2,09+$100 | P26: Si | Q26: =VLOOKUP(C26,QS!E:AB,21,0) -> #REF! | R26: =VLOOKUP(C26,QS!E:AB,22,0) -> #REF! | S26: =VLOOKUP(C26,QS!E:AB,23,0) -> #REF! | T26: =VLOOKUP(C26,QS!E:AB,24,0) -> #REF!
A27: jhonatan.moreno@bold.co | B27: LA FINCA DE RIGOLLANOGRANDE | C27: 1AG1WY7CSP | D27: Si | E27: =TEXT(F27, "mmmm yyyy") -> marzo 2024 | F27: 45352 | G27: =F27 -> 45352 | H27: =G27 -> 45352 | I27: Referido Spiders | J27: angie.rodriguez@bold.co | K27: 200000000 | P27: Pendientes
A28: jhonatan.moreno@bold.co | B28: GO RIGO GO PALMAS | C28: 3F86R9UN91 | D28: Si | E28: =TEXT(F28, "mmmm yyyy") -> marzo 2024 | F28: 45352 | G28: =F28 -> 45352 | H28: =G28 -> 45352 | I28: Referido Spiders | J28: sandra.robayo@bold.co | K28: 200000000 | P28: Pendientes
A29: luis.corredor@bold.co | B29: Zona cafe y pan | C29: C2T5G954F1 | D29: Si | E29: =TEXT(F29, "mmmm yyyy") -> marzo 2024 | F29: 45352 | G29: =F29 -> 45352 | H29: =G29 -> 45352 | I29: Referido Spiders | J29: nazareth.ruiz@bold.co | K29: 40000000 | L29: 2,19% + $300
A30: angel.lesmes@bold.co | B30: Mi Tierra | C30: T0EM6PSD79 | D30: Si | E30: =TEXT(F30, "mmmm yyyy") -> marzo 2024 | F30: 45352 | G30: =F30 -> 45352 | H30: =G30 -> 45352 | I30: Referido Spiders | J30: milton.ortiz@bold.co | K30: 50000000 | L30: 2,19% + $300
A31: jhonatan.moreno@bold.co | B31: GRACIES | C31: PQFEX2AY4O | D31: Si | E31: =TEXT(F31, "mmmm yyyy") -> marzo 2024 | F31: 45355 | G31: =F31 -> 45355 | H31: =G31 -> 45355 | I31: Cliente Propio | K31: 80000000 | L31: 2.19
A32: jhonatan.moreno@bold.co | B32: COLTOLIMA | C32: KUQFCYOJ5F | D32: Si | E32: =TEXT(F32, "mmmm yyyy") -> marzo 2024 | F32: 45355 | G32: =F32 -> 45355 | H32: =G32 -> 45355 | I32: Cliente Propio | P32: Pendientes
A33: luis.corredor@bold.co | B33: Veolia Archipiélago sas esp | C33: YO5Y2NTPRY | D33: Si | E33: =TEXT(F33, "mmmm yyyy") -> marzo 2024 | F33: 45355 | G33: =F33 -> 45355 | H33: =G33 -> 45355 | I33: Referido Outbound | J33: edwar.sinisterra@bold.co | K33: 150000000 | L33: 2.19 | P33: Revision
A34: cristian.baquero@bold.co | B34: Rosalba Sanchez | C34: 1MEOXAZD4L | D34: Si | E34: =TEXT(F34, "mmmm yyyy") -> marzo 2024 | F34: 45356 | G34: =F34 -> 45356 | H34: =G34 -> 45356 | I34: Referido Spiders | J34: angie.rodriguez@bold.co | K34: 80000000 | L34: 2,19 + $300 | P34: Pendientes
A35: cristian.baquero@bold.co | B35: VFS Colombia SAS | C35: W522Q392Y7 | D35: Si | E35: =TEXT(F35, "mmmm yyyy") -> marzo 2024 | F35: 45356 | G35: =F35 -> 45356 | H35: =G35 -> 45356 | I35: Referido Spiders | J35: milton.ortiz@bold.co | K35: 400000000 | L35: 0.0199 | P35: Pendientes
A36: cristian.baquero@bold.co | B36: VFS Colombia SAS | C36: PZKOSYJEEO | D36: Si | E36: =TEXT(F36, "mmmm yyyy") -> marzo 2024 | F36: 45356 | G36: =F36 -> 45356 | H36: =G36 -> 45356 | I36: Referido Spiders | J36: milton.ortiz@bold.co | K36: 400000000 | L36: 0.0199 | P36: Pendientes
A37: cristian.baquero@bold.co | B37: VFS Colombia SAS | C37: W636X85VHW | D37: Si | E37: =TEXT(F37, "mmmm yyyy") -> marzo 2024 | F37: 45356 | G37: =F37 -> 45356 | H37: =G37 -> 45356 | I37: Referido Spiders | J37: milton.ortiz@bold.co | K37: 400000000 | L37: 0.0199 | P37: Pendientes
A38: jhonatan.moreno@bold.co | B38: German Summa | C38: 0NAMJ65HII | D38: Si | E38: =TEXT(F38, "mmmm yyyy") -> marzo 2024 | F38: 45363 | G38: =F38 -> 45363 | H38: =G38 -> 45363 | I38: Cliente Propio | K38: 40000000
A39: luis.corredor@bold.co | B39: Combos cosmicos portal 80 | C39: OFZJDWZPTJ | D39: Si | E39: =TEXT(F39, "mmmm yyyy") -> marzo 2024 | F39: 45363 | G39: =F39 -> 45363 | H39: =G39 -> 45363 | I39: Cliente Propio | K39: 30000000 | L39: 2,19 + $300
A40: jhonatan.moreno@bold.co | B40: Atractiva Calzados | C40: TP4LNEUN1M | D40: Si | E40: =TEXT(F40, "mmmm yyyy") -> marzo 2024 | F40: 45365 | G40: =F40 -> 45365 | H40: =G40 -> 45365 | I40: Cliente Propio | K40: 30000000 | L40: 2,19 + $300
A41: cristian.baquero@bold.co | B41: HH innovación y fabricación | C41: 0KN0WI1S9F | D41: Si | E41: =TEXT(F41, "mmmm yyyy") -> marzo 2024 | F41: 45364 | G41: =F41 -> 45364 | H41: =G41 -> 45364 | K41: 30000000 | L41: 2,59 + $300
A42: jhonatan.moreno@bold.co | B42: La meca | C42: ATLO1FBHKN | D42: Si | E42: =TEXT(F42, "mmmm yyyy") -> marzo 2024 | F42: 45365 | G42: =F42 -> 45365 | H42: =G42 -> 45365 | I42: Referido Spiders | J42: milton.ortiz@bold.co | K42: 30000000 | L42: 2,19 + $300
A43: jhonatan.moreno@bold.co | B43: PM Burger Boliva | C43: OQ7TIDV5MD | D43: Si | E43: =TEXT(F43, "mmmm yyyy") -> marzo 2024 | F43: 45366 | G43: =F43 -> 45366 | H43: =G43 -> 45366 | I43: Referido Spiders | J43: milton.ortiz@bold.co | K43: 40000000 | L43: 2,19 + $300
A44: jhonatan.moreno@bold.co | B44: Bacanal | C44: 372E652JMS | D44: Si | E44: =TEXT(F44, "mmmm yyyy") -> marzo 2024 | F44: 45366 | G44: =F44 -> 45366 | H44: =G44 -> 45366 | I44: Referido Spiders | J44: milton.ortiz@bold.co | K44: 0 | L44: 2,19 + $300
A45: jhonatan.moreno@bold.co | B45: Pablo y Maria Burger Brothers | C45: GQVPXX6V8G | D45: Si | E45: =TEXT(F45, "mmmm yyyy") -> marzo 2024 | F45: 45366 | G45: =F45 -> 45366 | H45: =G45 -> 45366 | I45: Referido Spiders | J45: milton.ortiz@bold.co | K45: 0 | L45: 2,19 + $300
A46: jhonatan.torres@bold.co | B46: La Ruana | C46: SJN7XJ8236 | D46: Si | E46: =TEXT(F46, "mmmm yyyy") -> marzo 2024 | F46: 45371 | G46: =F46 -> 45371 | H46: =G46 -> 45371 | I46: Referido Spiders | J46: milton.ortiz@bold.co | K46: 80000000 | L46: 0.0219
A47: angel.lesmes@bold.co | B47: CONSTRUCERAMICAS COLOMBIA SAS | C47: 45E8YNVYMM | D47: Si | E47: =TEXT(F47, "mmmm yyyy") -> abril 2024 | F47: 45383 | G47: =F47 -> 45383 | H47: =G47 -> 45383 | I47: Referido Inbound | J47: ana.reyes@bold.co | K47: 700000000 | L47: 0.0169 | P47: Si
A48: jhonatan.moreno@bold.co | B48: Scarpy Portal 80 | C48: 5AVCGZK2P8 | D48: Si | E48: =TEXT(F48, "mmmm yyyy") -> abril 2024 | F48: 45386 | G48: =F48 -> 45386 | H48: =G48 -> 45386 | I48: Cliente Propio | K48: 30000000 | L48: 2,19 + $300
A49: jhonatan.torres@bold.co | B49: AMC Odontologia | C49: 442EGE688O | D49: Si | E49: =TEXT(F49, "mmmm yyyy") -> abril 2024 | F49: 45386 | G49: =F49 -> 45386 | H49: =G49 -> 45386 | I49: Referido Spiders | J49: milton.ortiz@bold.co | K49: 25000000 | L49: 2.29%
A50: jhonatan.torres@bold.co | B50: AMC Odontologia | C50: 9AR1MMWV5A | D50: Si | E50: =TEXT(F50, "mmmm yyyy") -> abril 2024 | F50: 45386 | G50: =F50 -> 45386 | H50: =G50 -> 45386 | I50: Referido Spiders | J50: milton.ortiz@bold.co | K50: 25000000 | L50: 2.29%
B51: Ichiraku Chia | C51: TXFEH92VFO | D51: Si | E51: =TEXT(F51, "mmmm yyyy") -> abril 2024 | F51: 45387 | G51: =F51 -> 45387 | H51: =G51 -> 45387 | I51: Cliente Propio | K51: 100000000 | L51: 0.0189
A52: angel.lesmes@bold.co | B52: Perros JR | C52: VPRNTGJCB2 | D52: Si | E52: =TEXT(F52, "mmmm yyyy") -> abril 2024 | F52: 45391 | G52: =F52 -> 45391 | H52: =G52 -> 45391 | I52: Referido Spiders | J52: angie.rodriguez@bold.co | K52: 50000000 | L52: 2,09%+$100 | P52: Pendientes
A53: angel.lesmes@bold.co | B53: Perros JR | C53: 0JO6SWOPF5 | D53: Si | E53: =TEXT(F53, "mmmm yyyy") -> abril 2024 | F53: 45391 | G53: =F53 -> 45391 | H53: =G53 -> 45391 | I53: Referido Spiders | J53: angie.rodriguez@bold.co | K53: 50000000 | L53: 2,09%+$100 | P53: Pendientes
A54: angel.lesmes@bold.co | B54: Perros JR | C54: SNM2QGYKAJ | D54: Si | E54: =TEXT(F54, "mmmm yyyy") -> abril 2024 | F54: 45391 | G54: =F54 -> 45391 | H54: =G54 -> 45391 | I54: Referido Spiders | J54: angie.rodriguez@bold.co | K54: 50000000 | L54: 2,09%+$100 | P54: Pendientes
A55: angel.lesmes@bold.co | B55: Perros JR | C55: VI2AZEVQ73 | D55: Si | E55: =TEXT(F55, "mmmm yyyy") -> abril 2024 | F55: 45391 | G55: =F55 -> 45391 | H55: =G55 -> 45391 | I55: Referido Spiders | J55: angie.rodriguez@bold.co | K55: 50000000 | L55: 2,09%+$100 | P55: Pendientes
A56: cristian.baquero@bold.co | B56: Aroma Resto Bar SAS | C56: WZGSPR0JXV | D56: Si | E56: =TEXT(F56, "mmmm yyyy") -> abril 2024 | F56: 45387 | G56: =F56 -> 45387 | H56: =G56 -> 45387 | I56: Cliente Propio | K56: 100000000 | L56: 0.0219
A57: jhonatan.moreno@bold.co | B57: Ricasole | C57: X4JIGATJGL | D57: Si | E57: =TEXT(F57, "mmmm yyyy") -> abril 2024 | F57: 45393 | G57: =F57 -> 45393 | H57: =G57 -> 45393 | I57: Cliente Propio | K57: 50000000 | L57: 2,19 + 300 | P57: Pendientes
A58: cristian.baquero@bold.co | B58: Ililaserdent | C58: H4DQ3W9NLM | D58: Si | E58: =TEXT(F58, "mmmm yyyy") -> abril 2024 | F58: 45394 | G58: =F58 -> 45394 | H58: =G58 -> 45394 | I58: Referido Spiders | J58: nazareth.ruiz@bold.co | K58: 50000000 | L58: 2,19 % + $ 300
A59: cristian.baquero@bold.co | B59: Thai Station | C59: 4SFPMWKA6T | D59: Si | E59: =TEXT(F59, "mmmm yyyy") -> abril 2024 | F59: 45394 | G59: =F59 -> 45394 | H59: =G59 -> 45394 | I59: Cliente Propio | K59: 100000000 | L59: 2,09%+$100
A60: angel.lesmes@bold.co | B60: Imporcepo | C60: VFR0TAG2F7 | D60: Si | E60: =TEXT(F60, "mmmm yyyy") -> abril 2024 | F60: 45397 | G60: =F60 -> 45397 | H60: =G60 -> 45397 | I60: Referido Spiders | J60: nazareth.ruiz@bold.co | K60: 50000000 | L60: 2,59+300
A61: jhonatan.moreno@bold.co | B61: Monalisa | C61: 2XGLJL6ASW | D61: Si | E61: =TEXT(F61, "mmmm yyyy") -> abril 2024 | F61: 45400 | G61: =F61 -> 45400 | H61: =G61 -> 45400 | I61: Cliente Propio | K61: 40000000 | L61: 2.29
A62: jhonatan.moreno@bold.co | B62: Ichiraku Norte | C62: 5LSE5CTE6X | D62: Si | E62: =TEXT(F62, "mmmm yyyy") -> abril 2024 | F62: 45411 | G62: =F62 -> 45411 | H62: =G62 -> 45411 | I62: Cliente Propio | K62: 100000000 | L62: 0.0189 | P62: Pendientes
A63: jhonatan.moreno@bold.co | B63: Emme cafam floresta | C63: RMJJCNLKKI | D63: Si | E63: =TEXT(F63, "mmmm yyyy") -> abril 2024 | F63: 45412 | G63: =F63 -> 45412 | H63: =G63 -> 45412 | I63: Cliente Propio | K63: 30000000 | L63: 2,19 + 300
A64: jhonatan.moreno@bold.co | B64: Emme ensueno | C64: O63GT7UONQ | D64: Si | E64: =TEXT(F64, "mmmm yyyy") -> abril 2024 | F64: 45412 | G64: =F64 -> 45412 | H64: =G64 -> 45412 | I64: Cliente Propio | K64: 30000000 | L64: 2,19 + 300
A65: jhonatan.moreno@bold.co | B65: TOTAL SERVICE | C65: 9D25IUH6ZU | D65: Si | E65: =TEXT(F65, "mmmm yyyy") -> mayo 2024 | F65: 45414 | G65: =F65 -> 45414 | H65: =G65 -> 45414 | I65: Referido Spiders | J65: nazareth.ruiz@bold.co | K65: 40000000 | L65: 2.19
A66: jhonatan.moreno@bold.co | B66: La Bendita | C66: RA4XAW89EA | D66: Si | E66: =TEXT(F66, "mmmm yyyy") -> mayo 2024 | F66: 45414 | G66: =F66 -> 45414 | H66: =G66 -> 45414 | I66: Referido Spiders | J66: paula.ruiz@bold.co | K66: 150000000 | L66: 2.19
A67: jhonatan.moreno@bold.co | B67: Isla Corona (arrecife) | C67: V7F11RKN8F | D67: Si | E67: =TEXT(F67, "mmmm yyyy") -> mayo 2024 | F67: 45414 | G67: =F67 -> 45414 | H67: =G67 -> 45414 | I67: Referido Spiders | J67: paula.ruiz@bold.co | K67: 150000000 | L67: 2.19
A68: luis.corredor@bold.co | B68: wcar | C68: 9Q9H9V0QE5 | D68: Si | E68: =TEXT(F68, "mmmm yyyy") -> mayo 2024 | F68: 45414 | G68: =F68 -> 45414 | H68: =G68 -> 45414 | I68: Cliente Propio | K68: 70000000 | L68: 2.19
A69: luis.corredor@bold.co | B69: Mrscreativo | C69: VFP4AM2X8R | D69: Si | E69: =TEXT(F69, "mmmm yyyy") -> mayo 2024 | F69: 45414 | G69: =F69 -> 45414 | H69: =G69 -> 45414 | I69: Cliente Propio | K69: 20000000 | L69: 2,19 + 300
A70: jhonatan.torres@bold.co | B70: RAMGUIFLEX | C70: XBJD6EJPEE | D70: Si | E70: =TEXT(F70, "mmmm yyyy") -> mayo 2024 | F70: 45414 | G70: =F70 -> 45414 | H70: =G70 -> 45414 | I70: Cliente Propio | K70: 800000000 | L70: 1.60% | P70: Si
A71: jhonatan.moreno@bold.co | B71: SUBWAY | C71: 5LEB6JQ3ZX | D71: Si | E71: =TEXT(F71, "mmmm yyyy") -> mayo 2024 | F71: 45415 | G71: =F71 -> 45415 | H71: =G71 -> 45415 | I71: Referido Spiders | J71: nazareth.ruiz@bold.co | K71: 120000000 | L71: 1.99
A72: jhonatan.moreno@bold.co | B72: Urban | C72: X243MWK7PT | D72: Si | E72: =TEXT(F72, "mmmm yyyy") -> mayo 2024 | F72: 45415 | G72: =F72 -> 45415 | H72: =G72 -> 45415 | I72: Referido Spiders | J72: nazareth.ruiz@bold.co | K72: 30000000 | L72: 1.99
A73: jhonatan.moreno@bold.co | B73: Tortas del Gordo | C73: C6WTZMVXUJ | D73: Si | E73: =TEXT(F73, "mmmm yyyy") -> mayo 2024 | F73: 45416 | G73: =F73 -> 45416 | H73: =G73 -> 45416 | I73: Cliente Propio | K73: 90000000 | L73: 2.19
A74: jhonatan.moreno@bold.co | B74: Seoul medicina estetica | C74: J141IRHCAT | D74: Si | E74: =TEXT(F74, "mmmm yyyy") -> mayo 2024 | F74: 45420 | G74: =F74 -> 45420 | H74: =G74 -> 45420 | I74: Referido Spiders | J74: nazareth.ruiz@bold.co | K74: 200000000 | L74: 1.99 | P74: Pendientes
A75: jhonatan.moreno@bold.co | B75: LinkCo Marketing | C75: XRDVP47X28 | D75: Si | E75: =TEXT(F75, "mmmm yyyy") -> mayo 2024 | F75: 45420 | G75: =F75 -> 45420 | H75: =G75 -> 45420 | I75: Cliente Propio | K75: 20000000 | L75: 1.99
A76: jhonatan.moreno@bold.co | B76: Bel Skin SAS | C76: 6FYGDXFONI | D76: Si | E76: =TEXT(F76, "mmmm yyyy") -> mayo 2024 | F76: 45421 | G76: =F76 -> 45421 | H76: =G76 -> 45421 | I76: Cliente Propio | K76: 100000000 | L76: 1.99
A77: cristian.baquero@bold.co | B77: Quality Tires | C77: KYQDQ9DDUT | D77: Si | E77: =TEXT(F77, "mmmm yyyy") -> mayo 2024 | F77: 45423 | G77: =F77 -> 45423 | H77: =G77 -> 45423 | I77: Cliente Propio | K77: 20000000 | L77: 2,19 + 300
A78: jhonatan.moreno@bold.co | B78: Ichiraku Medellin | C78: ASKFYM2VN1 | D78: Si | E78: =TEXT(F78, "mmmm yyyy") -> mayo 2024 | F78: 45428 | G78: =F78 -> 45428 | H78: =G78 -> 45428 | I78: Cliente Propio | K78: 100000000 | L78: 0.0189 | P78: Pendientes
A79: jhonatan.moreno@bold.co | B79: Ichiraku Candelaria | C79: 8Y1CCKGDWM | D79: Si | E79: =TEXT(F79, "mmmm yyyy") -> mayo 2024 | F79: 45428 | G79: =F79 -> 45428 | H79: =G79 -> 45428 | I79: Cliente Propio | K79: 100000000 | L79: 0.0189 | P79: Pendientes
A80: luis.corredor@bold.co | B80: Rogelio Red Tacos | C80: CR64Q2ZH6L | D80: Si | E80: =TEXT(F80, "mmmm yyyy") -> mayo 2024 | F80: 45428 | G80: =F80 -> 45428 | H80: =G80 -> 45428 | I80: Referido Spiders | J80: milton.ortiz@bold.co | K80: 500000000 | L80: 1,99 + 100 | P80: Pendientes
A81: juan.salgado@bold.co | B81: ACTION BLACK | C81: GEDYCRICWZ | D81: Si | E81: =TEXT(F81, "mmmm yyyy") -> mayo 2024 | F81: 45430 | G81: =F81 -> 45430 | H81: =G81 -> 45430 | I81: Cliente Propio | K81: 200000000 | L81: 1.79
A82: angel.lesmes@bold.co | B82: Hello Park | C82: DF5AYBNCG7 | D82: Si | E82: =TEXT(F82, "mmmm yyyy") -> mayo 2024 | F82: 45432 | G82: =F82 -> 45432 | H82: =G82 -> 45432 | I82: Cliente Propio | K82: 100000000 | L82: 2.09 | P82: Pendientes
A83: jhonatan.torres@bold.co | B83: Hotel Tequendama Medellin | C83: 5OCMIYC9E1 | D83: Si | E83: =TEXT(F83, "mmmm yyyy") -> mayo 2024 | F83: 45435 | G83: =F83 -> 45435 | H83: =G83 -> 45435 | I83: Referido Spiders | J83: paula.ruiz@bold.co | K83: 40000000 | L83: full
A84: jhonatan.moreno@bold.co | B84: Rodamientos CJR | C84: 853AVNZ579 | D84: Si | E84: =TEXT(F84, "mmmm yyyy") -> mayo 2024 | F84: 45443 | G84: =F84 -> 45443 | H84: =G84 -> 45443 | I84: Referido Spiders | J84: angie.rodriguez@bold.co | K84: 20000000 | L84: 2,59 + 300
A85: jhonatan.moreno@bold.co | B85: Grupo 360 | C85: DTFL3QWOCZ | D85: Si | E85: =TEXT(F85, "mmmm yyyy") -> junio 2024 | F85: 45447 | G85: =F85 -> 45447 | H85: =G85 -> 45447 | I85: Referido Spiders | J85: milton.ortiz@bold.co | K85: 200000000 | L85: 2.05 | P85: Si
A86: luis.corredor@bold.co | B86: Ferreteria luis penagos | C86: 01AVRUSPXN | D86: Si | E86: =TEXT(F86, "mmmm yyyy") -> junio 2024 | F86: 45444 | G86: =F86 -> 45444 | H86: =G86 -> 45444 | I86: Referido Spiders | J86: sandra.robayo@bold.co | K86: 700000000 | L86: 45383 | P86: Si
A87: jhonatan.moreno@bold.co | B87: Selva nevada | C87: PS1W9XB6FQ | D87: Si | E87: =TEXT(F87, "mmmm yyyy") -> junio 2024 | F87: 45447 | G87: =F87 -> 45447 | H87: =G87 -> 45447 | I87: Referido Spiders | J87: angie.rodriguez@bold.co | K87: 40000000 | L87: 2.19
A88: jhonatan.moreno@bold.co | B88: Ferricentro | C88: GNC0EBFLKR | D88: Si | E88: =TEXT(F88, "mmmm yyyy") -> junio 2024 | F88: 45447 | G88: =F88 -> 45447 | H88: =G88 -> 45447 | I88: Cliente Propio | K88: 2000000000 | L88: 1.4 | P88: Pendientes
A89: jhonatan.moreno@bold.co | B89: Oporto Pollo | C89: RLDMWCDBC9 | D89: Si | E89: =TEXT(F89, "mmmm yyyy") -> junio 2024 | F89: 45448 | G89: =F89 -> 45448 | H89: =G89 -> 45448 | I89: Referido Spiders | J89: Nicolas.velandia@bold.co | K89: 40000000 | L89: 2.29
A90: jhonatan.torres@bold.co | B90: KSP SEALS AND PARTS | C90: M4LOYUCSQI | D90: Si | E90: =TEXT(F90, "mmmm yyyy") -> junio 2024 | F90: 45454 | G90: =F90 -> 45454 | H90: =G90 -> 45454 | I90: Referido Spiders | J90: sandra.robayo@bold.co | K90: 50000000 | L90: 2.29 + 300
A91: jhonatan.torres@bold.co | B91: Pink key | C91: TXEIYCNRVA | D91: Si | E91: =TEXT(F91, "mmmm yyyy") -> junio 2024 | F91: 45451 | G91: =F91 -> 45451 | H91: =G91 -> 45451 | I91: Cliente Propio | K91: 50000000 | L91: 2.19 + 200
A92: luis.corredor@bold.co | B92: Bestseller | C92: KNJ3NC4FSQ | D92: Si | E92: =TEXT(F92, "mmmm yyyy") -> junio 2024 | F92: 45454 | G92: =F92 -> 45454 | H92: =G92 -> 45454 | I92: Cliente Propio | K92: 200000000 | L92: 2.19
A93: jhonatan.moreno@bold.co | B93: RESTAURANTES LA PAMPA PARRILLA | C93: NW6BWOKGG9 | D93: Si | E93: =TEXT(F93, "mmmm yyyy") -> junio 2024 | F93: 45456 | G93: =F93 -> 45456 | H93: =G93 -> 45456 | I93: Referido Spiders | J93: milton.ortiz@bold.co | K93: 500000000 | L93: 1,99+300 | P93: Pendientes
A94: luis.corredor@bold.co | B94: Repuestos rimar | C94: BE6TICAMHK | D94: Si | E94: =TEXT(F94, "mmmm yyyy") -> junio 2024 | F94: 45457 | G94: =F94 -> 45457 | H94: =G94 -> 45457 | I94: Referido Spiders | J94: sandra.robayo@bold.co | K94: 70000000 | L94: 2.09 | P94: Si
A95: jhonatan.moreno@bold.co | B95: Monkey Burger | C95: EOEZSU8XRB | D95: Si | E95: =TEXT(F95, "mmmm yyyy") -> junio 2024 | F95: 45464 | G95: =F95 -> 45464 | H95: =G95 -> 45464 | I95: Referido Spiders | J95: milton.ortiz@bold.co | K95: 500000000 | L95: 1,99+300 | P95: Pendientes
A96: angel.lesmes@bold.co | B96: Al Alma café | C96: 51C9TI7TZK | D96: Si | E96: =TEXT(F96, "mmmm yyyy") -> junio 2024 | F96: 45464 | G96: =F96 -> 45464 | H96: =G96 -> 45464 | I96: Referido Spiders | J96: sandra.robayo@bold.co | K96: 500000000 | L96: 1,99+300
A97: angel.lesmes@bold.co | B97: Suzuki Suba | C97: LIJXVKVO17 | D97: Si | E97: =TEXT(F97, "mmmm yyyy") -> junio 2024 | F97: 45464 | G97: =F97 -> 45464 | H97: =G97 -> 45464 | I97: Referido Spiders | J97: sandra.robayo@bold.co | K97: 500000000 | L97: 1.69
A98: angel.lesmes@bold.co | B98: Oben | C98: E273MPSWXT | D98: Si | E98: =TEXT(F98, "mmmm yyyy") -> junio 2024 | F98: 45456 | G98: =F98 -> 45456 | H98: =G98 -> 45456 | I98: Cliente Propio | K98: 50000000 | L98: 2,19+300
A99: angel.lesmes@bold.co | B99: Perros JR Colina | C99: 6I3LZUJUWN | D99: Si | E99: =TEXT(F99, "mmmm yyyy") -> junio 2024 | F99: 45450 | G99: =F99 -> 45450 | H99: =G99 -> 45450 | I99: Referido Spiders | J99: angie.rodriguez@bold.co | K99: 50000000 | L99: 2,15+200
A100: angel.lesmes@bold.co | B100: Perros JR PLaza de las Américas | C100: Y9EAD1AQFT | D100: Si | E100: =TEXT(F100, "mmmm yyyy") -> junio 2024 | F100: 45450 | G100: =F100 -> 45450 | H100: =G100 -> 45450 | I100: Referido Spiders | J100: angie.rodriguez@bold.co | K100: 50000000 | L100: 2,15+200
...

Sheet CLIENTES A, nuevos
A1: Ejecutivo | B1: Nombre Cliente | C1: Merchant ID | D1: Creado en CRM | E1: Mes Año | F1: Fecha de activacion | G1: Mes | H1: Año | I1: ORIGEN del Cliente | J1: Si es referido Correo electronico De quien refiere de no ser asi dejar N/A | K1: TPV Potencial en MIllones | L1: Tarifa Aplicada | M1: DATAFONOS | N1: QR-LINK-BOTON | O1: CONTRATOS FRAUDE | P1: CONTRATOS | Q1: TPV M0 | R1: TPV M1 | S1: TPV M2 | T1: TPV M3 | U1: PROMEDIO TPV | V1: Formato entrega de comercios | W1: KAM que recibe Comercio

Sheet ESCALAMIENTOS GRAL
A1: Área | B1: Custodio | C1: Nombre cliente | E1: Merchant | F1: Fecha incidente | G1: Mes | H1: Año | I1: Fecha de reporte | J1: Incidente | K1: Encargado | L1: Fecha solución | M1: Valor | N1: Observación | O1: Estado | P1: Categoria
A2: Producto pagos | B2: C. Camilo Casas | C2: POSTOBON | D2: Postobon | E2: UKH72XS44S | F2: 46028 | G2: ENERO | H2: =YEAR(F2) -> 2026 | I2: 46028 | J2: TX rechazadas | K2: Leidy Rodriguez Raul Navarrete | L2: 02/20/2026 | M2: 342700 | N2: PENDIENTE CERTIFICADO DE COBRO | O2: Resuelto | P2: Pagos rechazados/no abonados/descontados
A3: MKT | B3: Juan Camilo Salgado | C3: POSTOBON | D3: Postobon | E3: -- | F3: 46042 | G3: ENERO | H3: =YEAR(F3) -> 2026 | I3: 46042 | J3: Peticion | K3: Laura Londoño | L3: -- | M3: 0 | N3: Peticion de Pieza grafica para incentivar recudo digital. | O3: Pendiente | P3: Solicitud pieza grafica
A4: Producto pagos | B4: C. Camilo Casas | C4: POSTOBON | D4: Postobon | E4: UKH72XS44S | F4: 46039 | G4: ENERO | H4: =YEAR(F4) -> 2026 | I4: 46045 | J4: TX rechazadas | K4: Leidy Rodriguez | L4: -- | M4: 391458 | N4: /después de validar la transacción T4RRHIMENLZ por valor de $391.458 del pasado 17/01/2026, te confirmamos que no tenemos abono en nuestra cuenta. Como muestra en tu aplicación, la transacción no fue exitosa. En el caso de que tu cliente final insista en que tiene el descuento, es necesario que él o ella solicite a su banco un certificado del cobro de esta misma con fecha posterior al 27/01/2026 para poder escalar el caso con la entidad financiera. | O4: Pendiente | P4: Pagos rechazados/no abonados/descontados
A5: Producto pagos | B5: C. Camilo Casas | C5: POSTOBON | D5: Postobon | E5: UKH72XS44S | F5: 46028 | G5: ENERO | H5: =YEAR(F5) -> 2026 | I5: 46045 | J5: TX rechazadas | K5: Incidencias | L5: 46049 | M5: 442250 | N5: después de validar la transacción TOB09WUQ3T3 por valor de $442.250 del pasado 06/01/2026, te confirmamos que sí tenemos un abono. Hoy se solicitó un cambio de estado y podrás ver la modificación desde tu aplicación, así como el abono de la venta, en 1 día hábil en tu Saldo de Ventas Bold. | O5: Resuelto | P5: Pagos rechazados/no abonados/descontados
A6: Producto pagos | B6: C. Camilo Casas | C6: POSTOBON | D6: Postobon | E6: QBLW9W0FGB | F6: 45973 | G6: NOVIEMBRE | H6: =YEAR(F6) -> 2025 | I6: 46055 | J6: TX rechazadas | K6: Incidencias | M6: 762500 | N6: PENDIENTE CERTIFICADO DE COBRO | O6: Resuelto
A7: Producto pagos | B7: C. Camilo Casas | C7: POSTOBON | D7: Postobon | E7: QBLW9W0FGB | F7: 45997 | G7: DICIEMBRE | H7: =YEAR(F7) -> 2025 | I7: 46055 | J7: TX rechazadas | K7: Incidencias | M7: 526100 | N7: PENDIENTE CERTIFICADO DE COBRO / y info deTRX | O7: Resuelto
A8: Producto pagos | B8: C. Camilo Casas | C8: POSTOBON | D8: Postobon | E8: QBLW9W0FGB | F8: 45997 | G8: DICIEMBRE | H8: =YEAR(F8) -> 2025 | I8: 46055 | J8: TX rechazadas | K8: Incidencias | M8: 1505300 | N8: PENDIENTE CERTIFICADO DE COBRO / y info deTRX | O8: Resuelto
A9: Producto pagos | B9: C. Camilo Casas | C9: POSTOBON | D9: Postobon | E9: QBLW9W0FGB | F9: 45677 | G9: ENERO | H9: =YEAR(F9) -> 2025 | I9: 46045 | J9: TX rechazadas | K9: Leidy Rodriguez | L9: 46050 | M9: 495000 | N9: te confirmamos que sí tenemos un abono. Hoy 29 de enero se solicitó un cambio de estado y podrás ver la modificación desde tu aplicación, así como el abono de la venta, en 1 día hábil en tu Saldo de Ventas Bold. | O9: Resuelto | P9: Pagos rechazados/no abonados/descontados
A10: Producto pagos | B10: C. Camilo Casas | C10: POSTOBON | D10: Postobon | E10: UKH72XS44S | F10: 45987 | G10: NOVIEMBRE | H10: =YEAR(F10) -> 2025 | I10: 46075 | J10: TX rechazadas | K10: Leidy Rodriguez | L10: 46050 | M10: 300000 | N10: consignación entre cuentas ACH 7 Linda lamentamos las molestias generadas, te confirmamos que en efecto la transferencia dispersada por $1.882.032,00 el 18 de diciembre 2025 que ingreso a tu cuenta el 22 de diciembre del 2025 se compone de las transacciones TCXESFK250I, T0YGLC83436, TXN10CNJM2Q. | O10: Resuelto
A11: Producto cuenta | B11: Jeyson Salazar | C11: Coopicredito | D11: Coopicredito | E11: NAKCEJYG9R | F11: 46044 | G11: ENERO | H11: =YEAR(F11) -> 2026 | I11: 46044 | J11: Cuenta Bold | K11: Jesus Marrugo | M11: -- | N11: Cliente al intentar crear un usuario de consultas en su Cuenta Bold, arroja un error, está en revisión por parte del equipo de Banking | O11: Resuelto
A12: Producto pagos | B12: Jeyson Salazar | C12: Coopicredito | D12: Coopicredito | E12: CJZ9L7O0SB | F12: 46042 | G12: ENERO | H12: =YEAR(F12) -> 2026 | I12: 46042 | J12: Falla QR | K12: Carlos Manrique | M12: -- | N12: Se evidencia que las txs por QR no le estamos cobrando la comisión, es una falla en la API de Pagos, Producto está revisando la solución pronta. | O12: Resuelto
A13: Tecnologia | B13: Jeyson Salazar | C13: Coopicredito | D13: Coopicredito | E13: CJZ9L7O0SB | F13: 46042 | G13: ENERO | H13: =YEAR(F13) -> 2026 | I13: 46042 | J13: Solicitudes a Producto | K13: Lina Toquica | M13: -- | N13: Se evidencia diferencias en la longitud de caracteres en el campo "REALIZADO POR" de la estructura de Cierre de Turno, está ciendo revisada por el equipo de TI. | O13: Resuelto
A14: Producto pagos | B14: C. Camilo Casas | C14: POSTOBON | D14: Postobon | E14: UKH72XS44S | F14: 46042 | G14: ENERO | H14: =YEAR(F14) -> 2026 | I14: 132800 | J14: TX rechazadas | K14: Leidy Rodriguez | L14: 46030 | M14: 915000 | N14: después de validar la transacción TW4G4MSHDCK por valor de $915.000 del pasado 20/01/2026, te confirmamos que sí tenemos un abono. Hoy se solicitó un cambio de estado y podrás ver la modificación desde tu aplicación, así como el abono de la venta, en 1 día hábil en tu Saldo de Ventas Bold. | O14: Resuelto | P14: Pagos rechazados/no abonados/descontados
A15: Producto pagos | B15: C. Camilo Casas | C15: POSTOBON | D15: Postobon | E15: UKH72XS44S | F15: 46044 | G15: ENERO | H15: =YEAR(F15) -> 2026 | I15: 132800 | J15: Falla QR | K15: Bayron Romero | L15: 45680 | M15: -- | N15: QR presenta novedad se coloca valor X aparece otro valor en el app del cliente al momento de scanear usuario salo0520sebas@gmail.com | O15: Resuelto | P15: Problemas de plataforma
A16: Producto pagos | B16: C. Camilo Casas | C16: POSTOBON | D16: Postobon | E16: SE3RYFGAJY | F16: 46042 | G16: ENERO | H16: =YEAR(F16) -> 2026 | I16: 46045 | J16: TX rechazadas | K16: Leidy Rodriguez | L16: 46050 | M16: 1658000 | N16: después de validar la transacción TRRNTDA5IQ5 por valor de $1.658.000 del pasado 20/01/2026, te confirmamos que sí tenemos un abono. Hoy se solicitó un cambio de estado y podrás ver la modificación desde tu aplicación, así como el abono de la venta, en 1 día hábil en tu Saldo de Ventas Bold. | O16: Resuelto | P16: Pagos rechazados/no abonados/descontados
A17: Producto pagos | B17: C. Camilo Casas | C17: POSTOBON | D17: Postobon | E17: SE3RYFGAJY | F17: 46042 | G17: ENERO | H17: =YEAR(F17) -> 2026 | I17: 46045 | J17: TX rechazadas | K17: Leidy Rodriguez | L17: 46050 | M17: 245000 | N17: después de validar la transacción TSQN2T5WZFI por valor de $245.000 del pasado 20/01/2026, te confirmamos que sí tenemos un abono. Hoy se solicitó un cambio de estado y podrás ver la modificación desde tu aplicación, así como el abono de la venta, en 1 día hábil en tu Saldo de Ventas Bold. | O17: Resuelto | P17: Pagos rechazados/no abonados/descontados
A18: Producto pagos | B18: C. Camilo Casas | C18: POSTOBON | D18: Postobon | E18: DKFDV7RLFX | F18: 46042 | G18: ENERO | H18: =YEAR(F18) -> 2026 | I18: 46045 | J18: TX rechazadas | K18: Leidy Rodriguez | L18: 46049 | M18: 2315000 | N18: después de validar la transacción TJ5OTA5TFIR por valor de $2.315.000 del pasado 20/01/2026, te confirmamos que sí tenemos un abono. Hoy se solicitó un cambio de estado y podrás ver la modificación desde tu aplicación, así como el abono de la venta, en 1 día hábil en tu Saldo de Ventas Bold. | O18: Resuelto | P18: Pagos rechazados/no abonados/descontados
A19: Producto pagos | B19: C. Camilo Casas | C19: POSTOBON | D19: Postobon | E19: DKFDV7RLFX | F19: 46042 | G19: ENERO | H19: =YEAR(F19) -> 2026 | I19: 46045 | J19: TX rechazadas | K19: Leidy Rodriguez | L19: -- | M19: 1960300 | N19: PENDIENTE CERTIFICADO DE COBRO / ID TRANSACCIÓN | O19: Pendiente | P19: Pagos rechazados/no abonados/descontados
A20: Producto pagos | B20: C. Camilo Casas | C20: POSTOBON | D20: Postobon | E20: DKFDV7RLFX | F20: 46042 | G20: ENERO | H20: =YEAR(F20) -> 2026 | I20: 46045 | J20: TX rechazadas | K20: Leidy Rodriguez | L20: 46049 | M20: 101100 | N20: después de validar la transacción TC6H5UF8V7B por valor de $101.100 del pasado 20/01/2026, te confirmamos que sí tenemos un abono. Hoy se solicitó un cambio de estado y podrás ver la modificación desde tu aplicación, así como el abono de la venta, en 1 día hábil en tu Saldo de Ventas Bold. | O20: Resuelto | P20: Pagos rechazados/no abonados/descontados
A21: Producto pagos | B21: C. Camilo Casas | C21: POSTOBON | D21: Postobon | E21: SE3RYFGAJY | F21: 46037 | G21: ENERO | H21: =YEAR(F21) -> 2026 | I21: 46045 | J21: TX rechazadas | K21: Leidy Rodriguez | L21: 46050 | M21: 155100 | N21: después de validar la transacción TPN2EQAQ91K por valor de $155.100 del pasado 15/01/2026, te confirmamos que sí tenemos un abono. Hoy se solicitó un cambio de estado y podrás ver la modificación desde tu aplicación, así como el abono de la venta, en 1 día hábil en tu Saldo de Ventas Bold. | O21: Resuelto | P21: Pagos rechazados/no abonados/descontados
A22: Producto pagos | B22: C. Camilo Casas | C22: POSTOBON | D22: Postobon | E22: Z2LOEMM4GD | F22: 46022 | G22: =TEXT(F22,"mmmm") -> diciembre | H22: =YEAR(F22) -> 2025 | I22: 46045 | J22: TX rechazadas | K22: Leidy Rodriguez | L22: 46049 | M22: 1274749 | N22: Respecto a la consulta realizada el día 23/01/2026, te comentamos que para el comercio Z2LOEMM4GD no se logra localizar una transacción por valor de $1.274.749 del pasado 31/12/2025 tal como muestra el comprobante enviado. Agradecemos nos envíes el ID de la transacción, adicionalmente en el caso de que tu cliente final insista en que tiene el descuento, es necesario que él o ella solicite a su banco un certificado del cobro de esta misma con fecha posterior al 27/01/2026 para poder escalar el caso con la entidad financiera. | O22: Pendiente | P22: Pagos rechazados/no abonados/descontados
A23: Producto pagos | B23: C. Camilo Casas | C23: POSTOBON | D23: Postobon | E23: Q7VR1248VT | F23: 46044 | G23: DICEMBRE | H23: =YEAR(F23) -> 2026 | I23: 46045 | J23: Error ingreso App | K23: Bayron Steven | L23: 46047 | M23: -- | N23: Transportador: App no le permite el ingreso correctamente | O23: Pendiente | P23: Errores o Fallas cuenta BOLD
A24: Producto pagos | B24: C. Camilo Casas | C24: POSTOBON | D24: Postobon | E24: TOM95X6WAO | F24: 46042 | G24: ENERO | H24: =YEAR(F24) -> 2026 | I24: 46045 | J24: TX rechazadas | K24: Leidy Rodriguez | L24: 46049 | M24: 249900 | N24: después de validar la transacción TYK4V5G3OL7 por valor de $249.900 del pasado 20/01/2026, te confirmamos que sí tenemos un abono. Hoy se solicitó un cambio de estado y podrás ver la modificación desde tu aplicación, así como el abono de la venta, en 1 día hábil en tu Saldo de Ventas Bold. | O24: Resuelto | P24: Pagos rechazados/no abonados/descontados
A25: Producto pagos | B25: C. Camilo Casas | C25: POSTOBON | D25: Postobon | E25: QBLW9W0FGB | F25: 45965 | G25: NOVIEMBRE | H25: =YEAR(F25) -> 2025 | I25: 45965 | J25: TX rechazadas | K25: Bayron Romero | M25: 780000 | N25: Canal de escalamiento informa que sin certificado de cobro logran encontrar TRX revisar link de Slack | O25: Pendiente | P25: Pagos rechazados/no abonados/descontados
A26: Producto pagos | B26: C. Camilo Casas | C26: POSTOBON | D26: Postobon | E26: DKFDV7RLFX | F26: 46049 | G26: ENERO | H26: =YEAR(F26) -> 2026 | I26: 46049 | J26: TX rechazadas | K26: Leidy rogriguez | L26: 46049 | M26: 1488032 | N26: Se reversa transacción al pagador | O26: Resuelto | P26: Pagos rechazados/no abonados/descontados
A27: Producto pagos | B27: C. Camilo Casas | C27: Colanta | D27: Colanta | E27: VY6VES3Z9R | F27: 46062 | G27: FEBRERO | H27: =YEAR(F27) -> 2026 | I27: 46071 | J27: TX rechazadas | K27: Leidy Rodriguez | L27: 46072 | M27: 86402 | N27: se cambia de estado TRX y se abona el dinero el dia 20 de febrero al cuenta | O27: Resuelto | P27: Pagos rechazados/no abonados/descontados
A28: Producto pagos | B28: C. Camilo Giraldo | C28: POSTOBON | D28: Postobon | E28: TOM95X6WAO | F28: 46065 | G28: FEBRERO | H28: =YEAR(F28) -> 2026 | I28: 46072 | J28: TX rechazadas | K28: incidencias | L28: 46072 | M28: 1445124 | N28: la transacción no fue exitosa. En el caso de que tu cliente final insista en que tiene el descuento, es necesario que él o ella solicite a su banco un certificado del cobro de esta misma con fecha posterior al 19/02/2026 para poder escalar el caso con la entidad financiera. | O28: Pendiente | P28: Pagos rechazados/no abonados/descontados
A29: Producto pagos | B29: C. Camilo Casas | C29: Colanta | D29: Colanta | E29: VY6VES3Z9R | F29: 46062 | G29: FEBRERO | H29: =YEAR(F29) -> 2026 | I29: 46071 | J29: TX rechazadas | K29: Leidy Rodriguez | L29: 46072 | M29: 240668 | N29: ya encontraron el abono. El 19 de febrero se cambia el estado y 20 Febrero se abona dinero cuenta COLANTA | O29: Resuelto | P29: Pagos rechazados/no abonados/descontados
A30: Producto pagos | B30: C. Camilo Giraldo | C30: POSTOBON | D30: Postobon | E30: UKH72XS44S | F30: 46062 | G30: FEBRERO | H30: =YEAR(F30) -> 2026 | I30: 46072 | J30: TX rechazadas | K30: incidencias | L30: 46072 | M30: 1701800 | N30: Hoy se solicitó un cambio de estado y podrás ver la modificación desde tu aplicación, así como el abono de la venta, en 1 día hábil en tu Saldo de Ventas Bold. | O30: Resuelto | P30: Pagos rechazados/no abonados/descontados
A31: Producto pagos | B31: C. Camilo Casas | C31: Colanta | D31: Colanta | E31: VY6VES3Z9R | F31: 46056 | G31: FEBRERO | H31: =YEAR(F31) -> 2026 | I31: 46064 | J31: TX rechazadas | K31: Leidy Rodriguez | M31: 343495 | N31: transferencia interbancaria | O31: Pendiente | P31: Pagos rechazados/no abonados/descontados
A32: Producto pagos | B32: C. Camilo Giraldo | C32: POSTOBON | D32: Postobon | E32: UKH72XS44S | F32: 46056 | G32: FEBRERO | H32: =YEAR(F32) -> 2026 | I32: 46072 | J32: TX rechazadas | K32: Incidencias | L32: 46072 | M32: 586600 | N32: te confirmamos que sí tenemos un abono. Hoy se solicitó un cambio de estado y podrás ver la modificación desde tu aplicación, así como el abono de la venta, en 1 día hábil en tu Saldo de Ventas Bold. | O32: Resuelto | P32: Pagos rechazados/no abonados/descontados
A33: Producto pagos | B33: C. Camilo Giraldo | C33: POSTOBON | D33: Postobon | E33: UKH72XS44S | F33: 46062 | G33: FEBRERO | H33: =YEAR(F33) -> 2026 | I33: 46072 | J33: TX rechazadas | K33: Incidencias | L33: 46072 | M33: 360300 | N33: te confirmamos que sí tenemos un abono. Hoy se solicitó un cambio de estado y podrás ver la modificación desde tu aplicación, así como el abono de la venta, en 1 día hábil en tu Saldo de Ventas Bold. | O33: Resuelto | P33: Pagos rechazados/no abonados/descontados
A34: Producto pagos | B34: C. Camilo Giraldo | C34: POSTOBON | D34: Postobon | E34: UKH72XS44S | F34: 46063 | G34: FEBRERO | H34: =YEAR(F34) -> 2026 | I34: 46072 | J34: TX rechazadas | K34: Incidencias | L34: 46072 | M34: 519000 | N34: te confirmamos que sí tenemos un abono. Hoy se solicitó un cambio de estado y podrás ver la modificación desde tu aplicación, así como el abono de la venta, en 1 día hábil en tu Saldo de Ventas Bold. | O34: Resuelto | P34: Pagos rechazados/no abonados/descontados
A35: Producto pagos | B35: C. Camilo Casas | C35: POSTOBON | D35: Postobon | E35: SE3RYFGAJY | F35: 46191 | G35: JUNIO | H35: =YEAR(F35) -> 2026 | I35: 46072 | J35: TX rechazadas | K35: Leidy rodriguez | L35: 46072 | M35: 95500 | N35: Hoy se solicitó un cambio de estado y podrás ver la modificación desde tu aplicación, así como el abono de la venta, en 1 día hábil en tu Saldo de Ventas Bold. | O35: Resuelto | P35: Pagos rechazados/no abonados/descontados
A36: Producto pagos | B36: C. Camilo Casas | C36: Colanta | D36: Colanta | E36: VY6VES3Z9R | F36: 46297 | G36: OCTUBRE | H36: =YEAR(F36) -> 2026 | I36: 46072 | J36: TX rechazadas | K36: Leidy rodriguez | L36: 46077 | M36: 173230 | N36: se encuentra transacción consignada por llave | O36: Resuelto | P36: Pagos rechazados/no abonados/descontados
A38: Producto pagos | B38: C. Camilo Casas | C38: POSTOBON | D38: Postobon | E38: CPKYDJ4IMOIJ | F38: 46108 | G38: MARZO | H38: 2026 | I38: 46111 | J38: TX rechazadas | K38: Leidy rodriguez | L38: 46118 | M38: 331200 | N38: sapena@postobon.com.co -te confirmamos que no tenemos abono en nuestra cuenta. Como muestra en tu aplicación, la transacción no fue exitosa. En el caso de que tu cliente final insista en que tiene el descuento, es necesario que él o ella solicite a su banco un certificado del cobro de esta misma con fecha posterior al 06/04/2026 para poder escalar el caso con la entidad financiera. | O38: Falta certificado | P38: Pagos rechazados/no abonados/descontados
A39: Producto pagos | B39: C. Camilo Giraldo | C39: POSTOBON | D39: Postobon | E39: TOM95X6WAO | F39: 46106 | G39: ABRIL | H39: 2026 | I39: 46113 | J39: TX rechazadas | K39: Leidy rodriguez | L39: 46119 | M39: 800000 | N39: aliviafara9@gmail.com Respecto a tu consulta realizada el día 01/04/2026, después de validar la transacción TAVTEU2H6OY por valor de $800.000 del pasado 25/03/2026, te confirmamos que sí tenemos un abono. Hoy se solicitó un cambio de estado y podrás ver la modificación desde tu aplicación, así como el abono de la venta, en 1 día hábil en tu Saldo de Ventas Bold. | O39: Resuelto | P39: Pagos rechazados/no abonados/descontados
A40: Producto pagos | B40: C. Camilo Giraldo | C40: POSTOBON | D40: Postobon | E40: 4VETEWDH1L | F40: 46122 | G40: ABRIL | H40: 2026 | I40: 46122 | J40: Payouts no identificados | K40: Camilo Giraldo | L40: 46123 | M40: -- | N40: obocanegra@postobon.com.co Buenas tardes. Con respecto a su consulta sobre los depósitos de los días 09 y 10 de abril, le informo que los pagos ya han sido procesados y enviados desde nuestra plataforma. La demora que se presenta actualmente en la recepción de los fondos se debe a los tiempos de procesamiento de los ciclos de ACH entre las entidades bancarias. Por este motivo, el dinero se verá reflejado en su cuenta de Bancolombia en el transcurso del día, dependiendo de los horarios de compensación de dicha red. te confirmo que los envios fueron realizados a tiempo, pero por los tiempos de transferencia ACH hacia Bancolombia u otros bancos es la novedad presentada. | O40: Resuelto | P40: Otro
A41: Producto pagos | B41: C. Camilo Giraldo | C41: POSTOBON | D41: Postobon | E41: SE3RYFGAJY | F41: 46128 | G41: ABRIL | H41: 2026 | I41: 46134 | J41: TX rechazadas | K41: Leidy rodriguez | L41: 46139 | M41: 113000 | N41: mamaldonado@gascol.com.co: informa que se genero cobro doble por 113.000/R/ Respecto a la consulta realizada el día 23/04/2026, después de validar la transacción TZGPF5VKF1V - TSZA4GMPPVZ - TZ9V0SLX6OB- T0VNHT9FFXT - T56Z25OJ862 - TDFKFEN7ZQT - TLAUMR4XY70 - TQCE6T55C13, cada una por valor de $113.000por medio de pago QR del pasado 16/04/2026, te confirmamos que no tenemos abono en nuestra cuenta. Como muestra en tu aplicación, la transacción no fue exitosa. Adicionalmente, te confirmamos que la transacción con ID: T4D3Z330654 , se encuentra aprobada y fue abonada a la cuenta del comercio. Hola Michel , Respecto a la consulta realizada el día 23/04/2026, después de validar la transacción TZGPF5VKF1V - TSZA4GMPPVZ - TZ9V0SLX6OB- T0VNHT9FFXT - T56Z25OJ862 - TDFKFEN7ZQT - TLAUMR4XY70 - TQCE6T55C13, cada una por valor de $113.000por medio de pago QR del pasado 16/04/2026, te confirmamos que no tenemos abono en nuestra cuenta. Como muestra en tu aplicación, la transacción no fue exitosa. Adicionalmente, te confirmamos que la transacción con ID: T4D3Z330654 , se encuentra aprobada y fue abonada a la cuenta del comercio. En el caso de que tu cliente final insista en que tiene el descuento, es necesario que él o ella solicite a su banco un certificado del cobro de esta misma con fecha posterior al 27/04/2026 para poder escalar el caso con la entidad financiera. | O41: Resuelto | P41: Pagos rechazados/no abonados/descontados
A42: Producto pagos | B42: C. Camilo Giraldo | C42: POSTOBON | D42: Postobon | E42: Q7VR1248VT | F42: 46131 | G42: ABRIL | H42: 2026 | I42: 46131 | J42: TX rechazadas, TX duplicadas | K42: Leidy rodriguez | L42: 46139 | M42: 900000 | N42: jnavas@postobon.com.co: se busco la TRX y se pago el dia 20 con el Payout | O42: Resuelto | P42: Pagos rechazados/no abonados/descontados
A43: Producto pagos | B43: C. Camilo Casas | C43: POSTOBON | D43: Postobon | E43: UKH72XS44S | F43: 46150 | G43: MAYO | H43: 2026 | I43: 46164 | J43: TX rechazadas | K43: Leidy rodriguez | L43: 46167 | M43: 72000 | N43: jvergararodrigue@gmail.comil.com /r/Respecto a la consulta realizada el día 22/05/2026, después de validar la transacción T54GTGJY6XB - T43Q65GU48B por valor de $72.000 cada una a través de QR del pasado 08/05/2026, te confirmamos que no tenemos abono en nuestra cuenta. Como muestra en tu aplicación, la transacción no fue exitosa. En el caso de que tu cliente final insista en que tiene el descuento, es necesario que él o ella solicite a su banco un certificado del cobro de esta misma con fecha posterior al 25/05/2026 para poder escalar el caso con la entidad financiera. | O43: Falta certificado | P43: Pagos rechazados/no abonados/descontados
A44: Producto pagos | B44: C. Camilo Casas | C44: POSTOBON | D44: Postobon | E44: UKH72XS44S | F44: 46150 | G44: MAYO | H44: 2026 | I44: 46153 | J44: TX rechazadas | K44: Leidy rodriguez | L44: 46156 | M44: 72000 | N44: atmontoya@postobon.com.co /R/ Respecto a la consulta realizada el día 11/05/2026, después de validar la transacción T43Q65GU48B por valor de $72.000 a través de QR del pasado 08/05/2026, te confirmamos que no tenemos abono en nuestra cuenta. Como muestra en tu aplicación, la transacción no fue exitosa. En el caso de que tu cliente final insista en que tiene el descuento, es necesario que él o ella solicite a su banco un certificado del cobro de esta misma con fecha posterior al 14/05/2026 para poder escalar el caso con la entidad financiera. | O44: Falta certificado | P44: Pagos rechazados/no abonados/descontados
A45: Producto pagos | B45: C. Camilo Giraldo | C45: POSTOBON | D45: Postobon | E45: SE3RYFGAJY | F45: 46052 | G45: ABRIL | H45: 2026 | I45: 46165 | J45: TX rechazadas | K45: Leydy rodriguez | L45: -- | M45: 97500 | N45: efrico@postobon.com.co /R// | O45: Resuelto | P45: Pagos rechazados/no abonados/descontados
A46: Producto pagos | B46: C. Camilo Casas | C46: POSTOBON | D46: Postobon | E46: 6RIMATJBDJ | F46: 46150 | G46: MAYO | H46: 2026 | I46: 46156 | J46: TX rechazadas | K46: Leidy rodriguez | L46: 46157 | M46: 100000 | N46: jjsanchez@postobon.com.co /R// es TRX por llaves de Breve no por Bold.co | O46: Resuelto | P46: Pagos rechazados/no abonados/descontados
A47: Producto pagos | B47: C. Camilo Giraldo | C47: POSTOBON | D47: Postobon | E47: QBLW9W0FGB | F47: 46148 | G47: MAYO | H47: 2026 | I47: 46161 | J47: TX rechazadas | K47: Leidy rodriguez | L47: 46167 | M47: 184700 | N47: vanchris1401@gmail.com /R// Respecto a tu consulta realizada el día 22/05/2026, después de validar la transacción T2S752NHSVB por valor de $184.700 a través de QR del pasado 06/05/2026, te confirmamos que sí tenemos un abono. Hoy se solicitó un cambio de estado y podrás ver la modificación desde tu aplicación, así como el abono de la venta, en 1 día hábil en tu Saldo de Ventas Bold. | O47: Resuelto | P47: Pagos rechazados/no abonados/descontados
A48: Producto pagos | B48: C. Camilo Casas | C48: POSTOBON | D48: Postobon | E48: 6RIMATJBDJ | F48: 46151 | G48: MAYO | H48: 2026 | I48: 46162 | J48: TX rechazadas | K48: Leidy rodriguez | L48: 46163 | M48: 495278 | N48: cbarajas@postobon.com.co //R// Respecto a tu consulta realizada el día 20/05/2026, después de validar la transacción TET17X46HQB por valor de $495.278 a través de QR del pasado 09/05/2026, te confirmamos que sí tenemos un abono. Hoy se solicitó un cambio de estado y podrás ver la modificación desde tu aplicación, así como el abono de la venta, en 1 día hábil en tu Saldo de Ventas Bold. | O48: Resuelto | P48: Pagos rechazados/no abonados/descontados
A49: Producto pagos | B49: C. Camilo Giraldo | C49: POSTOBON | D49: Postobon | E49: 6RIMATJBDJ | F49: 46150 | G49: MAYO | H49: 2026 | I49: 46162 | J49: TX rechazadas | K49: Leydy rodriguez | L49: 46163 | M49: 100000 | N49: jcrodriguezc@postobon.com.co //R// Respecto a tu consulta realizada el día 20/05/2026, después de validar la transacción TKE3QPMIDPJ por valor de $100.000 a través de QR del pasado 08/05/2026, te confirmamos que sí tenemos un abono. Hoy se solicitó un cambio de estado y podrás ver la modificación desde tu aplicación, así como el abono de la venta, en 1 día hábil en tu Saldo de Ventas Bold. Si tienes alguna duda adicional, estamos atentos para ayudarte. | O49: Resuelto | P49: Pagos rechazados/no abonados/descontados
A50: Producto pagos | B50: C. Camilo Casas | C50: POSTOBON | D50: Postobon | F50: 46106 | G50: MARZO | H50: 2026 | I50: 46164 | J50: TX rechazadas | K50: Leidy rodriguez | L50: 46167 | M50: 634000 | N50: jcrodriguezc@postobon.com.co //R// Respecto a tu consulta realizada el día 22/05/2026, después de validar la transacción T4PJE5PF03Y por valor de $634.000 a través de QR del pasado 25/03/2026, te confirmamos que sí tenemos un abono. Hoy se solicitó un cambio de estado y podrás ver la modificación desde tu aplicación, así como el abono de la venta, en 1 día hábil en tu Saldo de Ventas Bold. | O50: Resuelto | P50: Pagos rechazados/no abonados/descontados
A51: Producto pagos | C51: POSTOBON | D51: Postobon | E51: TZA2JMQCEUK - TDC36KG21JB - TWOECYY0OOW - TPH4U47CZ69 | F51: 46150 | G51: MAYO | H51: 2026 | I51: 46161 | J51: TX rechazadas, TX duplicadas | K51: Leidy rodriguez | L51: 46163 | M51: 810750 | N51: ypenao@postobon.com.co //R// Respecto a la consulta realizada el día 19/05/2026, después de validar la transacción TZA2JMQCEUK - TDC36KG21JB - TWOECYY0OOW por valor de $810.750 cada una a través de QR del pasado 08/05/2026, te confirmamos que no tenemos abono en nuestra cuenta. Como muestra tu aplicación, la transacción no fue exitosa. En el caso de que tu cliente final insista en que tiene el descuento, es necesario que él o ella solicite a su banco un certificado del cobro de esta misma con fecha posterior al 21/05/2026 para poder escalar el caso con la entidad financiera. Solo evidenciamos un abono y es de la venta aprobada TPH4U47CZ69, la cual fue abonada con éxito a la cuenta que tienes registrada. Esperamos que esta información te haya sido de ayuda. | O51: Resuelto | P51: Pagos rechazados/no abonados/descontados
A52: Producto pagos | B52: C. Camilo Giraldo | C52: POSTOBON | D52: Postobon | E52: TKPXMWJHW98 - TCTLJY4ISWZ | F52: 46195 | G52: JUNIO | I52: 46196 | J52: TX rechazadas | K52: Leidy Rodriguez | L52: 46197 | M52: 600000 | N52: lrojas@postobon.com.co | O52: Resuelto | P52: Pagos rechazados/no abonados/descontados
A53: Producto pagos | B53: C. Camilo Giraldo | C53: POSTOBON | D53: Postobon | E53: TKPXMWJHW98 - TCTLJY4ISWZ | F53: 46195 | G53: JULIO | I53: 46206 | J53: TX rechazadas | K53: Leidy Rodriguez | L53: -- | M53: 600000 | N53: lrojas@postobon.com.co | O53: Resuelto | P53: Pagos rechazados/no abonados/descontados
A54: Producto pagos | B54: C. Camilo Casas | C54: POSTOBON | D54: Postobon | E54: TJMW56ZV0YX | F54: 46211 | G54: JULIO | H54: 2026 | I54: 46220 | J54: TX rechazadas | K54: Leidy Rodriguez | L54: 46226 | M54: 440000 | N54: después de validar la transacción TW4G4MSHDCK por valor de $915.000 del pasado 20/01/2026, te confirmamos que sí tenemos un abono. Hoy se solicitó un cambio de estado y podrás ver la modificación desde tu aplicación, así como el abono de la venta, en 1 día hábil en tu Saldo de Ventas Bold. | O54: Resuelto | P54: Pagos rechazados/no abonados/descontados
A55: Producto pagos | B55: C. Camilo Casas | C55: POSTOBON | D55: Postobon | E55: T88N5LDLQUJ | F55: 46211 | G55: JULIO | H55: 2026 | I55: 46220 | J55: TX rechazadas | K55: Leidy Rodriguez | L55: 46226 | M55: 257850 | N55: QR presenta novedad se coloca valor X aparece otro valor en el app del cliente al momento de scanear usuario salo0520sebas@gmail.com | O55: Resuelto | P55: Pagos rechazados/no abonados/descontados
A56: Producto pagos | B56: C. Camilo Giraldo | C56: POSTOBON | D56: Postobon | E56: TU6YLCJKGOR | F56: 46211 | G56: JULIO | H56: 2026 | I56: 44022 | J56: TX rechazadas | K56: Leidy Rodriguez | L56: 46226 | M56: 374800 | N56: después de validar la transacción TRRNTDA5IQ5 por valor de $1.658.000 del pasado 20/01/2026, te confirmamos que sí tenemos un abono. Hoy se solicitó un cambio de estado y podrás ver la modificación desde tu aplicación, así como el abono de la venta, en 1 día hábil en tu Saldo de Ventas Bold. | O56: Resuelto | P56: Pagos rechazados/no abonados/descontados
A57: Producto pagos | B57: C. Camilo Giraldo | C57: POSTOBON | D57: Postobon | E57: TMH8CJ8IJ0Q - TIYR44OC49X | F57: 46214 | G57: JULIO | H57: 2026 | I57: 46219 | J57: TX rechazadas | K57: Leidy Rodriguez | L57: 46227 | M57: 305000 | N57: después de validar la transacción TSQN2T5WZFI por valor de $245.000 del pasado 20/01/2026, te confirmamos que sí tenemos un abono. Hoy se solicitó un cambio de estado y podrás ver la modificación desde tu aplicación, así como el abono de la venta, en 1 día hábil en tu Saldo de Ventas Bold. | O57: Resuelto | P57: Pagos rechazados/no abonados/descontados
A58: Producto pagos | B58: C. Camilo Giraldo | C58: POSTOBON | D58: Postobon | E58: TTN1MKMXTUD | F58: 46211 | G58: JULIO | H58: 2026 | I58: 46212 | J58: TX rechazadas | K58: Leidy Rodriguez | L58: 46226 | M58: 233951 | N58: después de validar la transacción TJ5OTA5TFIR por valor de $2.315.000 del pasado 20/01/2026, te confirmamos que sí tenemos un abono. Hoy se solicitó un cambio de estado y podrás ver la modificación desde tu aplicación, así como el abono de la venta, en 1 día hábil en tu Saldo de Ventas Bold. | O58: Resuelto | P58: Pagos rechazados/no abonados/descontados
A59: Tecnologia | B59: C. Camilo Giraldo | C59: TTB | D59: TTB | E59: JA82FIY0Z4 | F59: 46231 | G59: JULIO | H59: 2026 | I59: 46231 | J59: Peticion | K59: Felipe Rodriguez | L59: 46231 | M59: -- | N59: Se envian a validar los datafonos en cuanto a datos a ilimitados, Felipe informa que todas las sim de estos equiupos son movistar y tienen plan ilimtado | O59: Resuelto
A60: Tecnologia | B60: C. Camilo Giraldo | C60: POSTOBON | D60: Postobon | E60: UKH72XS44S | F60: 46212 | G60: JULIO | H60: 2026 | I60: 46212 | J60: Error ingreso App | K60: Jorge marin | L60: 46219 | M60: -- | N60: a el usuario heydervale@gmail.com no le estaba llegando mensaje para ca,bio de contraseña | O60: Resuelto | P60: Ingreso a plataforma
A61: Producto pagos | B61: C. Camilo Giraldo | C61: POSTOBON | D61: Postobon | E61: L7QZVRPNHB | F61: 46212 | G61: JULIO | H61: 2026 | I61: 46212 | J61: Solicitudes a Producto | K61: john lancheros | L61: 46212 | M61: -- | N61: Se eliminan efectivo y nequi | O61: Resuelto | P61: Otro
A62: Producto pagos | B62: C. Camilo Giraldo | C62: POSTOBON | D62: Postobon | E62: L7QZVRPNHB | F62: 46212 | G62: JULIO | H62: 2026 | I62: 46212 | J62: Onboarding - Registro | K62: john lancheros | L62: 46212 | M62: -- | N62: Nuevo comercio de postobon en verificacion, se íde activar, logra quedar activo el mismo dia | O62: Resuelto | P62: Otro
A63: Producto pagos | B63: C. Camilo Giraldo | C63: COLANTA | D63: Colanta | E63: L7QZVRPNHB | F63: 46212 | G63: JULIO | H63: 2026 | I63: 46212 | J63: Impuestos | K63: David Rodriguez | L63: 46213 | M63: -- | N63: Se envia proyecto tienda cerkna a marcar en impuestos como los demas de POSTOBON | O63: Resuelto | P63: Errores tributarios
A64: Producto pagos | B64: C. Camilo Giraldo | C64: POSTOBON | D64: Postobon | E64: TODOS LOS MERCHANT | F64: 46209 | G64: JULIO | H64: 2026 | I64: 46209 | J64: Error en reporteria | K64: Be Romero | L64: 46211 | M64: -- | N64: todos los merchant estan presentando error al generar, cuando se soluciono se observa cambios en el modelo de reportes, por lo cual se solicta volver al modelo anterior ya que no logran conciliar asi | O64: Resuelto | P64: Error en reportes
A65: Producto pagos | B65: C. Camilo Giraldo | C65: POSTOBON | D65: Postobon | E65: TODOS LOS MERCHANT | F65: 46203 | G65: JUNIO | H65: 2026 | I65: 46189 | J65: Impuestos | K65: Lu Sanchez | L65: 46203 | M65: 748438 | N65: tuvimos intermitencia en *mayo 30 23:48 - 2 jun 9:33*. // postobon nos solicita la devolucion de estos impuestos o retenciones generados para no tener quiza un error en el momento de la liquidacion de comision. | O65: Resuelto | P65: Errores tributarios
A66: Producto pagos | B66: C. Camilo Giraldo | C66: POSTOBON | D66: Postobon | E66: DKFDV7RLFX | F66: 46189 | G66: JUNIO | H66: 2026 | I66: 46192 | J66: Payouts no identificados | K66: Andres espitia | L66: 46198 | M66: 1400000 | N66: eran TRx de otra fecha se valida y llega al payout siguiente | O66: Resuelto | P66: Payout
A67: Producto pagos | B67: C. Camilo Giraldo | C67: POSTOBON | D67: Postobon | E67: T4SVFAGV630 | F67: 46189 | G67: JUNIO | H67: 2026 | I67: 46193 | J67: TX rechazadas | K67: Leidy Rodriguez | L67: 46205 | M67: 867148 | N67: PENDIENTE CERTIFICADO DE COBRO / ID TRANSACCIÓN | O67: Resuelto | P67: Pagos rechazados/no abonados/descontados
A68: Producto pagos | B68: C. Camilo Giraldo | C68: POSTOBON | D68: Postobon | E68: TH7MNM667IZ | F68: 46211 | G68: JULIO | H68: 2026 | I68: 46220 | J68: TX rechazadas | K68: Leidy Rodriguez | L68: 46221 | M68: 350402 | N68: después de validar la transacción TC6H5UF8V7B por valor de $101.100 del pasado 20/01/2026, te confirmamos que sí tenemos un abono. Hoy se solicitó un cambio de estado y podrás ver la modificación desde tu aplicación, así como el abono de la venta, en 1 día hábil en tu Saldo de Ventas Bold. | O68: Falta certificado | P68: Pagos rechazados/no abonados/descontados
A69: Producto pagos | B69: C. Camilo Casas | C69: POSTOBON | D69: Postobon | E69: TMG1RJVA4R0, TVF3GIGHZVI, T99KDKLN86W | F69: 46208 | G69: JULIO | H69: 2026 | I69: 46212 | J69: TX rechazadas | K69: Leidy Rodriguez | L69: 46225 | M69: 746499 | N69: después de validar la transacción TPN2EQAQ91K por valor de $155.100 del pasado 15/01/2026, te confirmamos que sí tenemos un abono. Hoy se solicitó un cambio de estado y podrás ver la modificación desde tu aplicación, así como el abono de la venta, en 1 día hábil en tu Saldo de Ventas Bold. | O69: Resuelto | P69: Pagos rechazados/no abonados/descontados
A70: Producto pagos | B70: C. Camilo Giraldo | C70: POSTOBON | D70: Postobon | E70: T7AAQJ8F0AR | F70: 46164 | G70: ABRIL | H70: 2026 | I70: 46172 | J70: TX rechazadas | K70: Leidy Rodriguez | L70: 46182 | M70: 600000 | N70: Se evidencia que las txs por QR no le estamos cobrando la comisión, es una falla en la API de Pagos, Producto está revisando la solución pronta. | O70: Resuelto | P70: Pagos rechazados/no abonados/descontados
A71: Producto pagos | B71: C. Camilo Casas | C71: POSTOBON | D71: Postobon | E71: TIMIB612IH8 | F71: 46174 | G71: MAYO | H71: 2026 | I71: 46176 | J71: TX rechazadas | K71: Leidy Rodriguez | L71: 46182 | M71: 1528072 | N71: Se evidencia diferencias en la longitud de caracteres en el campo "REALIZADO POR" de la estructura de Cierre de Turno, está ciendo revisada por el equipo de TI. | O71: Falta certificado | P71: Pagos rechazados/no abonados/descontados
A72: Producto pagos | B72: C. Camilo Giraldo | C72: POSTOBON | D72: Postobon | E72: TCZWEGT34MM, TGDO4LRCA91, T3F6S461JQD | F72: 46174 | G72: MAYO | H72: 2026 | I72: 46178 | J72: TX rechazadas | K72: Leidy Rodriguez | L72: 46182 | M72: 133500 | N72: Se evidencia que las txs por QR no le estamos cobrando la comisión, es una falla en la API de Pagos, Producto está revisando la solución pronta. | O72: Falta certificado | P72: Pagos rechazados/no abonados/descontados
A73: Producto pagos | B73: C. Camilo Giraldo | C73: POSTOBON | D73: Postobon | E73: TQ74M6YGHOB | F73: 46224 | G73: AGOSTO | H73: 2026 | I73: 46241 | J73: TX rechazadas | K73: Be Romero | L73: 46244 | M73: 419600 | N73: Se evidencia diferencias en la longitud de caracteres en el campo "REALIZADO POR" de la estructura de Cierre de Turno, está ciendo revisada por el equipo de TI. | O73: Falta certificado | P73: Pagos rechazados/no abonados/descontados
A74: Producto pagos | B74: C. Camilo Giraldo | C74: POSTOBON | D74: Postobon | E74: CPKYDJ4IMOIJ | F74: 15 /8/2026 | G74: AGOSTO | H74: 2026 | I74: 46252 | J74: TX rechazadas | K74: Leidy Rodriguez | L74: -- | M74: 308700 | N74: se solicita certificado de la trx | O74: Falta certificado | P74: Pagos rechazados/no abonados/descontados
A75: Producto pagos | B75: C. Camilo Giraldo | C75: POSTOBON | D75: Postobon | E75: TOM95X6WAO | F75: 46249 | G75: AGOSTO | H75: 2026 | I75: 46244 | J75: TX rechazadas | K75: Leidy Rodriguez | L75: -- | M75: 212300 | N75: no se encontro el abono | O75: Resuelto | P75: Pagos rechazados/no abonados/descontados
A76: Producto pagos | B76: C. Camilo Giraldo | C76: POSTOBON | D76: Postobon | E76: TURV1HEZ141 | F76: 46250 | G76: AGOSTO | H76: 2026 | I76: 46237 | J76: TX rechazadas | K76: Leidy Rodriguez | M76: 195700 | N76: no se encontro el abono | O76: Resuelto | P76: Pagos rechazados/no abonados/descontados
A77: Producto pagos | B77: C. Camilo Giraldo | C77: POSTOBON | D77: Postobon | E77: TWFVI1LGUU7 | F77: 46255 | G77: AGOSTO | H77: 2026 | I77: 46258 | J77: TX rechazadas | K77: Leidy Rodriguez | L77: 46261 | M77: 1500000 | N77: SI ESTA EN UN DIA HABIL ESTARA EN TU CUENTA | O77: Resuelto | P77: Pagos rechazados/no abonados/descontados
A78: Producto pagos | B78: C. Camilo Giraldo | C78: POSTOBON | D78: Postobon | E78: TEMQTGDV7RU | F78: 46249 | G78: AGOSTO | H78: 2026 | I78: 46258 | J78: TX rechazadas | L78: 46262 | M78: 179300 | N78: SI ESTA EN UN DIA HABIL ESTARA EN TU CUENTA | O78: Resuelto | P78: Pagos rechazados/no abonados/descontados
A79: Producto pagos | B79: C. Camilo Giraldo | C79: POSTOBON | D79: Postobon | E79: #INC: 01697 | F79: 46262 | G79: AGOSTO | H79: 2026 | I79: 46262 | J79: Falla QR | K79: https://bold.enterprise.slack.com/archives/C0BTH0X900J | L79: 46265 | M79: -- | N79: se recibieron 21 correos con informe de las plantas afectadas mas de 350 trx afectadas / El dia 31 cambian de estado todos los retenidos y se envia un comunicado a todas las cajas a nivel nacional | O79: Resuelto | P79: Fallas QR
A80: Tecnologia | B80: C. Camilo Giraldo | C80: TTB | D80: TTB | E80: BTJHGRLYXZ | F80: 46261 | G80: AGOSTO | H80: 2026 | I80: 46261 | J80: Error ingreso App | K80: Camilo Giraldo | L80: 46261 | M80: -- | N80: se envian usuario y contraseñas de usuario limitados ttb | O80: Resuelto | P80: Ingreso a plataforma
A81: Producto pagos | B81: C. Camilo Giraldo | C81: POSTOBON | D81: Postobon | E81: Y5CUZZXX7J | F81: 46230 | G81: JULIO | H81: 2026 | I81: 46230 | J81: Falla QR | K81: ITLEVEL1-26048 | L81: -- | M81: 4029300 | N81: fue error del QR se estaba llendo el dinero aCF | O81: Pendiente | P81: Payout
A82: Producto pagos | B82: C. Camilo Giraldo | C82: COLANTA | D82: Colanta | E82: X6YO81UJK6 | F82: 46239 | G82: AGOSTO | H82: 2026 | I82: 46239 | J82: Payouts no identificados | K82: Aldemar jerez | L82: 46269 | M82: 633115 | N82: se estaba llendo el dinero a cuenta Cf, se corrige y envia el dinero a cuenta bbva | O82: Resuelto
A83: Producto pagos | B83: C. Camilo Giraldo | C83: COLANTA | D83: Colanta | E83: X6YO81UJK6 | F83: 46258 | G83: AGOSTO | H83: 2026 | I83: 46265 | J83: Payouts no identificados | K83: william mosquera | L83: 46269 | M83: 412517 | N83: faltaba dinero en el Payout del dia, el dia viernes 4 de sep. dan a respuesta | O83: Resuelto | P83: Payout
A84: Tecnologia | B84: C. Camilo Giraldo | C84: POSTOBON | D84: Postobon | E84: L7QZVRPNHB | F84: 46262 | G84: AGOSTO | H84: 2026 | I84: 46262 | J84: Error ingreso App | K84: Be Romero | L84: 46262 | M84: -- | N84: Usuario nonpodia ingresar | O84: Resuelto | P84: Ingreso a plataforma
A85: Tecnologia | B85: C. Camilo Giraldo | C85: POSTOBON | D85: Postobon | E85: UKH72XS44S | F85: 46252 | G85: AGOSTO | H85: 2026 | I85: 46253 | J85: Error en reporteria | K85: Isabel osorio | L85: -- | M85: -- | N85: no puede generar el mes de julio, Piix informa que esun error con varios usuarios aun no pueden, se solicita ajuan carlos generarlo con la nueva reporteria, quedamos qtentos | O85: Pendiente | P85: Error en reportes
A86: Producto pagos | B86: C. Camilo Giraldo | C86: COLANTA | D86: Colanta | E86: TODOS LOS MERCHANT | F86: 46249 | G86: AGOSTO | H86: 2026 | I86: 46255 | J86: Impuestos | K86: Sara lopez | L86: 46268 | M86: -- | N86: os comercios fueron marcados como regimen SPECIAL_TAX_REGIMEN_NO_ICA, | O86: Resuelto | P86: Errores tributarios
A87: Tecnologia | B87: C. Camilo Giraldo | C87: TTB | D87: TTB | E87: JA82FIY0Z4 | F87: 46261 | G87: AGOSTO | H87: 2026 | I87: 46261 | J87: Conectividad - Datos | K87: Jorgue Marin | L87: 46261 | M87: -- | N87: Equipo no contaba con datos | O87: Resuelto | P87: Datos - Internet - Conectividad
A88: Producto pagos | B88: C. Camilo Giraldo | C88: COLANTA | D88: Colanta | E88: PA80NXKNGV | F88: 46253 | G88: AGOSTO | H88: 2026 | I88: 46254 | J88: Impuestos | K88: David Rodriguez | L88: 46260 | M88: -- | N88: David Rodriguez informa viejo Camilo, estuvimos revisando y de nuestro lado estamos ok. Puedes revisar en la tab de reterenta en backoffice. | O88: Resuelto | P88: Errores tributarios
A89: Producto pagos | B89: C. Camilo Giraldo | C89: COLANTA | D89: Colanta | E89: X6YO81UJK6 | F89: 46239 | G89: AGOSTO | H89: 2026 | I89: 5/8/0206 | J89: Payouts no identificados | K89: Aldemar Jerez | L89: 46238 | M89: -- | N89: El dinero de estaba llendo a cuenta CF, al dinal erika transfirio los fondos y asumio el4x1000 | O89: Resuelto | P89: Payout
A90: Producto pagos | B90: C. Camilo Giraldo | C90: POSTOBON | D90: Postobon | E90: Z2LOEMM4GD | F90: 46216 | G90: AGOSTO | H90: 2026 | I90: 46247 | J90: Error ingreso App | K90: Be Romero | L90: 46247 | M90: -- | N90: No permitia crear el usuario, se manda a liberar correo e intentarlo de nuevo | O90: Resuelto | P90: Ingreso a plataforma
A91: Producto pagos | B91: C. Camilo Giraldo | C91: POSTOBON | D91: Postobon | E91: Q7VR1248VT | F91: 46245 | G91: AGOSTO | H91: 2026 | I91: 46245 | J91: TX rechazadas | K91: Be Romero | L91: 46245 | M91: 419600 | N91: La TRRx no salio de cuenta deposito, fue TRX por llave | O91: Resuelto | P91: Pagos rechazados/no abonados/descontados
A92: Producto pagos | B92: C. Camilo Giraldo | C92: POSTOBON | D92: Postobon | E92: UKH72XS44S | F92: 46237 | G92: AGOSTO | H92: 2026 | I92: 46237 | J92: Error ingreso App | K92: Tatiana tovar | L92: 46244 | M92: -- | N92: No permitia crear el usuario, se manda a liberar correo e intentarlo de nuevo | O92: Resuelto | P92: Ingreso a plataforma
A93: Tecnologia | B93: C. Camilo Giraldo | C93: TTB | D93: TTB | E93: BTJHGRLYXZ | F93: 46239 | G93: AGOSTO | H93: 2026 | I93: 46240 | J93: Peticion | K93: Felipe Rodriguez | L93: 46240 | M93: -- | N93: Se envian a validar los datafonos en cuanto a datos a ilimitados, nos responde Felipe que los unicos que admiten plan ilimitados son Sim movistar, por el momento estan con el plan mas alto los claro | O93: Resuelto | P93: Datos - Internet - Conectividad
A94: Producto pagos | B94: C. Camilo Giraldo | C94: POLLO ANDINO | D94: Pollo Andino | E94: DM4WDP0K9Y | F94: 46237 | G94: AGOSTO | H94: 2026 | I94: 46237 | J94: Solicitudes a Producto | K94: Sara Medina | L94: 46237 | M94: -- | N94: Se envia a Desactivar efectivo yNequi | O94: Resuelto | P94: Otro
A95: Producto pagos | B95: C. Camilo Giraldo | C95: POSTOBON | D95: Postobon | E95: UKH72XS44S | F95: 46237 | G95: AGOSTO | H95: 2026 | I95: 46237 | J95: Error ingreso App | K95: diego Cruz | L95: 46237 | M95: -- | N95: No permitia crear el usuario, se manda a liberar correo e intentarlo de nuevo | O95: Resuelto
A96: Tecnologia | B96: C. Camilo Giraldo | C96: POSTOBON | D96: Postobon | E96: Nit: 800090890 Nutrimenti S.A.S. | F96: 46267 | G96: SEPTIEMBRE | H96: 2026 | I96: 46267 | J96: Onboarding - Registro | K96: Cindid Daza | L96: 46267 | M96: -- | N96: se estaba creando un nuevo merchant para postobon, pero desistieron por temas de ellos internos, por lo cual se manda a eliminar y liberar el correo para futuro registro | O96: Resuelto | P96: Otro
A97: RISK | B97: C. Camilo Giraldo | C97: COLANTA | D97: Colanta | E97: VY6VES3Z9R | F97: 46266 | G97: SEPTIEMBRE | H97: 2026 | I97: 46266 | J97: Bloqueo | K97: jhonathan rojas | L97: 46266 | M97: -- | N97: Se bloquearon los comercios de colanta, por que estaban cambiando combres de comercio interna mente | O97: Resuelto | P97: Ingreso a plataforma
A98: Tecnologia | B98: C. Camilo Giraldo | C98: POSTOBON | D98: Postobon | E98: TODOS POSTOBON | F98: 46269 | G98: SEPTIEMBRE | H98: 2026 | I98: 46269 | J98: erroe en reporteria | K98: alejandro vivas | L98: 46272 | M98: -- | N98: Error en reporteria solo de link de pago ( sesoluciona enviando a postobon a el nuevo medio de reporteria) | O98: Resuelto | P98: Error en reportes
A99: Tecnologia | B99: C. Camilo Giraldo | C99: TTB | D99: TTB | E99: JA82FIY0Z4 | F99: 46269 | G99: SEPTIEMBRE | H99: 2026 | I99: 46269 | J99: Suplantacionde comercios | K99: Alex ospina | L99: 46269 | M99: -- | N99: Estaban suplantando a TTB, Se genera la detención del comercio 8811JX0BJJ que era desde donde estaban generando los QR | O99: Resuelto | P99: Error de seguridad
A100: Tecnologia | B100: C. Camilo Casas | C100: TTB | D100: TTB | E100: JA82FIY0Z4 | F100: 46274 | G100: SEPTIEMBRE | H100: 2026 | I100: 46274 | J100: Error en reporteria | K100: David aparicio | L100: 46274 | N100: novedad que presenta KIbana | O100: Resuelto | P100: Errores o Fallas cuenta BOLD
A101: Tecnologia | B101: C. Camilo Casas | C101: COLANTA | D101: Colanta | E101: VY6VES3Z9R | F101: 46274 | G101: SEPTIEMBRE | H101: 2026 | I101: 46274 | J101: Error ingreso App | K101: Carlos manrrique | L101: 46274 | N101: se presenta novedad en QR cambio de nombre | O101: Resuelto | P101: Fallas QR
...

Sheet OPERACIONES - MASIVOS
A1: PROYECTO | B1: RAZON SOCIAL | C1: MERCHANT-ID | D1: PRICIN ASIGNADO | E1: IMPUESTOS DesMarcados | F1: QR Agregador ON? | G1: PRODUCTOS OFF | H1: COMENTARIOS-NOVEDAD | I1: NIT | J1: DIRECCION | K1: ENCARGADO | L1: TELEFONO | M1: # CUENTA INSCRITA | N1: IMPLEMENTACION
A2: POSTOBON | B2: GASEOSAS LUX | C2: UKH72XS44S | D2: 0 | E2: Si | F2: Si | G2: Nequi, Efectivo | I2: 860001697 | J2: POSTOBON CALLE 80 BOGOTA / Km 0 + 435 Mts Punta Redonda Vía Siberia / CALLE 80 | K2: MARIA CAMILA ALVAREZ | L2: 3113874244 | M2: 24156243887 / BANCOLOMBIA | N2: LINK-QR
A3: POSTOBON | B3: GASEOSAS LUX | C3: QBLW9W0FGB | D3: 0 | E3: Si | F3: Si | G3: Nequi, Efectivo | I3: 860001697 | J3: PLANTA SEVILLANA BOGOTA LUX SUR | K3: MARIA CAMILA ALVAREZ | L3: 3113874244 | M3: 24500017464 / BANCOLOMBIA | N3: LINK-QR
A4: POSTOBON | B4: GASEOSAS LUX SAS | C4: DKFDV7RLFX | D4: 0 | E4: Si | F4: Si | G4: Nequi, Efectivo | I4: 860001697 | J4: AVENIDA - CALLE 9 # 50 - 85 SAN RAFAEL / | K4: MARIA CAMILA ALVAREZ | L4: 3113874244 | M4: 95632881 / BANCO DE BOGOTA | N4: LINK-QR
A5: POSTOBON | B5: GASEOSAS LUX SAS | C5: SE3RYFGAJY | D5: 0 | E5: Si | F5: Si | G5: Nequi, Efectivo | I5: 860001697 | J5: AC. 17 #39 / ZONA INDUSTRIAL | K5: MARIA CAMILA ALVAREZ | L5: 3113874244 | M5: 24156243887 / BANCOLOMBIA | N5: LINK-QR
A6: POSTOBON | B6: POSTOBON SA | C6: 6RIMATJBDJ | D6: 0 | E6: Si | F6: Si | G6: Nequi, Efectivo | I6: 890903939 | J6: CALLE 62 #44-77 AUTOPISTA SUR / POSTOBON ITAGUI | K6: MARIA CAMILA ALVAREZ | L6: 3113874244 | M6: 26833507931/ BANCOLOMBIA | N6: LINK-QR
A7: POSTOBON | B7: POSTOBON SA | C7: 4VETEWDH1L | D7: 0 | E7: Si | F7: Si | G7: Nequi, Efectivo | I7: 890903939 | J7: CALLE 52 # 47-42, Edificio Coltejer / POSTOBON BELLO | K7: MARIA CAMILA ALVAREZ | L7: 3113874244 | M7: 10032775656/ BANCOLOMBIA | N7: LINK-QR
A8: POSTOBON | B8: POSTOBON SA | C8: 6085Z6TTB7 | D8: 0 | E8: Si | F8: Si | G8: Nequi, Efectivo | H8: LINK DE APGO | I8: 890903939 | J8: Calle 52 # 47 - 42 / EDIFICIO COLTEJER / USUARIOS DOSQUEBRADAS/ | K8: MARIA CAMILA ALVAREZ | L8: 3113874244 | M8: 72501305555/ BANCOLOMBIA | N8: LINK-QR
A9: POSTOBON | B9: POSTOBON SA | C9: TOM95X6WAO | D9: 0 | E9: Si | F9: Si | G9: Nequi, Efectivo | I9: 890903939 | J9: SEDES. YUMBO-ZARSAL-BUGA-BUENAVENTURA-POPAYAN-JAMUNDI | K9: MARIA CAMILA ALVAREZ | L9: 3113874244 | M9: 245000182697 / BANCOLOMBIA | N9: LINK-QR
A10: POSTOBON | B10: POSTOBON SA | C10: 053AM2S3L4 | D10: 0 | E10: Si | F10: Si | G10: Nequi, Efectivo | I10: 890903939 | J10: Cucuta - Pamplona santander | K10: MARIA CAMILA ALVAREZ | L10: 3113874244 | M10: 24500003179 / BANCOLOMBIA | N10: LINK-QR
A11: POSTOBON | B11: POSTOBON SA | C11: Q7VR1248VT | D11: 0 | E11: Si | F11: Si | G11: Nequi, Efectivo | I11: 860001697 | J11: Piedecuesta-bucaramanga-giron-florida blanca | K11: MARIA CAMILA ALVAREZ | L11: 3113874244 | M11: 24500016809 / BANCOLOMBIA | N11: LINK-QR
A12: POSTOBON | B12: POSTOBON SA | C12: Z2LOEMM4GD | D12: 0 | E12: Si | F12: Si | G12: Nequi, Efectivo | I12: 890903939 | J12: Dg. 21 #54-40, Zapatero, Cartagena de Indias, Provincia de Cartagena, Bolívar | K12: MARIA CAMILA ALVAREZ | L12: 3113874244 | M12: 200020364 / BANCOLOMBIA | N12: LINK-QR
A13: POSTOBON | B13: POSTOBON SA | C13: 79GCNR6OJO | D13: 0 | E13: Si | F13: Si | G13: Nequi, Efectivo | I13: 890903939 | J13: MALAMBO BARRAQUILLA | K13: MARIA CAMILA ALVAREZ | L13: 3113874244 | M13: 24500010488 / BANCOLOMBIA | N13: LINK-QR
A14: POSTOBON | B14: GASEOSAS LUX | C14: R6S43QK37T | D14: 0 | E14: Si | F14: Si | G14: Nequi, Efectivo | I14: 860001697 | J14: Cra. 24a # 14-47, Villavicencio, Meta | K14: MARIA CAMILA ALVAREZ | L14: 3113874244 | M14: 24500003183 / BANCOLOMBIA | N14: LINK-QR
A15: POSTOBON | B15: GASEOSAS LUX | C15: PU7SF6NZY0 | D15: 0 | E15: Si | F15: Si | G15: Nequi, Efectivo | I15: 860001697 | J15: 40, Ibagué, Tolima | K15: MARIA CAMILA ALVAREZ | L15: 3113874244 | M15: 24500003184 / BANCOLOMBIA | N15: LINK-QR
A16: POSTOBON | B16: GASEOSAS LUX | C16: Y5CUZZXX7J | D16: 0 | E16: Si | F16: Si | G16: Nequi, Efectivo | I16: 860001697 | J16: Valledupar | K16: MARIA CAMILA ALVAREZ | L16: 3113874244 | M16: 24500003181 /BANCOLOMBIA | N16: LINK-QR
A17: POSTOBON | B17: GASEOSAS LUX | C17: SCXKIXA5L6 | D17: 0 | E17: Si | F17: Si | G17: Nequi, Efectivo | I17: 860001697 | J17: 23-357, Cra 5 #23-135, Neiva, Huila | K17: MARIA CAMILA ALVAREZ | L17: 3113874244 | N17: LINK-QR
A18: POSTOBON | B18: POSTOBON SA | C18: 8GCLJOWKQF | D18: 0 | E18: Si | F18: Si | G18: Nequi, Efectivo | I18: 890903939 | J18: Cra. 21a #28D-53, Comuna 4, Santa Marta, Magdalena | K18: MARIA CAMILA ALVAREZ | L18: 3113874244 | N18: LINK-QR
A19: POSTOBON | B19: GASEOSAS LUX | C19: GLKD99RUI4 | D19: 0 | E19: Si | F19: Si | G19: Nequi, Efectivo | I19: 860001697 | J19: Barrancabermeja / Gaseosas Lux Barranca | K19: MARIA CAMILA ALVAREZ | L19: 3113874244 | N19: LINK-QR
A20: POSTOBON | B20: GASEOSAS LUX | C20: 4KTN5UUBRO | D20: 0 | E20: Si | F20: Si | G20: Nequi, Efectivo | I20: 860001697 | J20: Duitama / Gaseosas Lux Duitama | K20: MARIA CAMILA ALVAREZ | L20: 3113874244 | N20: LINK-QR
A21: POSTOBON | B21: GASEOSAS LUX | C21: 14YAL4TC80 | D21: 0 | E21: Si | F21: Si | G21: Nequi, Efectivo | I21: 860001697 | J21: Gaseosas Lux Monteria | K21: MARIA CAMILA ALVAREZ | L21: 3113874244 | N21: LINK-QR
A22: POSTOBON | B22: GASEOSAS LUX | C22: D8WWQSR8UA | D22: 0 | E22: Si | F22: Si | G22: Nequi, Efectivo | I22: 860001697 | J22: Lux pasto | K22: MARIA CAMILA ALVAREZ | L22: 3113874244 | N22: LINK-QR
A23: POSTOBON | B23: POSTOBON SA | C23: 2KU5V7TSPF | D23: 0 | E23: Si | F23: Si | G23: Nequi, Efectivo | I23: 890903939 | J23: Chigorodo | K23: MARIA CAMILA ALVAREZ | L23: 3113874244 | N23: LINK-QR
A24: POSTOBON | B24: INVERSIONES TC SAS - TIENDAS CERCANAS | C24: L7QZVRPNHB | D24: 0 | E24: No aplica | F24: Si | G24: Nequi, Efectivo | H24: TODOS - APPI, MENOS PAGO EN EFECTIVO | I24: 902077218 | J24: TIENDAS CERCANAS - PROYECTO KAREN | K24: KAREN GONZALEZ | L24: 305 2566574 | N24: COMPLETO
A27: COLANTA | B27: AGROCOLANTA | C27: PA80NXKNGV | D27: 0 | E27: No aplica | F27: Si | J27: LIDER PROYECTO | K27: Orion Restrepo | L27: 3245298322 | M27: 39269999155 - DAVIVIENDA | N27: LINK-QR
A28: COLANTA | B28: COLANTA | C28: X6YO81UJK6 | D28: 0 | E28: Si | F28: Si | J28: ANALISTA CANAL TRADICIONAL | K28: Anni Carolina Peña | L28: 3245298322 | M28: 396270006440 - DAVIVIENDA | N28: LINK-QR
A29: COLANTA | B29: COLANTA | C29: RPNIJ33O92 | D29: 0 | E29: Si | F29: Si | J29: ANALISTA COMERCIALIZADORAS | K29: Nasly Gamboa | L29: 3245298322 | M29: 1890447809 - DAVIVIENDA | N29: DATAFONO - LINK
A30: COLANTA | B30: Capy COLANTA | C30: 65SK8AN59R | D30: 0 | E30: Si | F30: Si | J30: CONCILIACIÓN CUENTAS BANCARIAS | K30: Yohana Velasquez | L30: 3245298322 | M30: 558246880 - BBVA | N30: DATAFONO - LINK
A31: COLANTA | B31: COLANTA BASE | C31: VY6VES3Z9R | D31: 0 | E31: Si | F31: Si | J31: ANALISTA MERCOLANTA | K31: Orion Restrepo | L31: 3245298322 | M31: 558246880 - BBVA | N31: LINK-QR
A33: SULICOR | B33: SULICOR | C33: FUE3DBCUN3 | D33: 700 QR | E33: Si | F33: Si | J33: COORINADORA DEL PROYECTO | K33: Stephania Florez Garzon | L33: 3226013052 | M33: 7123971850 - BANCOLOMBIA | N33: QR
A34: SULICOR | B34: SULICOR | C34: FUE3DBCUN3 | J34: COORINADORA DEL PROYECTO | K34: Jaime Andres Hortua | L34: 3042147377 | M34: 7123971850 - BANCOLOMBIA | N34: QR
J35: COORINADORA DEL PROYECTO | K35: Tatiana Arena | L35: 3152090217 | M35: 7123971850 - BANCOLOMBIA | N35: QR
J36: JEFE DE CARTETA | K36: Juan Villalobos | L36: 3178833600 | M36: 7123971850 - BANCOLOMBIA | N36: QR
A38: TTB | B38: TTB SAS | C38: BTJHGRLYXZ | D38: Personalizado | E38: No aplica | F38: Si | H38: Parqueaderos IDU - Terminales con Proccis
A39: TTB | B39: TTB SAS | C39: 9I8LY96BBG | D39: Personalizado | E39: No aplica | F39: Si | H39: Parqueaderos IDU - Terminales con Proccis | N39: QR
A40: TTB | B40: TTB SAS | C40: H7H258JKKS | D40: Personalizado | E40: No aplica | F40: Si | H40: Parqueaderos Terminal dentro de la terminal de transporte | N40: QR
A41: TTB | B41: TTB SAS | C41: 3NQ4U0QUHW | D41: Personalizado | E41: No aplica | F41: Si | H41: Tasa de Uso - pendientes de las APIS | N41: QR
A42: TTB | B42: TTB SAS | C42: W7NPE2OB3Q | D42: Personalizado | E42: No aplica | F42: Si | H42: Zona de Parqueo Pago - GRUPO ZPP-silice | N42: QR
A43: TTB | B43: TTB SAS | C43: 5602GZ54UZ | D43: Personalizado | E43: No aplica | F43: Si | H43: Terminal de Transporte SA - SAlitre (Proccis)
A44: TTB | B44: TTB SAS | C44: JA82FIY0Z4 | D44: Personalizado | E44: No aplica | F44: Si | H44: Parqueaderos DADEP - Proccis
A45: TTB | B45: TTB SAS | C45: 9QZSA4AZC9 | D45: Personalizado | E45: No aplica | F45: Si | H45: Inmobiliario otro negocio por implementar | N45: QR
A46: TTB | B46: TTB SAS | C46: TP4M14EW7G | D46: Personalizado | E46: No aplica | F46: Si | H46: Zona de Parqueo Pago TTSA - ZPP SILICE | N46: QR
E47: FALSE | F47: FALSE
B48: BROT - Santa marta | C48: GKPL7TUHPY | D48: Personalizado | E48: No aplica | F48: No
B49: BROT - Bogota | C49: 8H88FI19GO | D49: Personalizado | E49: No aplica | F49: No
E290: FALSE | F290: FALSE
E291: FALSE | F291: FALSE
E292: FALSE | F292: FALSE
E293: FALSE | F293: FALSE
E294: FALSE | F294: FALSE
E295: FALSE | F295: FALSE
E296: FALSE | F296: FALSE
E297: FALSE | F297: FALSE
E298: FALSE | F298: FALSE
E299: FALSE | F299: FALSE
E300: FALSE | F300: FALSE
E301: FALSE | F301: FALSE
... E1005: FALSE | F1005: FALSE

Sheet Hoja 14
A1: Merchant ID | B1: # | C1: TIPO DE DOCUMENTO | D1: # DE DOCUMENTO | E1: Ejecutivo que realiza la ACTIVACIÓN | F1: Fecha de ACTIVACIÓN | G1: Mes
A2: BGBKG6TM1S | B2: 1 | C2: CC | D2: 52272434 | E2: jeyson.salazar@bold.co | F2: 46018 | G2: 46018
A3: 2WZ9UO778I | B3: 2 | C3: CC | D3: 23965716 | E3: jeyson.salazar@bold.co | F3: 46018 | G3: 46018
A4: YQV101FLPR | B4: 3 | C4: CC | D4: 79944143 | E4: jeyson.salazar@bold.co | F4: 46071 | G4: 46071
A5: LBPEPJ7MSE | B5: 4 | C5: NIT | D5: 830000897 | E5: jeyson.salazar@bold.co | F5: 46071 | G5: 46071
A6: 5QI9HHZ4V3 | B6: 5 | C6: CC | D6: 19265207 | E6: jeyson.salazar@bold.co | F6: 46071 | G6: 46071
A7: 7IPCV8YYHF | B7: 6 | C7: NIT | D7: 901404715 | E7: jeyson.salazar@bold.co | F7: 46071 | G7: 46071
A8: AB5GBIOYD3 | B8: 7 | C8: NIT | D8: 901356768 | E8: jeyson.salazar@bold.co | F8: 46082 | G8: 46082
A9: D3G5KP2NFQ | B9: 8 | C9: CC | D9: 88177710 | E9: jeyson.salazar@bold.co | F9: 46085 | G9: 46085
A10: A51QMI6IBF | B10: 9 | C10: CC | D10: 45495943 | E10: jeyson.salazar@bold.co | F10: 46105 | G10: 46105
A11: MPCK701TYS | B11: 10 | C11: NIT | D11: 900364915 | E11: jeyson.salazar@bold.co | F11: 46083 | G11: 46083
A12: JZ148KPFMY | B12: 11 | C12: CC | D12: 52586347 | E12: jeyson.salazar@bold.co | F12: 46085 | G12: 46085
A13: KFFXQCGZG5 | B13: 12 | C13: CC | D13: 19190461 | E13: jeyson.salazar@bold.co | F13: 46087 | G13: 46087
... A84: E6D99PZ39N | B84: 83 | C84: CC | D84: 23084872 | E84: jhonatan.miranda@bold.co | F84: 46213 | G84: 46213
A85: O7E3FDTTRK | B85: 84 | C85: CC | D85: 45439188
A86: B314HHF2GP | B86: 85 | C86: CC | D86: 1143154446 | E86: jhonatan.miranda@bold.co | F86: 46170 | G86: 46170
A87: ELRKWP5N03 | B87: 86 | C87: CC | D87: 40383825 | F87: 46189 | G87: 46189
A88: C5Z5R8DFCL | B88: 87 | C88: NIT | D88: 901698718 | E88: jhonatan.miranda@bold.co | F88: 46168 | G88: 46168
A89: M36H0SD4ZM | B89: 88 | C89: NIT | D89: 901698718 | E89: jhonatan.miranda@bold.co | F89: 46167 | G89: 46167
A90: AS0QNUV4YO | B90: 89 | C90: NIT | D90: 901698718 | E90: jhonatan.miranda@bold.co | F90: 46167 | G90: 46167
A91: PF6KDB9E4S | B91: 90 | C91: CC | D91: 22590279 | E91: jhonatan.miranda@bold.co | F91: 46164 | G91: 46164
A92: 55KVWQMS70 | B92: 91 | C92: CC | D92: 79992955 | E92: claudia.romero@bold.co | F92: 46167 | G92: 46167
A93: 5VHX9ONTCS | B93: 92 | C93: CC | D93: 79992955 | E93: claudia.romero@bold.co | F93: 46167 | G93: 46167
A94: WT0KEUX9PV | B94: 93 | C94: CC | D94: 79992955 | E94: claudia.romero@bold.co | F94: 46178 | G94: 46178
A95: FBKV42BLHH | B95: 94 | C95: CC | D95: 43813759 | E95: sebastian.matthaus@bold.co | F95: 46168 | G95: 46168
A96: MK04P4VVXM | B96: 95 | C96: CC | D96: 78021697 | E96: diana.rodriguez@bold.co | F96: 46206 | G96: 46206
A97: HF284JGTQS | B97: 96 | C97: CC | D97: 32715571 | E97: jhonatan.miranda@bold.co | F97: 46168 | G97: 46168
A98: 9W51BTCJXQ | B98: 97 | C98: CC | D98: 1062288729 | F98: 46188 | G98: 46188
A99: J4GOW94UA5 | B99: 98 | C99: CC | D99: 15425093 | E99: catalina.londono@bold.co | F99: 46191 | G99: 46191
A100: KMZKO5A9TC | B100: 99 | C100: CC | D100: 1152471202 | E100: diana.rodriguez@bold.co | F100: 46195 | G100: 46195
A101: R4H9OHF68U | B101: 100 | C101: CC | D101: 43111801 | E101: juan.olarte@bold.co | F101: 46167 | G101: 46167
A102: NDV9Z2XVAL | B102: 101 | C102: CC | D102: 1023872148 | E102: claudia.romero@bold.co | F102: 46167 | G102: 46167
A103: 0ATHDV5HJG | B103: 102 | C103: CC | D103: 1023872148 | E103: claudia.romero@bold.co | F103: 46167 | G103: 46167
A104: M60342CC0N | B104: 103 | C104: CC | D104: 41621134 | E104: claudia.romero@bold.co | F104: 46167 | G104: 46167
A105: F2QWCZAYS1 | B105: 104 | C105: CC | D105: 80149352 | E105: claudia.romero@bold.co | F105: 46167 | G105: 46167
A106: 6EJQC9HPJ3 | B106: 105 | C106: CC | D106: 72046283 | E106: jhonatan.miranda@bold.co | F106: 46170 | G106: 46170
A107: X9Z0YGEO01 | B107: 106 | C107: CC | D107: 93296210 | E107: catalina.londono@bold.co | F107: 46191 | G107: 46191
A108: YQGDZR8S4O | B108: 107 | C108: CC | D108: 18417683 | E108: viviana.roman@bold.co | F108: 46172 | G108: 46172
A109: GJIRNM7WB3 | B109: 108 | C109: CC | D109: 80275593 | E109: cristian.casas@bold.co | F109: 46225 | G109: 46225
A110: ZWCQJ5QTCO | B110: 109 | C110: CC | D110: 80275593 | E110: cristian.casas@bold.co | F110: 46225 | G110: 46225
A111: FQBYSU2YCV | B111: 110 | C111: CC | D111: 43105027 | E111: juan.olarte@bold.co | F111: 46167 | G111: 46167
A112: EJACCIZF8Z | B112: 111 | C112: CC | D112: 79490174 | E112: jeyson.salazar@bold.co | F112: 46170 | G112: 46170
A113: 0C0XOP1SPP | B113: 112 | C113: CC | D113: 79490174 | E113: harold.montenegro@bold.co | F113: 46161 | G113: 46161
A114: UHT0KE9BYE | B114: 113 | C114: CC | D114: 80761836 | E114: diana.lopez@bold.co | F114: 46165 | G114: 46165
A115: 007ZCN72T9 | B115: 114 | C115: CC | D115: 901616093 | E115: jhonatan.torres@bold.co | F115: 46165 | G115: 46165
A116: 0SNB18VV5N | B116: 115 | C116: CC | D116: 901616093 | E116: jhonatan.torres@bold.co | F116: 46165 | G116: 46165
A117: 3FYFN0GLIG | B117: 116 | C117: CC | D117: 11349116 | E117: jhonatan.torres@bold.co | F117: 46167 | G117: 46167
A118: P451TOFAQ6 | B118: 117 | C118: CC | D118: 1049622911 | F118: 46187 | G118: 46187
A119: QJGJF0KSC9 | B119: 118 | C119: CC | D119: 4104664 | E119: diana.lopez@bold.co | F119: 46168 | G119: 46168
A120: E34S5Y1IJ3 | B120: 119 | C120: CC | D120: 80469631 | E120: jeyson.salazar@bold.co | F120: 46169 | G120: 46169
A121: B0CKR5HU8C | B121: 120 | C121: CC | D121: 79443701 | E121: cristian.casas@bold.co
A122: R2BWFBJS7A | B122: 121 | C122: CC | D122: 79443701 | E122: cristian.casas@bold.co
A123: F7FFIOIC5L | B123: 122 | C123: CC | D123: 1233893309 | E123: harold.montenegro@bold.co | F123: 46182 | G123: 46182
A124: 3RTLO9YSA8 | B124: 123 | C124: CC | D124: 1233893309 | E124: harold.montenegro@bold.co | F124: 46182 | G124: 46182
A125: QNJRK7P5IE | B125: 124 | C125: CC | D125: 36160992 | E125: ana.torres@bold.co | F125: 46185 | G125: 46185
A126: NMML3SQ8A3 | B126: 125 | C126: CC | D126: 36160992 | E126: ana.torres@bold.co | F126: 46185 | G126: 46185
A127: GSNEJMYDH8 | B127: 126 | C127: CC | D127: 1088730875 | F127: 46188 | G127: 46188
A128: ONVMTZ3UU3 | B128: 127 | C128: CC | D128: 1043024064 | E128: jhonatan.miranda@bold.co | F128: 46169 | G128: 46169
A129: QAIEBN8BJZ | B129: 128 | C129: CC | D129: 12265989 | E129: julieth.ariza@bold.co | F129: 46170 | G129: 46170
A130: FXSIVM0KKC | B130: 129 | C130: CC | D130: 1013659364 | E130: julieth.ariza@bold.co | F130: 46170 | G130: 46170
A131: 4JF8VIZSZC | B131: 130 | C131: CC | D131: 30396573 | E131: diana.aguirre@bold.co | F131: 46171 | G131: 46171
A132: RT6MQ8ZP70 | B132: 131 | C132: CC | D132: 30396573 | E132: diana.aguirre@bold.co | F132: 46171 | G132: 46171
A133: OZ6PMK180A | B133: 132 | C133: CC | D133: 30396573 | E133: diana.aguirre@bold.co | F133: 46171 | G133: 46171
A134: Y81VZGVMM4 | B134: 133 | C134: CC | D134: 4104664 | E134: diana.lopez@bold.co
A135: Z3C6TXV5UQ | B135: 134 | C135: NIT | D135: 901695801 | E135: julieth.ariza@bold.co | F135: 46170 | G135: 46170
A136: M4VF6ORBY6 | B136: 135 | C136: CC | D136: 22669019 | E136: paula.londono@bold.co | F136: 46189 | G136: 46189
A137: BTNNM0C2JE | B137: 136 | C137: CC | D137: 1140821685 | E137: freddy.villanueva@bold.co | F137: 46185 | G137: 46185
A138: WPQPG6AJUN | B138: 137 | C138: NIT | D138: 901621886 | E138: claudia.romero@bold.co | F138: 46175 | G138: 46175
A139: BJOD61K3LZ | B139: 138 | C139: NIT | D139: 901621886 | E139: claudia.romero@bold.co | F139: 46175 | G139: 46175
A140: 0TYYHKUHP8 | B140: 139 | C140: CC | D140: 19190461 | E140: jeyson.salazar@bold.co | F140: 46175 | G140: 46175
A141: 1TZPXSCAW9 | B141: 140 | C141: CC | D141: 19268760 | E141: julieth.ariza@bold.co | F141: 46171 | G141: 46171
A142: AVFPZGR497 | B142: 141 | C142: CC | D142: 19268760 | E142: julieth.ariza@bold.co | F142: 46171 | G142: 46171
A143: AKYRQVNJP4 | B143: 142 | C143: CC | D143: 19190461 | E143: jeyson.salazar@bold.co | F143: 46175 | G143: 46175
A144: W0KI6T6CAC | B144: 143 | C144: CC | D144: 19190461 | E144: jeyson.salazar@bold.co | F144: 46175 | G144: 46175
A145: CCT2NJJLG8 | B145: 144 | C145: CC | D145: 19190461 | E145: jeyson.salazar@bold.co | F145: 46175 | G145: 46175
A146: 2KYEXILWP9 | B146: 145 | C146: CC | D146: 19190461 | E146: jeyson.salazar@bold.co | F146: 46175 | G146: 46175
... A169: Q597QN9M85 | B169: 168 | C169: CC | D169: 16762593 | E169: andres.bolanos@bold.co | F169: 46199 | G169: 46199
A170: KNSRAGEKVQ | B170: 169 | C170: CC | D170: 41528520
A171: WS16W6RZ9X | B171: 170 | C171: CC | D171: 1088242137 | E171: carolina.reyes@bold.co | F171: 46179 | G171: 46179
A172: JC19TDEONP | B172: 171 | C172: CC | D172: 1054801253 | E172: claudia.romero@bold.co | F172: 46186 | G172: 46186
A173: 6ATTBJKOAA | B173: 172 | C173: CC | D173: 1054801253 | E173: claudia.romero@bold.co | F173: 46186 | G173: 46186
A174: 5YYB30H3ZE | B174: 173 | C174: CC | D174: 10120090 | E174: carolina.reyes@bold.co | F174: 46184 | G174: 46184
A175: PAXLJDPDPK | B175: 174 | C175: CC | D175: 10120090 | E175: carolina.reyes@bold.co | F175: 46184 | G175: 46184
A176: PJRQR3FM2X | B176: 175 | C176: CC | D176: 18463150 | E176: viviana.roman@bold.co | F176: 46184 | G176: 46184
A177: 93N7SAGDT9 | B177: 176 | C177: NIT | D177: 901388604 | E177: edinson.rodriguez@bold.co | F177: 46184 | G177: 46184
A178: Z3TIAXD3BP | B178: 177 | C178: NIT | D178: 901388604 | E178: edinson.rodriguez@bold.co | F178: 46185 | G178: 46185
A179: 1IOK8M0I1O | B179: 178 | C179: NIT | D179: 901388604 | E179: edinson.rodriguez@bold.co | F179: 46185 | G179: 46185
A180: JCUTFONNF3 | B180: 179 | C180: CC | D180: 52987088 | E180: julieth.ariza@bold.co | F180: 46183 | G180: 46183
A181: SGAL2C7RAN | B181: 180 | C181: CC | D181: 52987088 | E181: julieth.ariza@bold.co | F181: 46183 | G181: 46183
A182: YJIK6VMIU2 | B182: 181 | C182: CC | D182: 52987088 | E182: julieth.ariza@bold.co | F182: 46183 | G182: 46183
... A202: 7R2HJW0QXI | B202: 201 | C202: CC | D202: 1105785628 | E202: julieth.ariza@bold.co | F202: 46199 | G202: 46199
A203: ENVQ1TNW9V | B203: 202 | C203: CC | D203: 1099543116
A204: R3C9CE5HM0 | B204: 203 | C204: CC | D204: 79162590 | E204: jeyson.salazar@bold.co | F204: 46193 | G204: 46193
A205: W5J7NRVBSR | B205: 204 | C205: CC | D205: 1095511178 | E205: diana.rodriguez@bold.co | F205: 46190 | G205: 46190
A206: OU92VWUWUM | B206: 205 | C206: CC | D206: 1095511178 | E206: diana.rodriguez@bold.co | F206: 46190 | G206: 46190
A207: YL5WQQJVH7 | B207: 206 | C207: CC | D207: 60373383 | E207: heidy.bernal@bold.co | F207: 46190 | G207: 46190
A208: 7EPUP3JG3J | B208: 207 | C208: CC | D208: 60373383 | E208: heidy.bernal@bold.co | F208: 46190 | G208: 46190
A209: YBQG6375MI | B209: 208 | C209: CC | D209: 1098769132 | E209: alex.gil@bold.co | F209: 46190 | G209: 46190
A210: SD2OPE2NAV | B210: 209 | C210: NIT | D210: 901356373 | E210: jhonatan.torres@bold.co | F210: 46211 | G210: 46211
A211: 8ME458AW8X | B211: 210 | C211: NIT | D211: 901356373 | E211: jhonatan.torres@bold.co | F211: 46211 | G211: 46211
...

Sheet Hoja 13
C9: Mes | D9: Merchant
C10: Junio | D10: AKYRQVNJP4
C11: Junio | D11: W0KI6T6CAC
C12: Junio | D12: CCT2NJJLG8
C13: Junio | D13: 2KYEXILWP9
C14: Junio | D14: SBMHCCWQOD
C15: Junio | D15: Y8SCE9O0XJ
C16: Junio | D16: H1HL6LBM7L
C17: Junio | D17: 4WZ93LQE5J
C18: Junio | D18: FQLTRDMNR1
C19: Junio | D19: 4CKTSEVUUS
C20: Junio | D20: MBTAWWLIOK
... C124: Junio | D124: H36DBBKT4X

Sheet iNCIDENCIAS
A1: CLIENTE | B1: MERCHANT | C1: COMENTARIO

Sheet Tabla dinámica 1

Sheet MASIVOS
A1: - | B1: EXECUTIVE STRATEGIC BUSSINES | C1: NOMBRE COMERCIAL | D1: RAZÓN SOCIAL | E1: NIT | F1: OBJETO SOCIAL | G1: CIUDAD PRINCIPAL | H1: EPIC | I1: REPRESENTANTE LEGAL | J1: CONTACTO | K1: TELÉFONO | L1: CORREO | M1: EJECUTIVO - OTRO CANAL
A2: 1 | B2: LUIS CORREDOR | C2: 4/72 | D2: SERVICIOS POSTALES NACIONALES S.A. | E2: 900062917-9 | F2: Servicios de correo y mensajería expresa | G2: BOGOTÁ | H2: SÍ ESTÁ
A3: 2 | B3: LUIS CORREDOR | C3: ALGARRA | D3: GLORIA COLOMBIA S.A.S. | E3: 830507278-9 | F3: Procesamiento de leche y derivados lácteos | G3: COGUA (CUND.) | H3: SÍ ESTÁ | I3: JORGE EDUARDO RODRIGUEZ
A4: 3 | B4: LUIS CORREDOR | C4: BIG COLA | D4: AJECONTROL S.A. | E4: 830081407-1 | F4: Elaboración de bebidas no alcohólicas | G4: FUNZA (CUND.) | H4: SÍ ESTÁ | I4: AUGUSTO MAYORGA
A5: 4 | B5: LUIS CORREDOR | C5: CINE COLOMBIA | D5: CINE COLOMBIA S.A.S. | E5: 890900076-0 | F5: Exhibición de películas y gestión de teatros | G5: BOGOTÁ | H5: SÍ ESTÁ | I5: MUNIR FAHLAH ALTAHONA
A6: 5 | B6: LUIS CORREDOR | C6: CORBETA | D6: COLOMBIANA DE COMERCIO S.A. | E6: 890900943-1 | F6: Comercio al por mayor y retail (Alkosto/Ktronix) | G6: MEDELLÍN | H6: SÍ ESTÁ | I6: MANUEL SANTIAGO MEJÍA
A7: 6 | B7: LUIS CORREDOR | C7: DISLICORES | D7: DISTRIBUIDORA DE VINOS Y LICORES S.A.S. | E7: 890916575-4 | F7: Comercialización de vinos y licores | G7: MEDELLÍN | H7: SÍ ESTÁ | I7: LUZ MARÍA GONZÁLEZ
A8: 7 | B8: LUIS CORREDOR | C8: DOMESA | D8: DOMESA COLOMBIA S.A.S. | E8: 830053811-1 | F8: Mensajería, logística y servicios postales | G8: BOGOTÁ | H8: SÍ ESTÁ
A9: 8 | B9: LUIS CORREDOR | C9: DONUCOL | D9: DONUCOL S.A.S. | E9: 860508791-1 | F9: Elaboración de donuts y servicios de café | G9: BOGOTÁ | H9: OTRO CANAL | I9: MIGUEL MERINO GORRITI
A10: 9 | B10: LUIS CORREDOR | C10: INTERRAPIDISIMO | D10: INTER RAPIDÍSIMO S.A. | E10: 800251569-7 | F10: Transporte de carga masiva y mensajería | G10: BOGOTÁ | H10: SÍ ESTÁ | I10: NORMAN ALBERTO CHAPARRO
A11: 10 | B11: LUIS CORREDOR | C11: JETSMART | D11: JETSMART COLOMBIA S.A.S. | E11: 901526059 - 0 | F11: Transporte aéreo comercial de pasajeros | G11: BOGOTÁ | H11: SÍ ESTÁ
A12: 11 | B12: LUIS CORREDOR | C12: LATAM | D12: LATAM AIRLINES COLOMBIA S.A. | E12: 890704196-6 | F12: Transporte aéreo nacional e internacional | G12: BOGOTÁ | H12: SÍ ESTÁ
A13: 12 | B13: LUIS CORREDOR | C13: LG | D13: LG ELECTRONICS COLOMBIA S.A. | E13: 830013921-9 | F13: Comercio de electrodomésticos y tecnología | G13: BOGOTÁ | H13: SÍ ESTÁ
A14: 13 | B14: LUIS CORREDOR | C14: FRIMAC S.A | D14: FRIMAC S.A | E14: 800197456-2 | F14: Transporte de carga por carretera | G14: BOGOTÁ | H14: OTRO CANAL
A15: 14 | B15: LUIS CORREDOR | C15: MAC POLLO | D15: AVÍCOLA METROPOLITANA S.A. | E15: 890201881-4 | F15: Procesamiento y comercialización de pollo | G15: BUCARAMANGA | H15: OTRO CANAL
A16: 15 | B16: LUIS CORREDOR | C16: PANAMERICANA | D16: PANAMERICANA LIBRERÍA Y PAPELERÍA S.A. | E16: 830037946 - 3 | F16: Comercio de libros, útiles y tecnología | G16: BOGOTÁ | H16: SÍ ESTÁ | I16: CARLOS FEDERICO RUIZ
A17: 16 | B17: LUIS CORREDOR | C17: QUALA | D17: QUALA S.A. | E17: 860074450 - 9 | F17: Fabricación de productos de consumo masivo | G17: BOGOTÁ | H17: SÍ ESTÁ | I17: MICHAEL DE RHODES
A18: 17 | B18: LUIS CORREDOR | C18: RAMO | D18: PRODUCTOS RAMO S.A. | E18: 860003831-8 | F18: Fabricación de ponqués y snacks | G18: MOSQUERA (CUND.) | H18: SÍ ESTÁ | I18: BERNARDO SERNA GÁMEZ
A19: 18 | B19: LUIS CORREDOR | C19: RICARONDO | D19: ALIMENTOS RICARONDO S.A.S. | E19: 890315688-6 | F19: Fabricación de embutidos y productos cárnicos | G19: CALI | H19: SÍ ESTÁ | I19: RICARDO OREJUELA
A20: 19 | B20: LUIS CORREDOR | C20: TIGO-MOVISTAR | D20: UNE EPM TELECOMUNICACIONES S.A. | E20: 890905211-4 | F20: Servicios de telefonía, datos y fibra óptica | G20: MEDELLÍN | H20: SÍ ESTÁ
A21: 20 | B21: LUIS CORREDOR | C21: TOTTO | D21: NALSANI S.A.S. | E21: 800051811-2 | F21: Fabricación de maletines, ropa y accesorios | G21: BOGOTÁ | H21: OTRO CANAL | I21: JONATHAN BURSZTYN
A22: 21 | B22: LUIS CORREDOR | C22: GRUPO LITORAL | D22: GRUPO LITORAL | E22: 890926933-0 | F22: Comercio al por mayor no especializado | G22: MEDELLÍN | H22: SÍ ESTÁ
A23: 22 | B23: LUIS CORREDOR | C23: VIRGIN MOBILE | D23: VIRGIN MOBILE COLOMBIA S.A.S. | E23: 900420122 - 7 | F23: Operador móvil virtual (telefonía) | G23: BOGOTÁ | H23: SÍ ESTÁ
A24: 23 | B24: LUIS CORREDOR | C24: WOM | D24: PARTNERS TELECOM COLOMBIA S.A.S. | E24: 901328718-4 | F24: Operador de red de servicios móviles | G24: BOGOTÁ | H24: -
A25: 24 | B25: JEYSON SALAZAR | C25: ALPINA | D25: ALPINA PRODUCTOS ALIMENTICIOS S.A.S. BIC | E25: 860025900-2 | F25: Fabricación de alimentos y derivados lácteos | G25: SOPÓ (CUND.) | H25: - | I25: ERNESTO FAJARDO PINTO
A26: 25 | B26: JEYSON SALAZAR | C26: AVIANCA | D26: AVIANCA S.A. | E26: 890100577-6 | F26: Transporte aéreo de pasajeros y carga | G26: BOGOTÁ | H26: -
A27: 26 | B27: JEYSON SALAZAR | C27: BIMBO | D27: BIMBO DE COLOMBIA S.A. | E27: 830002366-0 | F27: Fabricación de productos de panadería y bollería | G27: TENJO (CUND.) | H27: - | I27: TATIANA ESTRADA
A28: 27 | B28: JEYSON SALAZAR | C28: CLARO | D28: COMUNICACIÓN CELULAR S.A. (COMCEL) | E28: 800153993-7 | F28: Servicios de telecomunicaciones móviles y fijas | G28: BOGOTÁ | H28: -
A29: 28 | B29: JEYSON SALAZAR | C29: COCA COLA | D29: COCA-COLA FEMSA COLOMBIA S.A.S. | E29: 890903955-4 | F29: Embotellado y distribución de refrescos | G29: BOGOTÁ | H29: - | I29: JOHANA CERPA BARRERA
A30: 29 | B30: JEYSON SALAZAR | C30: COLOMBINA | D30: COLOMBINA S.A. | E30: 890301884-5 | F30: Fabricación de dulces, confites y alimentos | G30: TULUÁ (VALLE) | H30: - | I30: CÉSAR CAICEDO JARAMILLO
A31: 30 | B31: JEYSON SALAZAR | C31: DHL | D31: DHL EXPRESS COLOMBIA LTDA. | E31: 860502609-4 | F31: Logística y transporte internacional express | G31: BOGOTÁ | H31: -
A32: 31 | B32: JEYSON SALAZAR | C32: DIAGEO | D32: DIAGEO COLOMBIA S.A. | E32: 830006051-4 | F32: Importación y distribución de licores premium | G32: BOGOTÁ | H32: - | I32: CARLOS ALBERTO ORTIZ
A33: 32 | B33: JEYSON SALAZAR | C33: ENVIA | D33: ENVIA COLVANES S.A.S. | E33: 800180126-5 | F33: Transporte de carga y mensajería nacional | G33: BOGOTÁ | H33: - | I33: HENRY CUEVAS GALVIS
A34: 33 | B34: JEYSON SALAZAR | C34: FEMSA | D34: COCA-COLA FEMSA COLOMBIA S.A.S. | E34: 890903955-4 | F34: Operaciones industriales de bebidas y refrescos | G34: BOGOTÁ | H34: - | I34: JULIÁN CAVIEDES
A35: 34 | B35: JEYSON SALAZAR | C35: HUEVOS KIKES | D35: INCUBADORA SANTANDER S.A. | E35: 890200735-3 | F35: Producción y comercialización de huevos | G35: BUCARAMANGA | H35: - | I35: JUAN FELIPE MONTOYA
A36: 35 | B36: JEYSON SALAZAR | C36: JUAN VALDEZ | D36: PROMOTORA DE CAFÉ COLOMBIA S.A.S. | E36: 830112398-4 | F36: Comercio minorista de café y productos derivados | G36: BOGOTÁ | H36: - | I36: CAMILA ESCOBAR CORREDOR
A37: 36 | B37: JEYSON SALAZAR | C37: MAC CENTER | D37: B&M ASOCIADOS S.A.S. | E37: 900252339-1 | F37: Distribuidor autorizado de productos Apple | G37: BOGOTÁ | H37: -
A38: 37 | B38: JEYSON SALAZAR | C38: MILLONARIOS FC | D38: AZUL Y BLANCO MILLONARIOS F.C. S.A. | E38: 900428324-4 | F38: Deporte profesional y gestión de club de fútbol | G38: BOGOTÁ | H38: -
A39: 38 | B39: JEYSON SALAZAR | C39: PARMALAT | D39: PARMALAT COLOMBIA LTDA. | E39: 830011028-5 | F39: Procesamiento de leche y derivados lácteos | G39: CHÍA (CUND.) | H39: - | I39: LAURENT COHEN
A40: 39 | B40: JEYSON SALAZAR | C40: PEPSICO | D40: PEPSICO ALIMENTOS COLOMBIA S.A.S. | E40: 800048810-7 | F40: Fabricación de snacks y bebidas (Fritolay) | G40: BOGOTÁ | H40: - | I40: SANTOS ALONSO MARTÍNEZ
A41: 40 | B41: JEYSON SALAZAR | C41: QUICK | D41: QUICK SERVICES S.A.S. | E41: 900244364-7 | F41: Prestación de servicios logísticos y tecnología | G41: BOGOTÁ | H41: - | I41: CARLOS JULIÁN CAVIEDES
A42: 41 | B42: JEYSON SALAZAR | C42: SAMSUNG | D42: SAMSUNG ELECTRONICS COLOMBIA S.A. | E42: 830027915-0 | F42: Importación y venta de tecnología | G42: BOGOTÁ | H42: -
A43: 42 | B43: JEYSON SALAZAR | C43: SERVIENTREGA | D43: SERVIENTREGA S.A. | E43: 860512330-3 | F43: Mensajería especializada y logística masiva | G43: BOGOTÁ | H43: - | I43: LUZ MARY GUERRERO
A44: 43 | B44: JEYSON SALAZAR | C44: TCC | D44: TRANSPORTADORA COMERCIAL COLOMBIA S.A. | E44: 890903047-9 | F44: Soluciones logísticas y transporte de mercancía | G44: MEDELLÍN | H44: -
A45: 44 | B45: JEYSON SALAZAR | C45: WINGO | D45: AERO REPUBLICA S.A. | E45: 800198665-2 | F45: Transporte aéreo bajo modelo de bajo costo | G45: BOGOTÁ | H45: -
A46: 45 | B46: SERGIO LONDOÑO | C46: ALQUERIA | D46: PRODUCTOS NATURALES DE LA SABANA S.A.S. | E46: 860038252-9 | F46: Procesamiento de leche y derivados lácteos | G46: CHÍA (CUND.) | H46: SÍ ESTÁ | I46: CARLOS ENRIQUE CAVALIER | J46: Elizabeth Garzón
A47: 46 | B47: SERGIO LONDOÑO | C47: ARTURO CALLE | D47: COMERCIALIZADORA ARTURO CALLE S.A.S. | E47: 900342297-2 | F47: Fabricación de calzado y ropa | G47: BOGOTÁ | H47: SÍ ESTÁ | I47: CARLOS ARTURO CALLE
A48: 47 | B48: SERGIO LONDOÑO | C48: ATLETICO NACIONAL | D48: ATLETICO NACIONAL SA | E48: 900464187-4 | F48: Club deportivo | G48: MEDELLIN | H48: -
A49: 48 | B49: SERGIO LONDOÑO | C49: OFFCORSS | D49: C.I HERMECO SAS | E49: 890924167 | F49: Fabricación de calzado y ropa para niños | G49: MEDELLIN | H49: - | I49: YANET DE JESUS LONDOÑO | J49: Lo tiene radicado Valentina Monsalve / Online Sales
A50: 49 | B50: SERGIO LONDOÑO | C50: CUEROS VELEZ | D50: CUEROS VELEZ S.A.S. | E50: 800191700-8 | F50: Fabricación de calzado y ropa | G50: MEDELLÍN | H50: - | I50: JUAN RAÚL VELEZ | J50: Lo tiene radicado Valentina Monsalve / Online Sales
A51: 50 | B51: SERGIO LONDOÑO | C51: COORDINADORA | D51: COORDINADORA MERCANTIL S.A. | E51: 890900316-7 | F51: Transporte de carga y logística de paquetes | G51: MEDELLÍN | H51: - | I51: MARÍA ELENA OBITO | J51: Lo Tiene Eddie Enterprise
A52: 51 | B52: SERGIO LONDOÑO | C52: DEP MEDELLN | D52: EL EQUIPO DEL PUEBLO S.A. | E52: 890901378-5 | F52: Actividades de clubes deportivos profesionales | G52: MEDELLÍN | H52: -
A53: 52 | B53: SERGIO LONDOÑO | C53: GASEOSAS POOL | D53: DRINKS DE COLOMBIA S.A.S. | E53: 900810414-6 | F53: Producción bebidas no alcoholicas agua y gaseosas | G53: MEDELLÍN | H53: SÍ ESTÁ | I53: JOSÉ LUIS CALDERÓN
A54: 53 | B54: SERGIO LONDOÑO | C54: GEF / P. BLANCO | D54: CRYSTAL S.A.S. | E54: 890901672-5 | F54: Fabricación de calzado y ropa | G54: MEDELLÍN | H54: - | I54: JUAN ESTEBAN VALENCIA | J54: Lo tiene radicado Carolina Estupiñan / SMB Sales
A55: 54 | B55: SERGIO LONDOÑO | C55: GRUPO NUTRESA | D55: GRUPO NUTRESA S.A. | E55: 890901662-8 | F55: Procesamientos de alimentos carnicos, bebidas, helados, pastas | G55: MEDELLÍN | H55: SÍ ESTÁ | I55: CARLOS IGNACIO GALLEGO | J55: Viviana Sepulveda | L55: lvsepulveda@serviciosnutresa.com
A56: 55 | B56: SERGIO LONDOÑO | C56: LEONISA | D56: C.I. LEONISA S.A.S. | E56: 901093142-3 | F56: Fabricación de calzado y ropa | G56: MEDELLÍN | H56: SÍ ESTÁ | I56: DIEGO JOAQUÍN URREA
A57: 56 | B57: SERGIO LONDOÑO | C57: MINISO | D57: MINISO COLOMBIA SAS | E57: 901137699-5 | F57: Comercializador retail de bienes | G57: BOGOTÁ | H57: SÍ ESTÁ | I57: DANIEL RODRIGUEZ DÍAZ | J57: Lo está trabajando JuanCa
A58: 57 | B58: SERGIO LONDOÑO | C58: NESTLE | D58: NESTLÉ DE COLOMBIA S.A. | E58: 860002130-1 | F58: Procesamientos de alimentos carnicos, bebidas, helados, pastas | G58: BOGOTÁ | H58: SÍ ESTÁ | I58: FELIPE SILVA
A59: 58 | B59: SERGIO LONDOÑO | C59: NUTRESA | D59: COMPAÑÍA NACIONAL DE CHOCOLATES S.A.S. | E59: 890900313-0 | F59: Procesamientos de alimentos carnicos, bebidas, helados, pastas | G59: MEDELLÍN | H59: SÍ ESTÁ | I59: JUAN PABLO CANO
A60: 59 | B60: SERGIO LONDOÑO | C60: NUTRESA | D60: COMPAÑIA DE GALLETAS NOEL SAS | E60: 811014994-9 | F60: Procesamientos de alimentos carnicos, bebidas, helados, pastas | G60: MEDELLÍN | H60: SÍ ESTÁ | I60: ALBERTO HOYOS LOPERA
A61: 60 | B61: SERGIO LONDOÑO | C61: NUTRESA | F61: Procesamientos de alimentos carnicos, bebidas, helados, pastas | G61: MEDELLÍN | H61: -
A62: 61 | B62: SERGIO LONDOÑO | C62: SATENA | D62: SERVICIO AEREO A TERRITORIOS NACIONALES | E62: 899999043-4 | F62: Transporte aéreo regional de pasajeros | G62: BOGOTÁ | H62: -
A63: 62 | B63: SERGIO LONDOÑO | C63: SUPERRICAS | D63: PRODUCTOS ALIMENTICIOS SUPERRICAS S.A.S. | E63: 860032227-7 | F63: Fabricación de pasabocas y snacks salados | G63: BOGOTÁ | H63: - | I63: AMANDA LUZ SILVA
A64: 63 | B64: SERGIO LONDOÑO | C64: TRENDY BY SHOP | D64: TRENDY | E64: 901374981-3 | F64: Comercializador de cosmesticos | G64: BOGOTÁ | H64: - | I64: MARIA CAMILA ORREGO | J64: Lead radicado con SMB Mauricio Herrera
A65: 64 | B65: SERGIO LONDOÑO | C65: TQ TECNOQUIMICAS | D65: TECNOQUÍMICAS S.A. | E65: 890300294-1 | F65: Producción farmacéutica y consumo masivo | G65: CALI | H65: SÍ ESTÁ | I65: JUAN MANUEL BARBERI
B66: SERGIO LONDOÑO | C66: FAMILIA | D66: FAMILIA | E66: 811042978-1 | F66: Comercializador de bienes para aseo personal y hogar | G66: MEDELLÍN | J66: Cliente referido con contactos por Jefe Katerine, contactos ya no corresponden a funcionarios de Familia. 05/03
B67: SERGIO LONDOÑO | C67: BAVARIA | D67: BAVARIA | E67: 860005224-6 | F67: Productor y comercializador de bebidads | G67: BOGOTA | J67: Lo tiene radicado Daniela Espinosa / SMB
B68: SERGIO LONDOÑO | C68: CHEVIGNON- AMERICANINO- NAFNAF | D68: COMODIN SAS | E68: 800069933-6 | F68: Fabricación de calzado y ropa | G68: MEDELLÍN | J68: Revisando nuevos contactos - 6046048891 consultado en Informa Colombia | L68: impuestos@gco.com.co
B69: SERGIO LONDOÑO | C69: TENNIS | D69: TENIS | E69: 890920043-3 | F69: Fabricación de calzado y ropa | G69: MEDELLÍN | J69: Lo tiene radicado Karen Bedoya / Online Sales
B70: SERGIO LONDOÑO | C70: AGUA BENDITA | D70: AGUA BENDITA | E70: 811044893-1 | F70: Fabricación de vestidos de baño | G70: MEDELLÍN | J70: Lo tiene radicado Karen Bedoya / Online Sales
B71: SERGIO LONDOÑO | C71: STUDIO F Y ELA | D71: STF GROUP | E71: 805003626-4 | F71: Fabricación de calzado y ropa | G71: CALI | H71: SÍ ESTÁ | I71: CARLOS ALBERTO ACOSTA | L71: servicioalcliente@studiof.com.co
B72: SERGIO LONDOÑO | C72: PEPSICO
A73: 65 | B73: JUAN SALGADO | C73: ARA | H73: -
A74: 66 | B74: JUAN SALGADO | C74: ARROZ DIANA | D74: DICORP S.A.S. | E74: 890101780-1 | F74: Trilla, empaque y comercio de arroz y granos | G74: BOGOTÁ | H74: -
A75: 67 | B75: JUAN SALGADO | C75: BOMBAS CLAUDIA | H75: -
A76: 68 | B76: JUAN SALGADO | C76: CASA LUKER | D76: LUKER S.A. | E76: 890800071-3 | F76: Procesamiento de cacao, café y derivados | G76: MANIZALES | H76: -
A77: 69 | B77: JUAN SALGADO | C77: EPSON | D77: EPSON COLOMBIA S.A.S. | E77: 830004577-9 | F77: Comercio de equipos informáticos y periféricos | G77: BOGOTÁ | H77: -
A78: 70 | B78: JUAN SALGADO | C78: SONRIA | D78: SONRÍA CLÍNICAS DENTALES S.A.S. | E78: 830003540-3 | F78: Prestación de servicios de salud oral | G78: BOGOTÁ | H78: -
A79: 71 | B79: JUAN SALGADO | C79: TERMINAL TRS BOGOTA | D79: TERMINAL DE TRANSPORTE S.A. | E79: 860029020-0 | F79: Administración de terminales de transporte | G79: BOGOTÁ | H79: -

Sheet Hoja 7
A8: GRUPO | B8: SIESA
A9: PROSALUD | B9: CROMANTIC | C9: 4000000000 | D9: Para piloto
B10: BLIND | C10: 4000000000 | D10: Para piloto
A11: COLANTA | B11: COLANTA POS | C11: 5000000000 | D11: Cerrado para OB
A12: CEBA | B12: CEBA | C12: 4000000000 | D12: Cerrado con OB
A13: MILLONARIOS | B13: MILLOS FC | C13: 1800000000 | D13: Cerrado para OB
A14: LINEA ESTETICA | B14: LINEA ESTETICA | C14: 10000000000 | D14: Para piloto
A15: MESOFOOD | B15: OMA | C15: 2000000000 | D15: Perdido Int
B16: PRESTO | C16: 2000000000 | D16: Perdido Int
A17: QUEST | B17: QUEST | C17: 30000000000 | D17: Perdido Int

Sheet Hoja 8
A1: #REF!
F2: Año | G2: Área incidencia | H2: Cantidad incidentes | I2: Cantidad TX
F3: 2025
F4: Noviembre | G4: Pagos | H4: 7 | I4: 67283
F5: Diciembre | G5: Pagos | H5: 7 | I5: 73991
F6: 2026
F7: Enero | G7: MKT | H7: 1 | I7: 68348
G8: Cuenta | H8: 1
G9: Pagos | H9: 18
G10: Técnologia | H10: 1
F11: Febrero | G11: Pagos | H11: 8 | I11: 68948

Sheet Comisiones creditos
D4: Comisiones | F4: X Millon
C5: 1 | D5: 1500000 | F5: 6000
D6: Componentes
D7: Credito | E7: Tarjeta
D8: 0.7 | E8: 0.3
D10: CREDITO
D11: META | E11: MILLONES | F11: NTR | G11: Net reveneu | H11: Pago X Millon | I11: Cost Comision
D12: 1 | E12: 150000000 | F12: 0.01 | G12: =E12*F12 -> 1500000 | H12: 7000 | I12: =H12*E13/G12 -> 0.7
E13: 150
D15: Tarjeta
C16: 1 | D16: META UND | E16: MILLONES Com
D17: 2 | E17: COMODIN
H19: Proyeccion costo ejecutvio | J19: Ntr mes | K19: Meta mes | L19: Reveneu Mes | M19: Reveneu año | N19: Payback estimado
G20: Con comision 100% | H20: 5300000 | I20: mes | J20: 0.01 | K20: 150000000 | L20: =K20*J20 -> 1500000 | M20: =L20*12 -> 18000000 | N20: =H21/M20 -> 3.5333333
H21: =H20*12 -> 63600000 | I21: año
D23: Ponderado porcentual comisional
E25: Comisiones | H25: TICKET CREDITO | I25: Oper pormedio
D26: 1 | E26: 1500000 | H26: 50000000 | I26: 3
E27: Componentes | H27: CREDITO | L27: Tarjeta #
E28: Credito | F28: Tarjeta | H28: META | I28: MILLONES | J28: # Millones | L28: META UND | M28: UNID | N28: Cupo Medio
E29: 0.7 | F29: 0.3 | H29: 1 | I29: 150000000 | J29: =I33/1000000 -> 500 | L29: 1 | M29: 2 | N29: 15
D31: Caso
H32: Caso | I32: Millones desembolsados | J32: Operaciones
E33: =H33*E29 -> 2.3333333 | F33: =L33*F29 -> 0.75 | H33: =I33/I29 -> 3.3333333 | I33: 500000000 | J33: 4 | L33: =M33/M29 -> 2.5 | M33: 5 | N33: =N29*M33 -> 75
E34: =E33+F33 -> 3.0833333 | F34: =(E34*E43)+E34 -> 3.1604167 | G34: =(E34*F43)+E34 -> 3.2375
D35: Pago comision | E35: =E34*E26 -> 4625000 | F35: =F34*D5 -> 4740625 | G35: =E26*G34 -> 4856250
D36: Diferencia | E36: 0 | F36: =F35-E35 -> 115625 | G36: =G35-F35 -> 115625
D37: Desembolso M | E37: =J29 -> 500
D38: Pague por Millon | E38: =E35/E37 -> 9250 | F38: =F35/E37 -> 9481.25 | G38: =G35/E37 -> 9712.5
D40: Acelerador
D41: Credito | E41: igual o mayo | F41: igual o mayo
E42: 4 Oper | F42: 6 Oper
D43: Acelerador | E43: 0.025 | F43: 0.05

Sheet D1
O3: UKH72XS44S
O4: QBLW9W0FGB
O5: DKFDV7RLFX
O6: SE3RYFGAJY
O7: 6RIMATJBDJ
O8: 4VETEWDH1L
O9: 6085Z6TTB7
O10: TOM95X6WAO
O11: 053AM2S3L4
O12: Q7VR1248VT
O13: Z2LOEMM4GD
O14: 79GCNR6OJO
... O26: PA80NXKNGV
D27: Julio | F27: agosto | H27: septiembre | J27: Promedios base | O27: X6YO81UJK6
D28: Valor venta | E28: Operaciones | F28: Valor venta | G28: Operaciones | H28: Valor venta | I28: Operaciones | J28: Valor venta | K28: Operaciones | L28: % Participacion | O28: RPNIJ33O92
C29: AIRLAINS | D29: 2978000000 | E29: 48160 | F29: 2697000000 | G29: 42662 | H29: 2911000000 | I29: 45678 | J29: =AVERAGE(D29,F29,H29) -> 2862000000 | K29: =AVERAGE(E29,G29,I29) -> 45500 | L29: =J29/J41 -> 0.0040532732 | O29: 65SK8AN59R
C30: AMEX | D30: 4688000000 | E30: 51763 | F30: 4441000000 | G30: 46912 | H30: 4567000000 | I30: 51256 | J30: =AVERAGE(D30,F30,H30) -> 4565333333 | K30: =AVERAGE(E30,G30,I30) -> 49977 | L30: =J30/J41 -> 0.0064655986 | O30: VY6VES3Z9R
C31: BIGPASS | D31: 1323000000 | E31: 18468 | F31: 1251000000 | G31: 16864 | H31: 1266000000 | I31: 17658 | J31: =AVERAGE(D31,F31,H31) -> 1280000000 | K31: =AVERAGE(E31,G31,I31) -> 17663.333 | L31: =J31/J41 -> 0.0018127847 | O31: FUE3DBCUN3
C32: CODENSA | D32: 2515000000 | E32: 22709 | F32: 2274000000 | G32: 20415 | H32: 2610000000 | I32: 23481 | J32: =AVERAGE(D32,F32,H32) -> 2466333333 | K32: =AVERAGE(E32,G32,I32) -> 22201.667 | L32: =J32/J41 -> 0.003492915 | O32: 5RWPJKS60Q
C33: COMPENSAR | D33: 885000000 | E33: 18086 | F33: 896000000 | G33: 18572 | H33: 936000000 | I33: 19151 | J33: =AVERAGE(D33,F33,H33) -> 9.0566667e+08 | K33: =AVERAGE(E33,G33,I33) -> 18603 | L33: =J33/J41 -> 0.0012826396 | O33: LZOL8WQC5T
C34: DAVIPLATA | D34: 286000000 | E34: 5531 | F34: 208000000 | G34: 4175 | H34: 170000000 | I34: 3406 | J34: =AVERAGE(D34,F34,H34) -> 2.2133333e+08 | K34: =AVERAGE(E34,G34,I34) -> 4370.6667 | L34: =J34/J41 -> 0.00031346068 | O34: B345I7Y21T
C35: DINNERS | D35: 843000000 | E35: 8392 | F35: 880000000 | G35: 8758 | H35: 805000000 | I35: 8559 | J35: =AVERAGE(D35,F35,H35) -> 8.4266667e+08 | K35: =AVERAGE(E35,G35,I35) -> 8569.6667 | L35: =J35/J41 -> 0.0011934166 | O35: 4M2O6VLH9I
C36: MASTERCARD | D36: 480590000000 | E36: 7362334 | F36: 412054000000 | G36: 6308439 | H36: 481715000000 | I36: 7361753 | J36: =AVERAGE(D36,F36,H36) -> 458119666667 | K36: =AVERAGE(E36,G36,I36) -> 7010842 | L36: =J36/J41 -> 0.64880649 | O36: 2JJFT1YI1D
C37: PASARELA | D37: 1738000000 | E37: 8306 | F37: 1704000000 | G37: 8027 | H37: 2254000000 | I37: 10671 | J37: =AVERAGE(D37,F37,H37) -> 1898666667 | K37: =AVERAGE(E37,G37,I37) -> 9001.3333 | L37: =J37/J41 -> 0.0026889639 | O37: JVGLF7F4WH
C38: QR | D38: 24498000000 | E38: 539301 | F38: 24452000000 | G38: 535997 | H38: 30468000000 | I38: 711998 | J38: =AVERAGE(D38,F38,H38) -> 26472666667 | K38: =AVERAGE(E38,G38,I38) -> 595765.33 | L38: =J38/J41 -> 0.037491597 | O38: UP7X07KY9P
C39: SODEXO | D39: 7972000000 | E39: 105797 | F39: 6380000000 | G39: 82887 | H39: 8343000000 | I39: 110950 | J39: =AVERAGE(D39,F39,H39) -> 7565000000 | K39: =AVERAGE(E39,G39,I39) -> 99878 | L39: =J39/J41 -> 0.010713841 | O39: VB1IU8K35P
C40: VISA | D40: 217362000000 | E40: 3265769 | F40: 184236000000 | G40: 2783489 | H40: 195092000000 | I40: 2978554 | J40: =AVERAGE(D40,F40,H40) -> 198896666667 | K40: =AVERAGE(E40,G40,I40) -> 3009270.7 | L40: =J40/J41 -> 0.28168502 | O40: M7TSQ07RQC
D41: =SUM(D27:D40) -> 745678000000 | E41: =SUM(E27:E40) -> 11454616 | F41: =SUM(F27:F40) -> 641473000000 | G41: =SUM(G27:G40) -> 9877197 | H41: =SUM(H27:H40) -> 731137000000 | I41: =SUM(I27:I40) -> 11343115 | J41: =AVERAGE(D41,F41,H41) -> 706096000000 | K41: =AVERAGE(E41,G41,I41) -> 10891643 | O41: EOIJTLOCJ1
C42: Ticket promedio | D42: =D41/E41 -> 65098.472 | F42: =F41/G41 -> 64944.842 | H42: =H41/I41 -> 64456.457 | O42: H2ENZD9KV7
C43: TPV TOTAL M PROM | D43: =AVERAGE(D41,F41,H41) -> 706096000000 | O43: 0H2W4C9ZQC
C44: Ticket Total | D44: =SUM(D42:I42)/3 -> 64833.257 | O44: TP9X2KCMWS
O45: BHNXRPS507
O46: MNFKER260S
O47: H4Y5AGH0FR
O48: 8GRBQHK7D2
O49: Y3INN0E4RT
O50: XMMWK35GCB
O51: BDMS1J57N0
O52: 2TLTH1KUEU
O53: A78Q2QG67N
O54: 6GU5HGJRI2
O55: WA14MO4JV3
O56: B2LSO7Y8ZJ
... O500: 585CKXOEHH

Sheet Cronograma
N1: FEBRERO | Q1: 2026
B2: DOMINGO | C2: LUNES | D2: MARTES | E2: MIÉRCOLES | F2: JUEVES | G2: VIERNES | H2: SÁBADO | I2: DOMINGO | J2: LUNES | K2: MARTES | L2: MIÉRCOLES | M2: JUEVES | N2: VIERNES | O2: SÁBADO | P2: DOMINGO | Q2: LUNES | R2: MARTES | S2: MIÉRCOLES | T2: JUEVES | U2: VIERNES | V2: SÁBADO | W2: DOMINGO | X2: LUNES | Y2: MARTES | Z2: MIÉRCOLES | AA2: JUEVES | AB2: VIERNES | AC2: SÁBADO | AD2: domingo | AE2: lunes | AJ2: martes
B3: 1 | C3: 2 | D3: 3 | E3: 4 | F3: 5 | G3: 6 | H3: 7 | I3: 8 | J3: 9 | K3: 10 | L3: 11 | M3: 12 | N3: 13 | O3: 14 | P3: 15 | Q3: 16 | R3: 17 | S3: 18 | T3: 19 | U3: 20 | V3: 21 | W3: 22 | X3: 23 | Y3: 24 | Z3: 25 | AA3: 26 | AB3: 27 | AC3: 28 | AD3: 1 | AE3: 2 | AJ3: 3
A4: PSTOBON
A5: Camilo | D5: ITAGUI | G5: ITAGUI
A6: Casas | I6: Villeta | J6: Villeta | K6: Villeta | L6: Mesa | M6: Mesa | N6: Madrid | O6: Madrid
A8: COLANTA
A9: Casas
A10: Camilo | J10: Antioquia | K10: Antioquia | L10: Antioquia | M10: Antioquia | N10: Antioquia | O10: Antioquia | X10: Antioquia | Y10: Antioquia | Z10: Antioquia | AA10: Antioquia | AB10: Antioquia | AC10: Antioquia
A12: COOPICREDITO
A13: Casas
A14: Camilo
N21: MARZO | Q21: 2026
B22: DOMINGO | C22: LUNES | D22: MARTES | E22: MIÉRCOLES | F22: JUEVES | G22: VIERNES | H22: SÁBADO | I22: DOMINGO | J22: LUNES | K22: MARTES | L22: MIÉRCOLES | M22: JUEVES | N22: VIERNES | O22: SÁBADO | P22: DOMINGO | Q22: LUNES | R22: MARTES | S22: MIÉRCOLES | T22: JUEVES | U22: VIERNES | V22: SÁBADO | W22: DOMINGO | X22: LUNES | Y22: MARTES | Z22: MIÉRCOLES | AA22: JUEVES | AB22: VIERNES | AC22: SÁBADO
B23: 1 | C23: 2 | D23: 3 | E23: 4 | F23: 5 | G23: 6 | H23: 7 | I23: 8 | J23: 9 | K23: 10 | L23: 11 | M23: 12 | N23: 13 | O23: 14 | P23: 15 | Q23: 16 | R23: 17 | S23: 18 | T23: 19 | U23: 20 | V23: 21 | W23: 22 | X23: 23 | Y23: 24 | Z23: 25 | AA23: 26 | AB23: 27 | AC23: 28
A24: POSTOBON
A25: Camilo | C25: CORREO | G25: Itagui | J25: CORREO | M25: Acomp. Ruta postobon | N25: Rio negro | P25: Malambo | Q25: Malambo | R25: Malambo | S25: Malambo | T25: Malambo | U25: Malambo | V25: Malambo | X25: CORREO
A26: Casas | C26: siberia | D26: sevillana | P26: Malambo | Q26: Malambo | R26: Malambo | S26: Malambo | T26: Malambo | U26: Malambo | V26: Malambo
A28: COLANTA
A29: Casas
A30: Camilo
A32: COOPICREDITO
A33: Casas
A34: Camilo
N38: ABRIL | Q38: 2026
B39: MIÉRCOLES | C39: JUEVES | D39: VIERNES | E39: SÁBADO | F39: DOMINGO | G39: LUNES | H39: MARTES | I39: MIÉRCOLES | J39: JUEVES | K39: VIERNES | L39: SÁBADO | M39: DOMINGO | N39: LUNES | O39: MARTES | P39: MIÉRCOLES | Q39: JUEVES | R39: VIERNES | S39: SÁBADO | T39: DOMINGO | U39: LUNES | V39: MARTES | W39: MIÉRCOLES | X39: JUEVES | Y39: VIERNES | Z39: SÁBADO | AA39: DOMINGO | AB39: LUNES | AC39: MARTES | AD39: MIÉRCOLES | AE39: JUEVES
B40: 1 | C40: 2 | D40: 3 | E40: 4 | F40: 5 | G40: 6 | H40: 7 | I40: 8 | J40: 9 | K40: 10 | L40: 11 | M40: 12 | N40: 13 | O40: 14 | P40: 15 | Q40: 16 | R40: 17 | S40: 18 | T40: 19 | U40: 20 | V40: 21 | W40: 22 | X40: 23 | Y40: 24 | Z40: 25 | AA40: 26 | AB40: 27 | AC40: 28 | AD40: 29 | AE40: 30
A41: POSTOBON
A42: Camilo | H42: La Dorada | K42: Mariquita | U42: Villavicencio
A43: Casas | G43: Zipaquira | I43: Fusagasuga | K43: Caqueza | N43: Ricaute | P43: Ibague | U43: Villavicencio | W43: Granada
A45: COLANTA
A46: Casas | AB46: Medellin | AC46: Medellin | AD46: Medellin | AE46: Sabaneta
A47: Camilo | AB47: Medellin | AC47: Medellin | AD47: Medellin | AE47: Sabaneta
A49: COOPICREDITO
A50: Casas
A51: Camilo
A52: Juank | H52: Bogota | I52: Bogota | J52: Bogota | Q52: Bogota
A54: Capacitaciones Na
A55: Juank | U55: Barranquilla | V55: Barranquilla | W55: Bogota | AC55: Bogota
N58: MAYO | Q58: 2026
B59: VIERNES | C59: SÁBADO | D59: DOMINGO | E59: LUNES | F59: MARTES | G59: MIÉRCOLES | H59: JUEVES | I59: VIERNES | J59: SÁBADO | K59: DOMINGO | L59: LUNES | M59: MARTES | N59: MIÉRCOLES | O59: JUEVES | P59: VIERNES | Q59: SÁBADO | R59: DOMINGO | S59: LUNES | T59: MARTES | U59: MIÉRCOLES | V59: JUEVES | W59: VIERNES | X59: SÁBADO | Y59: DOMINGO | Z59: LUNES | AA59: MARTES | AB59: MIÉRCOLES | AC59: JUEVES | AD59: VIERNES | AE59: SÁBADO | AJ59: DOMINGO
B60: 1 | C60: 2 | D60: 3 | E60: 4 | F60: 5 | G60: 6 | H60: 7 | I60: 8 | J60: 9 | K60: 10 | L60: 11 | M60: 12 | N60: 13 | O60: 14 | P60: 15 | Q60: 16 | R60: 17 | S60: 18 | T60: 19 | U60: 20 | V60: 21 | W60: 22 | X60: 23 | Y60: 24 | Z60: 25 | AA60: 26 | AB60: 27 | AC60: 28 | AD60: 29 | AE60: 30 | AJ60: 31
A61: POSTOBON
A62: Camilo | E62: Santa Marta | G62: Aracataca | I62: Bosconia | L62: Valledupar | N62: Fonseca | P62: Maicao | T62: Riohacha
A63: Casas | E63: Saldaña | G63: Neiva | I63: Garzon | L63: Florencia
A64: Juank | V64: Medellin
A66: COLANTA
A67: Casas | E67: , | F67: Medellin | G67: Medellin | H67: Sabaneta | I67: Sabaneta | J67: Sabaneta | Z67: Sabaneta | AA67: Sabaneta | AB67: Sabaneta | AC67: Sabaneta | AD67: Sabaneta | AE67: Sabaneta
A68: Camilo | Z68: Sabaneta | AA68: Sabaneta | AB68: Sabaneta | AC68: Sabaneta | AD68: Sabaneta | AE68: Sabaneta
A70: COOPICREDITO
A71: Casas
A72: Camilo
A73: Capacitaciones Na | I73: Medellin
A74: Juank | F74: Bogota | H74: Medellin | I74: PROPUESTA Clientes contrato de suministro | M74: Cali | O74: Bucaramanga | U74: Bogota | Z74: Bucaramanga | AA74: Cucuta | AD74: CALI
N79: JUNIO | Q79: 2026
B80: LUNES | C80: MARTES | D80: MIÉRCOLES | E80: JUEVES | F80: VIERNES | G80: SÁBADO | H80: DOMINGO | I80: LUNES | J80: MARTES | K80: MIÉRCOLES | L80: JUEVES | M80: VIERNES | N80: SÁBADO | O80: DOMINGO | P80: LUNES | Q80: MARTES | R80: MIÉRCOLES | S80: JUEVES | T80: VIERNES | U80: SÁBADO | V80: DOMINGO | W80: LUNES | X80: MARTES | Y80: MIÉRCOLES | Z80: JUEVES | AA80: VIERNES | AB80: SÁBADO | AC80: DOMINGO | AD80: LUNES | AE80: MARTES
B81: 1 | C81: 2 | D81: 3 | E81: 4 | F81: 5 | G81: 6 | H81: 7 | I81: 8 | J81: 9 | K81: 10 | L81: 11 | M81: 12 | N81: 13 | O81: 14 | P81: 15 | Q81: 16 | R81: 17 | S81: 18 | T81: 19 | U81: 20 | V81: 21 | W81: 22 | X81: 23 | Y81: 24 | Z81: 25 | AA81: 26 | AB81: 27 | AC81: 28 | AD81: 29 | AE81: 30
A82: POSTOBON
A83: Camilo | B83: Ocaña | D83: Aguachica | F83: El Banco | J83: Magangue | K83: Sincelejo | W83: desplazamiento | X83: Puertoberrio | Y83: Barrancabermeja | AA83: Pinchote | AC83: retorno
A84: Casas | B84: Pasto | D84: Ipiales | F84: Tumaco | J84: Chiquinquira | L84: Barbosa
A86: COLANTA
A87: Casas
A88: Camilo
A90: COOPICREDITO
A91: Casas | Q91: COOPICREDITO | R91: COOPICREDITO | S91: COOPICREDITO | T91: COOPICREDITO | U91: COOPICREDITO
A92: Camilo | Q92: COOPICREDITO | R92: COOPICREDITO | S92: COOPICREDITO | T92: COOPICREDITO | U92: COOPICREDITO
A94: POLLO ANDINO
A95: Casas | Q95: POLLO ANDINO | R95: POLLO ANDINO | S95: POLLO ANDINO | T95: POLLO ANDINO | U95: POLLO ANDINO
A96: Camilo
A98: Capacitaciones Na
A99: Juank
N104: JULIO | Q104: 2026
B105: MIÉRCOLES | C105: JUEVES | D105: VIERNES | E105: SÁBADO | F105: DOMINGO | G105: LUNES | H105: MARTES | I105: MIÉRCOLES | J105: JUEVES | K105: VIERNES | L105: SÁBADO | M105: DOMINGO | N105: LUNES | O105: MARTES | P105: MIÉRCOLES | Q105: JUEVES | R105: VIERNES | S105: SÁBADO | T105: DOMINGO | U105: LUNES | V105: MARTES | W105: MIÉRCOLES | X105: JUEVES | Y105: VIERNES | Z105: SÁBADO | AA105: DOMINGO | AB105: LUNES | AC105: MARTES | AD105: MIÉRCOLES | AE105: JUEVES | AJ105: VIERNES
B106: 1 | C106: 2 | D106: 3 | E106: 4 | F106: 5 | G106: 6 | H106: 7 | I106: 8 | J106: 9 | K106: 10 | L106: 11 | M106: 12 | N106: 13 | O106: 14 | P106: 15 | Q106: 16 | R106: 17 | S106: 18 | T106: 19 | U106: 20 | V106: 21 | W106: 22 | X106: 23 | Y106: 24 | Z106: 25 | AA106: 26 | AB106: 27 | AC106: 28 | AD106: 29 | AE106: 30 | AJ106: 31
A107: POSTOBON
A108: Camilo | H108: desplazamiento | I108: Caucasia | K108: Monteria | O108: desplazamiento | P108: Stf Antioquia | Q108: Chigorodo
A109: Casas | AB109: Tunja | AD109: Duitama | AJ109: Yopal
A111: COLANTA
A112: Casas
A113: Camilo
A115: COOPICREDITO
A116: Casas
A117: Camilo | C117: MEDELLIN
N118: S
A119: POLLO ANDINO
A120: Casas
A121: Camilo
A123: SULICOR
A124: Casas | D124: Bogota | J124: Bogota | K124: Funza
A125: Camilo | AB125: Bogota
N126: AGOSTO | Q126: 2026
B127: SÁBADO | C127: DOMINGO | D127: LUNES | E127: MARTES | F127: MIÉRCOLES | G127: JUEVES | H127: VIERNES | I127: SÁBADO | J127: DOMINGO | K127: LUNES | L127: MARTES | M127: MIÉRCOLES | N127: JUEVES | O127: VIERNES | P127: SÁBADO | Q127: DOMINGO | R127: LUNES | S127: MARTES | T127: MIÉRCOLES | U127: JUEVES | V127: VIERNES | W127: SÁBADO | X127: DOMINGO | Y127: LUNES | Z127: MARTES | AA127: MIÉRCOLES | AB127: JUEVES | AC127: VIERNES | AD127: SÁBADO | AE127: DOMINGO
B128: 1 | C128: 2 | D128: 3 | E128: 4 | F128: 5 | G128: 6 | H128: 7 | I128: 8 | J128: 9 | K128: 10 | L128: 11 | M128: 12 | N128: 13 | O128: 14 | P128: 15 | Q128: 16 | R128: 17 | S128: 18 | T128: 19 | U128: 20 | V128: 21 | W128: 22 | X128: 23 | Y128: 24 | Z128: 25 | AA128: 26 | AB128: 27 | AC128: 28 | AD128: 29 | AE128: 30 | AG128: 650 | AH128: Bonos
A129: POSTOBON | B129: Yopal | AG129: 100 | AH129: SAB
A130: Camilo | N130: San Andres | AG130: 150 | AH130: SAB
A131: Casas | N131: San Andres | AG131: 100 | AH131: MED
AG132: 100 | AH132: MED
A133: COLANTA | AG133: 200 | AH133: MED
A134: Casas | Y134: Bog recap planta.
A135: Camilo | Y135: MEDELLIN
...

Sheet METAS
A1: “ | S1: Me a pagar
A2: Mes | B2: agosto | C2: septiembre | D2: octubre | E2: noviembre | F2: diciembre | G2: enero | H2: febrero | I2: marzo | J2: abril | K2: mayo | L2: junio | M2: julio | N2: agosto | O2: septiembre | P2: octubre | Q2: noviembre | R2: TPV | S2: junio | T2: mes de cliente
A3: marzo | B3: 140000000 | R3: junio | S3: m0 | T3: junio
A4: abril | B4: 140000000 | C4: 140000000 | R4: junio | S4: m1 | T4: mayo
A5: mayo | B5: 140000000 | C5: 140000000 | D5: 140000000 | R5: junio | S5: m2 | T5: abril
A6: junio | B6: 140000000 | C6: 140000000 | D6: 140000000 | E6: 140000000 | R6: junio | S6: m3 | T6: marzo
A7: julio | B7: 140000000 | C7: 140000000 | D7: 140000000 | E7: 140000000 | F7: 140000000 | R7: junio | S7: m4 | T7: febrero
A8: agosto | B8: 100000000 | C8: 140000000 | D8: 140000000 | E8: 140000000 | F8: 140000000 | G8: 140000000 | R8: junio | S8: m5 | T8: enero
A9: septiembre | C9: 100000000 | D9: 140000000 | E9: 140000000 | F9: 140000000 | G9: 140000000 | H9: 140000000
A10: octubre | D10: 100000000 | E10: 140000000 | F10: 140000000 | G10: 140000000 | H10: 140000000 | I10: 140000000
A11: noviembre | E11: 100000000 | F11: 140000000 | G11: 140000000 | H11: 140000000 | I11: 140000000 | J11: 140000000
A12: diciembre | F12: 100000000 | G12: 140000000 | H12: 140000000 | I12: 140000000 | J12: 140000000 | K12: 140000000
A13: enero | G13: 100000000 | H13: 140000000 | I13: 140000000 | J13: 140000000 | K13: 140000000 | L13: 140000000
A14: febrero | H14: 100000000 | I14: 140000000 | J14: 140000000 | K14: 140000000 | L14: 140000000 | M14: 140000000
A15: marzo | I15: 100000000 | J15: 140000000 | K15: 140000000 | L15: 140000000 | M15: 140000000 | N15: 140000000
A16: Abril | J16: 100000000 | K16: 140000000 | L16: 140000000 | M16: 140000000 | N16: 140000000 | O16: 140000000
A17: Mayo | K17: 100000000 | L17: 140000000 | M17: 140000000 | N17: 140000000 | O17: 140000000 | P17: 140000000
A18: Junio | L18: 100000000 | M18: 140000000 | N18: 147000000 | O18: 147000000 | P18: 147000000 | Q18: 147000000
A19: Julio | M19: 105000000 | N19: 147000000 | O19: 147000000 | P19: 147000000 | Q19: 147000000
A20: Agosto | N20: 105000000 | O20: 147000000 | P20: 147000000 | Q20: 147000000
A21: septiembre | O21: 105000000 | P21: 147000000 | Q21: 147000000
A22: octubre | P22: 105000000 | Q22: 147000000
A23: noviembre | Q23: 105000000
A26: TOTAL META TPV | B26: =SUM(B3:B25) -> 800000000 | C26: =SUM(C3:C25) -> 800000000 | D26: =SUM(D3:D25) -> 800000000 | E26: =SUM(E3:E25) -> 800000000 | F26: =SUM(F3:F25) -> 800000000 | G26: =SUM(G3:G25) -> 800000000 | H26: =SUM(H3:H25) -> 800000000 | I26: =SUM(I3:I25) -> 800000000 | ... Q26: =SUM(Q3:Q25) -> 840000000
A27: META NTR VARIACIÓN CURVA | B27: 5200000 | C27: 5200000 | D27: 5200000 | E27: 5200000 | F27: 5200000 | G27: 5200000 | H27: 5200000 | I27: 5200000 | J27: 5200000 | K27: 5200000 | L27: 5200000 | M27: 5200000 | N27: 5200000 | O27: 5200000 | P27: 5200000 | Q27: 5200000
A28: 0.3 | B28: M0 = 100M | C28: M0 = 100M | D28: M0 = 100M | E28: M0 = 100M | F28: M0 = 100M | G28: M0 = 100M | H28: M0 = 100M | I28: M0 = 100M | J28: M0 = 100M | K28: M0 = 100M | L28: M0 = 100M | M28: M0 = 100M | N28: M0 = 100M | O28: M0 = 100M | P28: M0 = 100M | Q28: M0 = 100M
A29: 0.4
A30: NTR Objetivo Promedio | B30: =B27/B26 -> 0.0065 | C30: =C27/C26 -> 0.0065 | D30: =D27/D26 -> 0.0065 | E30: =E27/E26 -> 0.0065 | F30: =F27/F26 -> 0.0065 | G30: =G27/G26 -> 0.0065 | H30: =H27/H26 -> 0.0065 | I30: =I27/I26 -> 0.0065 | ... Q30: =Q27/Q26 -> 0.0061904762
A34: META IMPLEMENTADORES
B35: POSTOBON | C35: COLNATA | D35: Adicional implementan META
A36: META CUALITATIVA 40% DE LA META: | B36: iMPLEMENTACION Malambo al 100% | C36: iMPLEMENTACION MERCOLANTA SEDE
B37: iMPLEMENTACION Malambo al 100% | C37: iMPLEMENTACION MERCOLANTA SEDE | E37: IMPLEMENTACIONES AGOSTO OK 100%
A40: META CUANTITATIVA 60% DE LA META:
O41: julio | P41: agosto | Q41: septiembre
O42: m0 | P42: m0 | Q42: m0
A43: Julio | F43: COSTO QR $60 | O43: m1 | P43: m1
O44: m2
A45: CRISTIAN | E45: NTR PARA LIQUIDAR AGOSTO | H45: CRISTIAN
A46: COLANTA %1 QR | D46: JULIO .98% NTR | H46: AGOSTO NR META
A47: TPV | B47: NTR | C47: NR | H47: =C48+C52+C56+C60 -> 52160000
A48: 1000000000 | B48: 0.009 | C48: =A48*B48 -> 9000000
A50: POSTOBON 600 FEE | D50: JULIO .16% NTR
A51: TPV | B51: NTR | C51: NR
A52: 18000000000 | B52: 0.0015 | C52: =A52*B52 -> 27000000
A54: SULICOR 700 FEE | D54: JULIO .26% NTR
A55: TPV | B55: NTR | C55: NR
A56: 1100000000 | B56: 0.0016 | C56: =A56*B56 -> 1760000
A58: TTB Personalizada | D58: JULIO 2,33% NTR
A59: TPV | B59: NTR | C59: NR
A60: 1200000000 | B60: 0.012 | C60: =A60*B60 -> 14400000
A62: CAMILO | E62: NTR PARA LIQUIDAR AGOSTO | H62: CAMILO
A63: COLANTA %1 QR | D63: JULIO .98% NTR | H63: AGOSTO NR META
A64: TPV | B64: NTR | C64: NR | H64: =C65+C69 -> 36000000
A65: 1000000000 | B65: 0.009 | C65: =A65*B65 -> 9000000
A67: POSTOBON 600 FEE | D67: JULIO .16% NTR
A68: TPV | B68: NTR | C68: NR
A69: 18000000000 | B69: 0.0015 | C69: =A69*B69 -> 27000000
A71: MASIVOS PARA LIQUIDAR
A73: GASEOSAS LUX | B73: QBLW9W0FGB
A74: GASEOSAS LUX SAS | B74: DKFDV7RLFX
A75: GASEOSAS LUX SAS | B75: SE3RYFGAJY
A76: POSTOBON SA | B76: 6RIMATJBDJ
A77: POSTOBON SA | B77: 4VETEWDH1L
A78: POSTOBON SA | B78: 6085Z6TTB7
A79: POSTOBON SA | B79: TOM95X6WAO
A80: POSTOBON SA | B80: 053AM2S3L4
A81: POSTOBON SA | B81: Q7VR1248VT
A82: POSTOBON SA | B82: XIE3ZA3Y14
A83: POSTOBON SA | B83: Z2LOEMM4GD
A84: POSTOBON SA | B84: 79GCNR6OJO
... A114: TTB SAS | B114: TP4M14EW7G
